Workbook

Sheet README
A1: Zumi Holdings — Q3 2025 Group Ledger
A3: ## Your assignment
A4: You are the new analyst. The CFO dropped this raw export on your desk Friday at 5pm and wants a clean Q3 P&L by Monday 9am. By brand. By month. With variance commentary.
A6: ## What you have
A7: Tab 'Raw_Ledger' has 1,200+ entries pulled from three different systems (POS, accounting, payroll). It is messy on purpose. Real exports are.
A8: Tab 'Chart_of_Accounts' is the official mapping. Use it.
A9: Tab 'FX_Rates' has month-end NGN rates for USD and GHS entries.
A10: Tab 'Bank_Statements' is the source of truth for cash. Reconcile against the ledger.
A12: ## What you must build
A13: 1. 'Cleaned' tab. One row per transaction, NGN-normalized, properly categorized. Use formulas, not paste-values.
A14: 2. 'PL_By_Brand_Month' tab. Revenue / COGS / Gross Profit / Opex / EBITDA. Brand x Month matrix.
A15: 3. 'Reconciliation' tab. Reconcile Cleaned to Bank_Statements. Flag every variance over NGN 50,000.
... A24: When you write commentary, write like you mean it. Short sentences. Specific numbers. No fluff. The CEO hates fluff.

Sheet tbl_Bank
A1: Month | B1: Bank_Account | C1: Currency | D1: Total_Inflow | E1: Total_Outflow | F1: Net_Movement | G1: Notes
A2: 2025-07 | B2: GTB - NGN Operating | C2: NGN | D2: 132840000 | E2: -98120000 | F2: 34720000
A3: 2025-07 | B3: GTB - USD Domiciliary | C3: USD | D3: 14820 | E3: -1460 | F3: 13360 | G3: Logistics + ads
A4: 2025-08 | B4: GTB - NGN Operating | C4: NGN | D4: 141980000 | E4: -106410000 | F4: 35570000 | G4: Includes duplicate vendor pmt
A5: 2025-08 | B5: GTB - USD Domiciliary | C5: USD | D5: 16320 | E5: -1640 | F5: 14680
A6: 2025-09 | B6: GTB - NGN Operating | C6: NGN | D6: 152410000 | E6: -109840000 | F6: 42570000
A7: 2025-09 | B7: GTB - USD Domiciliary | C7: USD | D7: 18940 | E7: -1710 | F7: 17230

Sheet tbl_Accounts
A1: Account_Code | B1: Account_Name | C1: Type | D1: PL_Bucket
A2: 4000 | B2: Order Revenue | C2: Revenue | D2: Revenue
A3: 4010 | B3: Subscription Revenue | C3: Revenue | D3: Revenue
A4: 4020 | B4: Logistics Contract Revenue | C4: Revenue | D4: Revenue
A5: 4900 | B5: Refunds & Chargebacks | C5: Revenue | D5: Revenue
A6: 5000 | B6: Food Cost | C6: COGS | D6: COGS
A7: 5010 | B7: Inventory Purchases | C7: COGS | D7: COGS
A8: 5020 | B8: Packaging | C8: COGS | D8: COGS
A9: 5030 | B9: Fuel & Vehicle | C9: COGS | D9: COGS
A10: 5040 | B10: Rider Payouts | C10: COGS | D10: COGS
A11: 5050 | B11: Aggregator Commission | C11: COGS | D11: COGS
A12: 6000 | B12: Salaries & Wages | C12: Opex | D12: Opex
... A21: 6900 | B21: Other / Uncategorized | C21: Opex | D21: Opex

Sheet tbl_FX
A1: Month | B1: Currency | C1: Rate_to_NGN | D1: Key
A2: 2025-07 | B2: NGN | C2: 1 | D2: =tbl_FX[[#This Row],[Month]] & tbl_FX[[#This Row],[Currency]] -> 2025-07NGN
A3: 2025-07 | B3: USD | C3: 1530 | D3: =tbl_FX[[#This Row],[Month]] & tbl_FX[[#This Row],[Currency]] -> 2025-07USD
A4: 2025-07 | B4: GHS | C4: 102 | D4: =tbl_FX[[#This Row],[Month]] & tbl_FX[[#This Row],[Currency]] -> 2025-07GHS
A5: 2025-08 | B5: NGN | C5: 1 | D5: =tbl_FX[[#This Row],[Month]] & tbl_FX[[#This Row],[Currency]] -> 2025-08NGN
A6: 2025-08 | B6: USD | C6: 1572 | D6: =tbl_FX[[#This Row],[Month]] & tbl_FX[[#This Row],[Currency]] -> 2025-08USD
A7: 2025-08 | B7: GHS | C7: 99 | D7: =tbl_FX[[#This Row],[Month]] & tbl_FX[[#This Row],[Currency]] -> 2025-08GHS
A8: 2025-09 | B8: NGN | C8: 1 | D8: =tbl_FX[[#This Row],[Month]] & tbl_FX[[#This Row],[Currency]] -> 2025-09NGN
A9: 2025-09 | B9: USD | C9: 1611 | D9: =tbl_FX[[#This Row],[Month]] & tbl_FX[[#This Row],[Currency]] -> 2025-09USD
A10: 2025-09 | B10: GHS | C10: 96 | D10: =tbl_FX[[#This Row],[Month]] & tbl_FX[[#This Row],[Currency]] -> 2025-09GHS

Sheet tbl_Ledger
A1: Txn_ID | B1: Date | C1: Source_System | D1: Brand | E1: Channel | F1: Account_Code | G1: Account_Name | H1: Description | I1: Currency | J1: Amount | K1: Vendor_or_Customer | L1: Reference | M1: Notes | N1: Month | O1: Key | P1: Rate_to_NGN | Q1: Adjusted_Amount_NGN | R1: Account_Type | S1: PL_Bucket | T1: Clean_Amount
A2: T101434 | B2: 45839 | C2: QuickBooks | D2: Zumi Logistics | F2: 5030 | G2: Fuel & Vehicle | H2: Fuel top-up — invoice missing date | I2: NGN | J2: -240000 | K2: NNPC Retail | L2: BILL-NODATE | N2: =TEXT(tbl_Ledger[[#This Row],[Date]],"yyyy-mm") -> 2025-07 | O2: =TEXT(tbl_Ledger[[#This Row],[Date]],"yyyy-mm") & TRIM(tbl_Ledger[[#This Row],[Currency]]) -> 2025-07NGN | P2: =_xlfn.XLOOKUP(tbl_Ledger[[#This Row],[Key]], tbl_FX[Key], tbl_FX[Rate_to_NGN]) -> 1 | Q2: =IF(tbl_Ledger[[#This Row],[Account_Type]]="Expense",-ABS(tbl_Ledger[[#This Row],[Amount]]*tbl_Ledger[[#This Row],[Rate_to_NGN]]),tbl_Ledger[[#This Row],[Amount]]*tbl_Ledger[[#This Row],[Rate_to_NGN]]) -> -240000 | R2: =_xlfn.XLOOKUP(tbl_Ledger[[#This Row],[Account_Code]], tbl_Accounts[Account_Code], tbl_Accounts[Type]) -> COGS | S2: =_xlfn.XLOOKUP(tbl_Ledger[[#This Row],[Account_Code]], tbl_Accounts[Account_Code], tbl_Accounts[PL_Bucket]) -> COGS | T2: =IF(AND(S2="Revenue",F2<>4900),ABS(Q2),-ABS(Q2)) -> -240000
A3: T100001 | B3: 45839 | C3: POS-Square | D3: Zumi Eats | E3: Mobile App | F3: 4000 | G3: Order Revenue | H3: Mobile App daily settlement 2025-07-01 | I3: NGN | J3: 27600 | L3: INV-20250701-MOB | N3: =TEXT(tbl_Ledger[[#This Row],[Date]],"yyyy-mm") -> 2025-07 | O3: =TEXT(tbl_Ledger[[#This Row],[Date]],"yyyy-mm") & TRIM(tbl_Ledger[[#This Row],[Currency]]) -> 2025-07NGN | P3: =_xlfn.XLOOKUP(tbl_Ledger[[#This Row],[Key]], tbl_FX[Key], tbl_FX[Rate_to_NGN]) -> 1 | Q3: =IF(tbl_Ledger[[#This Row],[Account_Type]]="Expense",-ABS(tbl_Ledger[[#This Row],[Amount]]*tbl_Ledger[[#This Row],[Rate_to_NGN]]),tbl_Ledger[[#This Row],[Amount]]*tbl_Ledger[[#This Row],[Rate_to_NGN]]) -> 27600 | R3: =_xlfn.XLOOKUP(tbl_Ledger[[#This Row],[Account_Code]], tbl_Accounts[Account_Code], tbl_Accounts[Type]) -> Revenue | S3: =_xlfn.XLOOKUP(tbl_Ledger[[#This Row],[Account_Code]], tbl_Accounts[Account_Code], tbl_Accounts[PL_Bucket]) -> Revenue | T3: =IF(AND(S3="Revenue",F3<>4900),ABS(Q3),-ABS(Q3)) -> 27600
A4: T100002 | B4: 45839 | C4: POS-Square | D4: Zumi Eats | E4: Website | F4: 4000 | G4: Order Revenue | H4: Website daily settlement 2025-07-01 | I4: NGN | J4: 29800 | L4: INV-20250701-WEB | N4: =TEXT(tbl_Ledger[[#This Row],[Date]],"yyyy-mm") -> 2025-07 | O4: =TEXT(tbl_Ledger[[#This Row],[Date]],"yyyy-mm") & TRIM(tbl_Ledger[[#This Row],[Currency]]) -> 2025-07NGN | P4: =_xlfn.XLOOKUP(tbl_Ledger[[#This Row],[Key]], tbl_FX[Key], tbl_FX[Rate_to_NGN]) -> 1 | Q4: =IF(tbl_Ledger[[#This Row],[Account_Type]]="Expense",-ABS(tbl_Ledger[[#This Row],[Amount]]*tbl_Ledger[[#This Row],[Rate_to_NGN]]),tbl_Ledger[[#This Row],[Amount]]*tbl_Ledger[[#This Row],[Rate_to_NGN]]) -> 29800 | R4: =_xlfn.XLOOKUP(tbl_Ledger[[#This Row],[Account_Code]], tbl_Accounts[Account_Code], tbl_Accounts[Type]) -> Revenue | S4: =_xlfn.XLOOKUP(tbl_Ledger[[#This Row],[Account_Code]], tbl_Accounts[Account_Code], tbl_Accounts[PL_Bucket]) -> Revenue | T4: =IF(AND(S4="Revenue",F4<>4900),ABS(Q4),-ABS(Q4)) -> 29800
A5: T100003 | B5: 45839 | C5: POS-Square | D5: Zumi Eats | E5: Aggregator-Glovo | F5: 4000 | G5: Order Revenue | H5: Aggregator-Glovo daily settlement 2025-07-01 | I5: NGN | J5: 29500 | L5: INV-20250701-AGG | N5: =TEXT(tbl_Ledger[[#This Row],[Date]],"yyyy-mm") -> 2025-07 | O5: =TEXT(tbl_Ledger[[#This Row],[Date]],"yyyy-mm") & TRIM(tbl_Ledger[[#This Row],[Currency]]) -> 2025-07NGN | P5: =_xlfn.XLOOKUP(tbl_Ledger[[#This Row],[Key]], tbl_FX[Key], tbl_FX[Rate_to_NGN]) -> 1 | Q5: =IF(tbl_Ledger[[#This Row],[Account_Type]]="Expense",-ABS(tbl_Ledger[[#This Row],[Amount]]*tbl_Ledger[[#This Row],[Rate_to_NGN]]),tbl_Ledger[[#This Row],[Amount]]*tbl_Ledger[[#This Row],[Rate_to_NGN]]) -> 29500 | R5: =_xlfn.XLOOKUP(tbl_Ledger[[#This Row],[Account_Code]], tbl_Accounts[Account_Code], tbl_Accounts[Type]) -> Revenue | S5: =_xlfn.XLOOKUP(tbl_Ledger[[#This Row],[Account_Code]], tbl_Accounts[Account_Code], tbl_Accounts[PL_Bucket]) -> Revenue | T5: =IF(AND(S5="Revenue",F5<>4900),ABS(Q5),-ABS(Q5)) -> 29500
A6: T100004 | B6: 45839 | C6: POS-Square | D6: Zumi Eats | E6: Walk-in | F6: 4000 | G6: Order Revenue | H6: Walk-in daily settlement 2025-07-01 | I6: NGN | J6: 31400 | L6: INV-20250701-WAL | N6: =TEXT(tbl_Ledger[[#This Row],[Date]],"yyyy-mm") -> 2025-07 | O6: =TEXT(tbl_Ledger[[#This Row],[Date]],"yyyy-mm") & TRIM(tbl_Ledger[[#This Row],[Currency]]) -> 2025-07NGN | P6: =_xlfn.XLOOKUP(tbl_Ledger[[#This Row],[Key]], tbl_FX[Key], tbl_FX[Rate_to_NGN]) -> 1 | Q6: =IF(tbl_Ledger[[#This Row],[Account_Type]]="Expense",-ABS(tbl_Ledger[[#This Row],[Amount]]*tbl_Ledger[[#This Row],[Rate_to_NGN]]),tbl_Ledger[[#This Row],[Amount]]*tbl_Ledger[[#This Row],[Rate_to_NGN]]) -> 31400 | R6: =_xlfn.XLOOKUP(tbl_Ledger[[#This Row],[Account_Code]], tbl_Accounts[Account_Code], tbl_Accounts[Type]) -> Revenue | S6: =_xlfn.XLOOKUP(tbl_Ledger[[#This Row],[Account_Code]], tbl_Accounts[Account_Code], tbl_Accounts[PL_Bucket]) -> Revenue | T6: =IF(AND(S6="Revenue",F6<>4900),ABS(Q6),-ABS(Q6)) -> 31400
A7: T100005 | B7: 45839 | C7: POS-Square | D7: Zumi Mart | E7: POS-Lekki | F7: 4000 | G7: Order Revenue | H7: POS-Lekki daily settlement 2025-07-01 | I7: NGN | J7: 48600 | L7: INV-20250701-POS | N7: =TEXT(tbl_Ledger[[#This Row],[Date]],"yyyy-mm") -> 2025-07 | O7: =TEXT(tbl_Ledger[[#This Row],[Date]],"yyyy-mm") & TRIM(tbl_Ledger[[#This Row],[Currency]]) -> 2025-07NGN | P7: =_xlfn.XLOOKUP(tbl_Ledger[[#This Row],[Key]], tbl_FX[Key], tbl_FX[Rate_to_NGN]) -> 1 | Q7: =IF(tbl_Ledger[[#This Row],[Account_Type]]="Expense",-ABS(tbl_Ledger[[#This Row],[Amount]]*tbl_Ledger[[#This Row],[Rate_to_NGN]]),tbl_Ledger[[#This Row],[Amount]]*tbl_Ledger[[#This Row],[Rate_to_NGN]]) -> 48600 | R7: =_xlfn.XLOOKUP(tbl_Ledger[[#This Row],[Account_Code]], tbl_Accounts[Account_Code], tbl_Accounts[Type]) -> Revenue | S7: =_xlfn.XLOOKUP(tbl_Ledger[[#This Row],[Account_Code]], tbl_Accounts[Account_Code], tbl_Accounts[PL_Bucket]) -> Revenue | T7: =IF(AND(S7="Revenue",F7<>4900),ABS(Q7),-ABS(Q7)) -> 48600
A8: T100006 | B8: 45839 | C8: POS-Square | D8: Zumi Mart | E8: POS-VI | F8: 4000 | G8: Order Revenue | H8: POS-VI daily settlement 2025-07-01 | I8: NGN | J8: 45700 | L8: INV-20250701-POS | N8: =TEXT(tbl_Ledger[[#This Row],[Date]],"yyyy-mm") -> 2025-07 | O8: =TEXT(tbl_Ledger[[#This Row],[Date]],"yyyy-mm") & TRIM(tbl_Ledger[[#This Row],[Currency]]) -> 2025-07NGN | P8: =_xlfn.XLOOKUP(tbl_Ledger[[#This Row],[Key]], tbl_FX[Key], tbl_FX[Rate_to_NGN]) -> 1 | Q8: =IF(tbl_Ledger[[#This Row],[Account_Type]]="Expense",-ABS(tbl_Ledger[[#This Row],[Amount]]*tbl_Ledger[[#This Row],[Rate_to_NGN]]),tbl_Ledger[[#This Row],[Amount]]*tbl_Ledger[[#This Row],[Rate_to_NGN]]) -> 45700 | R8: =_xlfn.XLOOKUP(tbl_Ledger[[#This Row],[Account_Code]], tbl_Accounts[Account_Code], tbl_Accounts[Type]) -> Revenue | S8: =_xlfn.XLOOKUP(tbl_Ledger[[#This Row],[Account_Code]], tbl_Accounts[Account_Code], tbl_Accounts[PL_Bucket]) -> Revenue | T8: =IF(AND(S8="Revenue",F8<>4900),ABS(Q8),-ABS(Q8)) -> 45700
A9: T100007 | B9: 45839 | C9: POS-Square | D9: Zumi Mart | E9: POS-Ikeja | F9: 4000 | G9: Order Revenue | H9: POS-Ikeja daily settlement 2025-07-01 | I9: NGN | J9: 46300 | L9: INV-20250701-POS | N9: =TEXT(tbl_Ledger[[#This Row],[Date]],"yyyy-mm") -> 2025-07 | O9: =TEXT(tbl_Ledger[[#This Row],[Date]],"yyyy-mm") & TRIM(tbl_Ledger[[#This Row],[Currency]]) -> 2025-07NGN | P9: =_xlfn.XLOOKUP(tbl_Ledger[[#This Row],[Key]], tbl_FX[Key], tbl_FX[Rate_to_NGN]) -> 1 | Q9: =IF(tbl_Ledger[[#This Row],[Account_Type]]="Expense",-ABS(tbl_Ledger[[#This Row],[Amount]]*tbl_Ledger[[#This Row],[Rate_to_NGN]]),tbl_Ledger[[#This Row],[Amount]]*tbl_Ledger[[#This Row],[Rate_to_NGN]]) -> 46300 | R9: =_xlfn.XLOOKUP(tbl_Ledger[[#This Row],[Account_Code]], tbl_Accounts[Account_Code], tbl_Accounts[Type]) -> Revenue | S9: =_xlfn.XLOOKUP(tbl_Ledger[[#This Row],[Account_Code]], tbl_Accounts[Account_Code], tbl_Accounts[PL_Bucket]) -> Revenue | T9: =IF(AND(S9="Revenue",F9<>4900),ABS(Q9),-ABS(Q9)) -> 46300
A10: T100008 | B10: 45839 | C10: POS-Square | D10: Zumi Mart | E10: Online | F10: 4000 | G10: Order Revenue | H10: Online daily settlement 2025-07-01 | I10: NGN | J10: 49000 | L10: INV-20250701-ONL | N10: =TEXT(tbl_Ledger[[#This Row],[Date]],"yyyy-mm") -> 2025-07 | O10: =TEXT(tbl_Ledger[[#This Row],[Date]],"yyyy-mm") & TRIM(tbl_Ledger[[#This Row],[Currency]]) -> 2025-07NGN | P10: =_xlfn.XLOOKUP(tbl_Ledger[[#This Row],[Key]], tbl_FX[Key], tbl_FX[Rate_to_NGN]) -> 1 | Q10: =IF(tbl_Ledger[[#This Row],[Account_Type]]="Expense",-ABS(tbl_Ledger[[#This Row],[Amount]]*tbl_Ledger[[#This Row],[Rate_to_NGN]]),tbl_Ledger[[#This Row],[Amount]]*tbl_Ledger[[#This Row],[Rate_to_NGN]]) -> 49000 | R10: =_xlfn.XLOOKUP(tbl_Ledger[[#This Row],[Account_Code]], tbl_Accounts[Account_Code], tbl_Accounts[Type]) -> Revenue | S10: =_xlfn.XLOOKUP(tbl_Ledger[[#This Row],[Account_Code]], tbl_Accounts[Account_Code], tbl_Accounts[PL_Bucket]) -> Revenue | T10: =IF(AND(S10="Revenue",F10<>4900),ABS(Q10),-ABS(Q10)) -> 49000
A11: T100009 | B11: 45839 | C11: NetSuite | D11: Zumi Logistics | E11: Contract-Dangote | F11: 4020 | G11: Logistics Contract Revenue | H11: Contract-Dangote daily settlement 2025-07-01 | I11: NGN | J11: 41900 | K11: Dangote | L11: INV-20250701-CON | N11: =TEXT(tbl_Ledger[[#This Row],[Date]],"yyyy-mm") -> 2025-07 | O11: =TEXT(tbl_Ledger[[#This Row],[Date]],"yyyy-mm") & TRIM(tbl_Ledger[[#This Row],[Currency]]) -> 2025-07NGN | P11: =_xlfn.XLOOKUP(tbl_Ledger[[#This Row],[Key]], tbl_FX[Key], tbl_FX[Rate_to_NGN]) -> 1 | Q11: =IF(tbl_Ledger[[#This Row],[Account_Type]]="Expense",-ABS(tbl_Ledger[[#This Row],[Amount]]*tbl_Ledger[[#This Row],[Rate_to_NGN]]),tbl_Ledger[[#This Row],[Amount]]*tbl_Ledger[[#This Row],[Rate_to_NGN]]) -> 41900 | R11: =_xlfn.XLOOKUP(tbl_Ledger[[#This Row],[Account_Code]], tbl_Accounts[Account_Code], tbl_Accounts[Type]) -> Revenue | S11: =_xlfn.XLOOKUP(tbl_Ledger[[#This Row],[Account_Code]], tbl_Accounts[Account_Code], tbl_Accounts[PL_Bucket]) -> Revenue | T11: =IF(AND(S11="Revenue",F11<>4900),ABS(Q11),-ABS(Q11)) -> 41900
A12: T100010 | B12: 45839 | C12: NetSuite | D12: Zumi Logistics | E12: Contract-MTN | F12: 4020 | G12: Logistics Contract Revenue | H12: Contract-MTN daily settlement 2025-07-01 | I12: USD | J12: 28.04 | K12: MTN | L12: INV-20250701-CON | N12: =TEXT(tbl_Ledger[[#This Row],[Date]],"yyyy-mm") -> 2025-07 | O12: =TEXT(tbl_Ledger[[#This Row],[Date]],"yyyy-mm") & TRIM(tbl_Ledger[[#This Row],[Currency]]) -> 2025-07USD | P12: =_xlfn.XLOOKUP(tbl_Ledger[[#This Row],[Key]], tbl_FX[Key], tbl_FX[Rate_to_NGN]) -> 1530 | Q12: =IF(tbl_Ledger[[#This Row],[Account_Type]]="Expense",-ABS(tbl_Ledger[[#This Row],[Amount]]*tbl_Ledger[[#This Row],[Rate_to_NGN]]),tbl_Ledger[[#This Row],[Amount]]*tbl_Ledger[[#This Row],[Rate_to_NGN]]) -> 42901.2 | R12: =_xlfn.XLOOKUP(tbl_Ledger[[#This Row],[Account_Code]], tbl_Accounts[Account_Code], tbl_Accounts[Type]) -> Revenue | S12: =_xlfn.XLOOKUP(tbl_Ledger[[#This Row],[Account_Code]], tbl_Accounts[Account_Code], tbl_Accounts[PL_Bucket]) -> Revenue | T12: =IF(AND(S12="Revenue",F12<>4900),ABS(Q12),-ABS(Q12)) -> 42901.2
A13: T100011 | B13: 45839 | C13: NetSuite | D13: Zumi Logistics | E13: Contract-Flutterwave | F13: 4020 | G13: Logistics Contract Revenue | H13: Contract-Flutterwave daily settlement 2025-07-01 | I13: USD | J13: 28.95 | K13: Flutterwave | L13: INV-20250701-CON | N13: =TEXT(tbl_Ledger[[#This Row],[Date]],"yyyy-mm") -> 2025-07 | O13: =TEXT(tbl_Ledger[[#This Row],[Date]],"yyyy-mm") & TRIM(tbl_Ledger[[#This Row],[Currency]]) -> 2025-07USD | P13: =_xlfn.XLOOKUP(tbl_Ledger[[#This Row],[Key]], tbl_FX[Key], tbl_FX[Rate_to_NGN]) -> 1530 | Q13: =IF(tbl_Ledger[[#This Row],[Account_Type]]="Expense",-ABS(tbl_Ledger[[#This Row],[Amount]]*tbl_Ledger[[#This Row],[Rate_to_NGN]]),tbl_Ledger[[#This Row],[Amount]]*tbl_Ledger[[#This Row],[Rate_to_NGN]]) -> 44293.5 | R13: =_xlfn.XLOOKUP(tbl_Ledger[[#This Row],[Account_Code]], tbl_Accounts[Account_Code], tbl_Accounts[Type]) -> Revenue | S13: =_xlfn.XLOOKUP(tbl_Ledger[[#This Row],[Account_Code]], tbl_Accounts[Account_Code], tbl_Accounts[PL_Bucket]) -> Revenue | T13: =IF(AND(S13="Revenue",F13<>4900),ABS(Q13),-ABS(Q13)) -> 44293.5
A14: T100012 | B14: 45839 | C14: NetSuite | D14: Zumi Logistics | E14: Spot-Market | F14: 4020 | G14: Logistics Contract Revenue | H14: Spot-Market daily settlement 2025-07-01 | I14: NGN | J14: 47700 | L14: INV-20250701-SPO | N14: =TEXT(tbl_Ledger[[#This Row],[Date]],"yyyy-mm") -> 2025-07 | O14: =TEXT(tbl_Ledger[[#This Row],[Date]],"yyyy-mm") & TRIM(tbl_Ledger[[#This Row],[Currency]]) -> 2025-07NGN | P14: =_xlfn.XLOOKUP(tbl_Ledger[[#This Row],[Key]], tbl_FX[Key], tbl_FX[Rate_to_NGN]) -> 1 | Q14: =IF(tbl_Ledger[[#This Row],[Account_Type]]="Expense",-ABS(tbl_Ledger[[#This Row],[Amount]]*tbl_Ledger[[#This Row],[Rate_to_NGN]]),tbl_Ledger[[#This Row],[Amount]]*tbl_Ledger[[#This Row],[Rate_to_NGN]]) -> 47700 | R14: =_xlfn.XLOOKUP(tbl_Ledger[[#This Row],[Account_Code]], tbl_Accounts[Account_Code], tbl_Accounts[Type]) -> Revenue | S14: =_xlfn.XLOOKUP(tbl_Ledger[[#This Row],[Account_Code]], tbl_Accounts[Account_Code], tbl_Accounts[PL_Bucket]) -> Revenue | T14: =IF(AND(S14="Revenue",F14<>4900),ABS(Q14),-ABS(Q14)) -> 47700
A15: T101249 | B15: 45839 | C15: QuickBooks | D15: Zumi Mart | F15: 5010 | G15: Inventory Purchases | H15: Distell Wholesale invoice 2025-07 | I15: NGN | J15: -1691000 | K15: Distell Wholesale | L15: BILL-13747 | N15: =TEXT(tbl_Ledger[[#This Row],[Date]],"yyyy-mm") -> 2025-07 | O15: =TEXT(tbl_Ledger[[#This Row],[Date]],"yyyy-mm") & TRIM(tbl_Ledger[[#This Row],[Currency]]) -> 2025-07NGN | P15: =_xlfn.XLOOKUP(tbl_Ledger[[#This Row],[Key]], tbl_FX[Key], tbl_FX[Rate_to_NGN]) -> 1 | Q15: =IF(tbl_Ledger[[#This Row],[Account_Type]]="Expense",-ABS(tbl_Ledger[[#This Row],[Amount]]*tbl_Ledger[[#This Row],[Rate_to_NGN]]),tbl_Ledger[[#This Row],[Amount]]*tbl_Ledger[[#This Row],[Rate_to_NGN]]) -> -1691000 | R15: =_xlfn.XLOOKUP(tbl_Ledger[[#This Row],[Account_Code]], tbl_Accounts[Account_Code], tbl_Accounts[Type]) -> COGS | S15: =_xlfn.XLOOKUP(tbl_Ledger[[#This Row],[Account_Code]], tbl_Accounts[Account_Code], tbl_Accounts[PL_Bucket]) -> COGS | T15: =IF(AND(S15="Revenue",F15<>4900),ABS(Q15),-ABS(Q15)) -> -1691000
A16: T101265 | B16: 45839 | C16: QuickBooks | D16: Zumi Logistics | F16: 5030 | G16: Fuel & Vehicle | H16: NNPC Retail invoice 2025-07 | I16: NGN | J16: -522000 | K16: NNPC Retail | L16: BILL-18601 | N16: =TEXT(tbl_Ledger[[#This Row],[Date]],"yyyy-mm") -> 2025-07 | O16: =TEXT(tbl_Ledger[[#This Row],[Date]],"yyyy-mm") & TRIM(tbl_Ledger[[#This Row],[Currency]]) -> 2025-07NGN | P16: =_xlfn.XLOOKUP(tbl_Ledger[[#This Row],[Key]], tbl_FX[Key], tbl_FX[Rate_to_NGN]) -> 1 | Q16: =IF(tbl_Ledger[[#This Row],[Account_Type]]="Expense",-ABS(tbl_Ledger[[#This Row],[Amount]]*tbl_Ledger[[#This Row],[Rate_to_NGN]]),tbl_Ledger[[#This Row],[Amount]]*tbl_Ledger[[#This Row],[Rate_to_NGN]]) -> -522000 | R16: =_xlfn.XLOOKUP(tbl_Ledger[[#This Row],[Account_Code]], tbl_Accounts[Account_Code], tbl_Accounts[Type]) -> COGS | S16: =_xlfn.XLOOKUP(tbl_Ledger[[#This Row],[Account_Code]], tbl_Accounts[Account_Code], tbl_Accounts[PL_Bucket]) -> COGS | T16: =IF(AND(S16="Revenue",F16<>4900),ABS(Q16),-ABS(Q16)) -> -522000
A17: T100013 | B17: 45840 | C17: POS-Square | D17: Zumi Eats | E17: Mobile App | F17: 4000 | G17: Order Revenue | H17: Mobile App daily settlement 2025-07-02 | I17: NGN | J17: 31500 | L17: INV-20250702-MOB | N17: =TEXT(tbl_Ledger[[#This Row],[Date]],"yyyy-mm") -> 2025-07 | O17: =TEXT(tbl_Ledger[[#This Row],[Date]],"yyyy-mm") & TRIM(tbl_Ledger[[#This Row],[Currency]]) -> 2025-07NGN | P17: =_xlfn.XLOOKUP(tbl_Ledger[[#This Row],[Key]], tbl_FX[Key], tbl_FX[Rate_to_NGN]) -> 1 | Q17: =IF(tbl_Ledger[[#This Row],[Account_Type]]="Expense",-ABS(tbl_Ledger[[#This Row],[Amount]]*tbl_Ledger[[#This Row],[Rate_to_NGN]]),tbl_Ledger[[#This Row],[Amount]]*tbl_Ledger[[#This Row],[Rate_to_NGN]]) -> 31500 | R17: =_xlfn.XLOOKUP(tbl_Ledger[[#This Row],[Account_Code]], tbl_Accounts[Account_Code], tbl_Accounts[Type]) -> Revenue | S17: =_xlfn.XLOOKUP(tbl_Ledger[[#This Row],[Account_Code]], tbl_Accounts[Account_Code], tbl_Accounts[PL_Bucket]) -> Revenue | T17: =IF(AND(S17="Revenue",F17<>4900),ABS(Q17),-ABS(Q17)) -> 31500
A18: T100014 | B18: 45840 | C18: POS-Square | D18: Zumi Eats | E18: Website | F18: 4000 | G18: Order Revenue | H18: Website daily settlement 2025-07-02 | I18: NGN | J18: 27600 | L18: INV-20250702-WEB | N18: =TEXT(tbl_Ledger[[#This Row],[Date]],"yyyy-mm") -> 2025-07 | O18: =TEXT(tbl_Ledger[[#This Row],[Date]],"yyyy-mm") & TRIM(tbl_Ledger[[#This Row],[Currency]]) -> 2025-07NGN | P18: =_xlfn.XLOOKUP(tbl_Ledger[[#This Row],[Key]], tbl_FX[Key], tbl_FX[Rate_to_NGN]) -> 1 | Q18: =IF(tbl_Ledger[[#This Row],[Account_Type]]="Expense",-ABS(tbl_Ledger[[#This Row],[Amount]]*tbl_Ledger[[#This Row],[Rate_to_NGN]]),tbl_Ledger[[#This Row],[Amount]]*tbl_Ledger[[#This Row],[Rate_to_NGN]]) -> 27600 | R18: =_xlfn.XLOOKUP(tbl_Ledger[[#This Row],[Account_Code]], tbl_Accounts[Account_Code], tbl_Accounts[Type]) -> Revenue | S18: =_xlfn.XLOOKUP(tbl_Ledger[[#This Row],[Account_Code]], tbl_Accounts[Account_Code], tbl_Accounts[PL_Bucket]) -> Revenue | T18: =IF(AND(S18="Revenue",F18<>4900),ABS(Q18),-ABS(Q18)) -> 27600
A19: T100015 | B19: 45840 | C19: POS-Square | D19: Zumi Eats | E19: Aggregator-Glovo | F19: 4000 | G19: Order Revenue | H19: Aggregator-Glovo daily settlement 2025-07-02 | I19: NGN | J19: 27700 | L19: INV-20250702-AGG | N19: =TEXT(tbl_Ledger[[#This Row],[Date]],"yyyy-mm") -> 2025-07 | O19: =TEXT(tbl_Ledger[[#This Row],[Date]],"yyyy-mm") & TRIM(tbl_Ledger[[#This Row],[Currency]]) -> 2025-07NGN | P19: =_xlfn.XLOOKUP(tbl_Ledger[[#This Row],[Key]], tbl_FX[Key], tbl_FX[Rate_to_NGN]) -> 1 | Q19: =IF(tbl_Ledger[[#This Row],[Account_Type]]="Expense",-ABS(tbl_Ledger[[#This Row],[Amount]]*tbl_Ledger[[#This Row],[Rate_to_NGN]]),tbl_Ledger[[#This Row],[Amount]]*tbl_Ledger[[#This Row],[Rate_to_NGN]]) -> 27700 | R19: =_xlfn.XLOOKUP(tbl_Ledger[[#This Row],[Account_Code]], tbl_Accounts[Account_Code], tbl_Accounts[Type]) -> Revenue | S19: =_xlfn.XLOOKUP(tbl_Ledger[[#This Row],[Account_Code]], tbl_Accounts[Account_Code], tbl_Accounts[PL_Bucket]) -> Revenue | T19: =IF(AND(S19="Revenue",F19<>4900),ABS(Q19),-ABS(Q19)) -> 27700
A20: T100016 | B20: 45840 | C20: POS-Square | D20: Zumi Eats | E20: Aggregator-Bolt | F20: 4000 | G20: Order Revenue | H20: Aggregator-Bolt daily settlement 2025-07-02 | I20: NGN | J20: 27000 | L20: INV-20250702-AGG | N20: =TEXT(tbl_Ledger[[#This Row],[Date]],"yyyy-mm") -> 2025-07 | O20: =TEXT(tbl_Ledger[[#This Row],[Date]],"yyyy-mm") & TRIM(tbl_Ledger[[#This Row],[Currency]]) -> 2025-07NGN | P20: =_xlfn.XLOOKUP(tbl_Ledger[[#This Row],[Key]], tbl_FX[Key], tbl_FX[Rate_to_NGN]) -> 1 | Q20: =IF(tbl_Ledger[[#This Row],[Account_Type]]="Expense",-ABS(tbl_Ledger[[#This Row],[Amount]]*tbl_Ledger[[#This Row],[Rate_to_NGN]]),tbl_Ledger[[#This Row],[Amount]]*tbl_Ledger[[#This Row],[Rate_to_NGN]]) -> 27000 | R20: =_xlfn.XLOOKUP(tbl_Ledger[[#This Row],[Account_Code]], tbl_Accounts[Account_Code], tbl_Accounts[Type]) -> Revenue | S20: =_xlfn.XLOOKUP(tbl_Ledger[[#This Row],[Account_Code]], tbl_Accounts[Account_Code], tbl_Accounts[PL_Bucket]) -> Revenue | T20: =IF(AND(S20="Revenue",F20<>4900),ABS(Q20),-ABS(Q20)) -> 27000
A21: T100017 | B21: 45840 | C21: POS-Square | D21: Zumi Mart | E21: POS-Lekki | F21: 4000 | G21: Order Revenue | H21: POS-Lekki daily settlement 2025-07-02 | I21: NGN | J21: 50900 | L21: INV-20250702-POS | N21: =TEXT(tbl_Ledger[[#This Row],[Date]],"yyyy-mm") -> 2025-07 | O21: =TEXT(tbl_Ledger[[#This Row],[Date]],"yyyy-mm") & TRIM(tbl_Ledger[[#This Row],[Currency]]) -> 2025-07NGN | P21: =_xlfn.XLOOKUP(tbl_Ledger[[#This Row],[Key]], tbl_FX[Key], tbl_FX[Rate_to_NGN]) -> 1 | Q21: =IF(tbl_Ledger[[#This Row],[Account_Type]]="Expense",-ABS(tbl_Ledger[[#This Row],[Amount]]*tbl_Ledger[[#This Row],[Rate_to_NGN]]),tbl_Ledger[[#This Row],[Amount]]*tbl_Ledger[[#This Row],[Rate_to_NGN]]) -> 50900 | R21: =_xlfn.XLOOKUP(tbl_Ledger[[#This Row],[Account_Code]], tbl_Accounts[Account_Code], tbl_Accounts[Type]) -> Revenue | S21: =_xlfn.XLOOKUP(tbl_Ledger[[#This Row],[Account_Code]], tbl_Accounts[Account_Code], tbl_Accounts[PL_Bucket]) -> Revenue | T21: =IF(AND(S21="Revenue",F21<>4900),ABS(Q21),-ABS(Q21)) -> 50900
A22: T100018 | B22: 45840 | C22: POS-Square | D22: Zumi Mart | E22: POS-VI | F22: 4000 | G22: Order Revenue | H22: POS-VI daily settlement 2025-07-02 | I22: NGN | J22: 45500 | L22: INV-20250702-POS | N22: =TEXT(tbl_Ledger[[#This Row],[Date]],"yyyy-mm") -> 2025-07 | O22: =TEXT(tbl_Ledger[[#This Row],[Date]],"yyyy-mm") & TRIM(tbl_Ledger[[#This Row],[Currency]]) -> 2025-07NGN | P22: =_xlfn.XLOOKUP(tbl_Ledger[[#This Row],[Key]], tbl_FX[Key], tbl_FX[Rate_to_NGN]) -> 1 | Q22: =IF(tbl_Ledger[[#This Row],[Account_Type]]="Expense",-ABS(tbl_Ledger[[#This Row],[Amount]]*tbl_Ledger[[#This Row],[Rate_to_NGN]]),tbl_Ledger[[#This Row],[Amount]]*tbl_Ledger[[#This Row],[Rate_to_NGN]]) -> 45500 | R22: =_xlfn.XLOOKUP(tbl_Ledger[[#This Row],[Account_Code]], tbl_Accounts[Account_Code], tbl_Accounts[Type]) -> Revenue | S22: =_xlfn.XLOOKUP(tbl_Ledger[[#This Row],[Account_Code]], tbl_Accounts[Account_Code], tbl_Accounts[PL_Bucket]) -> Revenue | T22: =IF(AND(S22="Revenue",F22<>4900),ABS(Q22),-ABS(Q22)) -> 45500
A23: T100019 | B23: 45840 | C23: POS-Square | D23: Zumi Mart | E23: POS-Ikeja | F23: 4000 | G23: Order Revenue | H23: POS-Ikeja daily settlement 2025-07-02 | I23: NGN | J23: 48200 | L23: INV-20250702-POS | N23: =TEXT(tbl_Ledger[[#This Row],[Date]],"yyyy-mm") -> 2025-07 | O23: =TEXT(tbl_Ledger[[#This Row],[Date]],"yyyy-mm") & TRIM(tbl_Ledger[[#This Row],[Currency]]) -> 2025-07NGN | P23: =_xlfn.XLOOKUP(tbl_Ledger[[#This Row],[Key]], tbl_FX[Key], tbl_FX[Rate_to_NGN]) -> 1 | Q23: =IF(tbl_Ledger[[#This Row],[Account_Type]]="Expense",-ABS(tbl_Ledger[[#This Row],[Amount]]*tbl_Ledger[[#This Row],[Rate_to_NGN]]),tbl_Ledger[[#This Row],[Amount]]*tbl_Ledger[[#This Row],[Rate_to_NGN]]) -> 48200 | R23: =_xlfn.XLOOKUP(tbl_Ledger[[#This Row],[Account_Code]], tbl_Accounts[Account_Code], tbl_Accounts[Type]) -> Revenue | S23: =_xlfn.XLOOKUP(tbl_Ledger[[#This Row],[Account_Code]], tbl_Accounts[Account_Code], tbl_Accounts[PL_Bucket]) -> Revenue | T23: =IF(AND(S23="Revenue",F23<>4900),ABS(Q23),-ABS(Q23)) -> 48200
A24: T100020 | B24: 45840 | C24: POS-Square | D24: Zumi Mart | E24: POS-Abuja | F24: 4000 | G24: Order Revenue | H24: POS-Abuja daily settlement 2025-07-02 | I24: NGN | J24: 46900 | L24: INV-20250702-POS | N24: =TEXT(tbl_Ledger[[#This Row],[Date]],"yyyy-mm") -> 2025-07 | O24: =TEXT(tbl_Ledger[[#This Row],[Date]],"yyyy-mm") & TRIM(tbl_Ledger[[#This Row],[Currency]]) -> 2025-07NGN | P24: =_xlfn.XLOOKUP(tbl_Ledger[[#This Row],[Key]], tbl_FX[Key], tbl_FX[Rate_to_NGN]) -> 1 | Q24: =IF(tbl_Ledger[[#This Row],[Account_Type]]="Expense",-ABS(tbl_Ledger[[#This Row],[Amount]]*tbl_Ledger[[#This Row],[Rate_to_NGN]]),tbl_Ledger[[#This Row],[Amount]]*tbl_Ledger[[#This Row],[Rate_to_NGN]]) -> 46900 | R24: =_xlfn.XLOOKUP(tbl_Ledger[[#This Row],[Account_Code]], tbl_Accounts[Account_Code], tbl_Accounts[Type]) -> Revenue | S24: =_xlfn.XLOOKUP(tbl_Ledger[[#This Row],[Account_Code]], tbl_Accounts[Account_Code], tbl_Accounts[PL_Bucket]) -> Revenue | T24: =IF(AND(S24="Revenue",F24<>4900),ABS(Q24),-ABS(Q24)) -> 46900
A25: T100021 | B25: 45840 | C25: POS-Square | D25: Zumi Mart | E25: Online | F25: 4000 | G25: Order Revenue | H25: Online daily settlement 2025-07-02 | I25: NGN | J25: 49800 | L25: INV-20250702-ONL | N25: =TEXT(tbl_Ledger[[#This Row],[Date]],"yyyy-mm") -> 2025-07 | O25: =TEXT(tbl_Ledger[[#This Row],[Date]],"yyyy-mm") & TRIM(tbl_Ledger[[#This Row],[Currency]]) -> 2025-07NGN | P25: =_xlfn.XLOOKUP(tbl_Ledger[[#This Row],[Key]], tbl_FX[Key], tbl_FX[Rate_to_NGN]) -> 1 | Q25: =IF(tbl_Ledger[[#This Row],[Account_Type]]="Expense",-ABS(tbl_Ledger[[#This Row],[Amount]]*tbl_Ledger[[#This Row],[Rate_to_NGN]]),tbl_Ledger[[#This Row],[Amount]]*tbl_Ledger[[#This Row],[Rate_to_NGN]]) -> 49800 | R25: =_xlfn.XLOOKUP(tbl_Ledger[[#This Row],[Account_Code]], tbl_Accounts[Account_Code], tbl_Accounts[Type]) -> Revenue | S25: =_xlfn.XLOOKUP(tbl_Ledger[[#This Row],[Account_Code]], tbl_Accounts[Account_Code], tbl_Accounts[PL_Bucket]) -> Revenue | T25: =IF(AND(S25="Revenue",F25<>4900),ABS(Q25),-ABS(Q25)) -> 49800
A26: T100022 | B26: 45840 | C26: NetSuite | D26: Zumi Logistics | E26: Contract-Dangote | F26: 4020 | G26: Logistics Contract Revenue | H26: Contract-Dangote daily settlement 2025-07-02 | I26: USD | J26: 28.56 | K26: Dangote | L26: INV-20250702-CON | N26: =TEXT(tbl_Ledger[[#This Row],[Date]],"yyyy-mm") -> 2025-07 | O26: =TEXT(tbl_Ledger[[#This Row],[Date]],"yyyy-mm") & TRIM(tbl_Ledger[[#This Row],[Currency]]) -> 2025-07USD | P26: =_xlfn.XLOOKUP(tbl_Ledger[[#This Row],[Key]], tbl_FX[Key], tbl_FX[Rate_to_NGN]) -> 1530 | Q26: =IF(tbl_Ledger[[#This Row],[Account_Type]]="Expense",-ABS(tbl_Ledger[[#This Row],[Amount]]*tbl_Ledger[[#This Row],[Rate_to_NGN]]),tbl_Ledger[[#This Row],[Amount]]*tbl_Ledger[[#This Row],[Rate_to_NGN]]) -> 43696.8 | R26: =_xlfn.XLOOKUP(tbl_Ledger[[#This Row],[Account_Code]], tbl_Accounts[Account_Code], tbl_Accounts[Type]) -> Revenue | S26: =_xlfn.XLOOKUP(tbl_Ledger[[#This Row],[Account_Code]], tbl_Accounts[Account_Code], tbl_Accounts[PL_Bucket]) -> Revenue | T26: =IF(AND(S26="Revenue",F26<>4900),ABS(Q26),-ABS(Q26)) -> 43696.8
A27: T100023 | B27: 45840 | C27: NetSuite | D27: Zumi Logistics | E27: Contract-MTN | F27: 4020 | G27: Logistics Contract Revenue | H27: Contract-MTN daily settlement 2025-07-02 | I27: NGN | J27: 49900 | K27: MTN | L27: INV-20250702-CON | N27: =TEXT(tbl_Ledger[[#This Row],[Date]],"yyyy-mm") -> 2025-07 | O27: =TEXT(tbl_Ledger[[#This Row],[Date]],"yyyy-mm") & TRIM(tbl_Ledger[[#This Row],[Currency]]) -> 2025-07NGN | P27: =_xlfn.XLOOKUP(tbl_Ledger[[#This Row],[Key]], tbl_FX[Key], tbl_FX[Rate_to_NGN]) -> 1 | Q27: =IF(tbl_Ledger[[#This Row],[Account_Type]]="Expense",-ABS(tbl_Ledger[[#This Row],[Amount]]*tbl_Ledger[[#This Row],[Rate_to_NGN]]),tbl_Ledger[[#This Row],[Amount]]*tbl_Ledger[[#This Row],[Rate_to_NGN]]) -> 49900 | R27: =_xlfn.XLOOKUP(tbl_Ledger[[#This Row],[Account_Code]], tbl_Accounts[Account_Code], tbl_Accounts[Type]) -> Revenue | S27: =_xlfn.XLOOKUP(tbl_Ledger[[#This Row],[Account_Code]], tbl_Accounts[Account_Code], tbl_Accounts[PL_Bucket]) -> Revenue | T27: =IF(AND(S27="Revenue",F27<>4900),ABS(Q27),-ABS(Q27)) -> 49900
A28: T100024 | B28: 45840 | C28: NetSuite | D28: Zumi Logistics | E28: Contract-Flutterwave | F28: 4020 | G28: Logistics Contract Revenue | H28: Contract-Flutterwave daily settlement 2025-07-02 | I28: NGN | J28: 48500 | K28: Flutterwave | L28: INV-20250702-CON | N28: =TEXT(tbl_Ledger[[#This Row],[Date]],"yyyy-mm") -> 2025-07 | O28: =TEXT(tbl_Ledger[[#This Row],[Date]],"yyyy-mm") & TRIM(tbl_Ledger[[#This Row],[Currency]]) -> 2025-07NGN | P28: =_xlfn.XLOOKUP(tbl_Ledger[[#This Row],[Key]], tbl_FX[Key], tbl_FX[Rate_to_NGN]) -> 1 | Q28: =IF(tbl_Ledger[[#This Row],[Account_Type]]="Expense",-ABS(tbl_Ledger[[#This Row],[Amount]]*tbl_Ledger[[#This Row],[Rate_to_NGN]]),tbl_Ledger[[#This Row],[Amount]]*tbl_Ledger[[#This Row],[Rate_to_NGN]]) -> 48500 | R28: =_xlfn.XLOOKUP(tbl_Ledger[[#This Row],[Account_Code]], tbl_Accounts[Account_Code], tbl_Accounts[Type]) -> Revenue | S28: =_xlfn.XLOOKUP(tbl_Ledger[[#This Row],[Account_Code]], tbl_Accounts[Account_Code], tbl_Accounts[PL_Bucket]) -> Revenue | T28: =IF(AND(S28="Revenue",F28<>4900),ABS(Q28),-ABS(Q28)) -> 48500
A29: T100025 | B29: 45840 | C29: NetSuite | D29: Zumi Logistics | E29: Spot-Market | F29: 4020 | G29: Logistics Contract Revenue | H29: Spot-Market daily settlement 2025-07-02 | I29: NGN | J29: 48000 | L29: INV-20250702-SPO | N29: =TEXT(tbl_Ledger[[#This Row],[Date]],"yyyy-mm") -> 2025-07 | O29: =TEXT(tbl_Ledger[[#This Row],[Date]],"yyyy-mm") & TRIM(tbl_Ledger[[#This Row],[Currency]]) -> 2025-07NGN | P29: =_xlfn.XLOOKUP(tbl_Ledger[[#This Row],[Key]], tbl_FX[Key], tbl_FX[Rate_to_NGN]) -> 1 | Q29: =IF(tbl_Ledger[[#This Row],[Account_Type]]="Expense",-ABS(tbl_Ledger[[#This Row],[Amount]]*tbl_Ledger[[#This Row],[Rate_to_NGN]]),tbl_Ledger[[#This Row],[Amount]]*tbl_Ledger[[#This Row],[Rate_to_NGN]]) -> 48000 | R29: =_xlfn.XLOOKUP(tbl_Ledger[[#This Row],[Account_Code]], tbl_Accounts[Account_Code], tbl_Accounts[Type]) -> Revenue | S29: =_xlfn.XLOOKUP(tbl_Ledger[[#This Row],[Account_Code]], tbl_Accounts[Account_Code], tbl_Accounts[PL_Bucket]) -> Revenue | T29: =IF(AND(S29="Revenue",F29<>4900),ABS(Q29),-ABS(Q29)) -> 48000
A30: T101239 | B30: 45840 | C30: QuickBooks | D30: Zumi Eats | F30: 5040 | G30: Rider Payouts | H30: Rider Payroll invoice 2025-07 | I30: NGN | J30: -562000 | K30: Rider Payroll | L30: BILL-47775 | N30: =TEXT(tbl_Ledger[[#This Row],[Date]],"yyyy-mm") -> 2025-07 | O30: =TEXT(tbl_Ledger[[#This Row],[Date]],"yyyy-mm") & TRIM(tbl_Ledger[[#This Row],[Currency]]) -> 2025-07NGN | P30: =_xlfn.XLOOKUP(tbl_Ledger[[#This Row],[Key]], tbl_FX[Key], tbl_FX[Rate_to_NGN]) -> 1 | Q30: =IF(tbl_Ledger[[#This Row],[Account_Type]]="Expense",-ABS(tbl_Ledger[[#This Row],[Amount]]*tbl_Ledger[[#This Row],[Rate_to_NGN]]),tbl_Ledger[[#This Row],[Amount]]*tbl_Ledger[[#This Row],[Rate_to_NGN]]) -> -562000 | R30: =_xlfn.XLOOKUP(tbl_Ledger[[#This Row],[Account_Code]], tbl_Accounts[Account_Code], tbl_Accounts[Type]) -> COGS | S30: =_xlfn.XLOOKUP(tbl_Ledger[[#This Row],[Account_Code]], tbl_Accounts[Account_Code], tbl_Accounts[PL_Bucket]) -> COGS | T30: =IF(AND(S30="Revenue",F30<>4900),ABS(Q30),-ABS(Q30)) -> -562000
A31: T101243 | B31: 45840 | C31: QuickBooks | D31: Zumi Eats | F31: 5050 | G31: Aggregator Commission | H31: Bolt Food invoice 2025-07 | I31: NGN | J31: -255000 | K31: Bolt Food | L31: BILL-82046 | N31: =TEXT(tbl_Ledger[[#This Row],[Date]],"yyyy-mm") -> 2025-07 | O31: =TEXT(tbl_Ledger[[#This Row],[Date]],"yyyy-mm") & TRIM(tbl_Ledger[[#This Row],[Currency]]) -> 2025-07NGN | P31: =_xlfn.XLOOKUP(tbl_Ledger[[#This Row],[Key]], tbl_FX[Key], tbl_FX[Rate_to_NGN]) -> 1 | Q31: =IF(tbl_Ledger[[#This Row],[Account_Type]]="Expense",-ABS(tbl_Ledger[[#This Row],[Amount]]*tbl_Ledger[[#This Row],[Rate_to_NGN]]),tbl_Ledger[[#This Row],[Amount]]*tbl_Ledger[[#This Row],[Rate_to_NGN]]) -> -255000 | R31: =_xlfn.XLOOKUP(tbl_Ledger[[#This Row],[Account_Code]], tbl_Accounts[Account_Code], tbl_Accounts[Type]) -> COGS | S31: =_xlfn.XLOOKUP(tbl_Ledger[[#This Row],[Account_Code]], tbl_Accounts[Account_Code], tbl_Accounts[PL_Bucket]) -> COGS | T31: =IF(AND(S31="Revenue",F31<>4900),ABS(Q31),-ABS(Q31)) -> -255000
A32: T101254 | B32: 45840 | C32: QuickBooks | D32: Zumi Mart | F32: 5010 | G32: Inventory Purchases | H32: Dangote Sugar invoice 2025-07 | I32: NGN | J32: -862000 | K32: Dangote Sugar | L32: BILL-69162 | N32: =TEXT(tbl_Ledger[[#This Row],[Date]],"yyyy-mm") -> 2025-07 | O32: =TEXT(tbl_Ledger[[#This Row],[Date]],"yyyy-mm") & TRIM(tbl_Ledger[[#This Row],[Currency]]) -> 2025-07NGN | P32: =_xlfn.XLOOKUP(tbl_Ledger[[#This Row],[Key]], tbl_FX[Key], tbl_FX[Rate_to_NGN]) -> 1 | Q32: =IF(tbl_Ledger[[#This Row],[Account_Type]]="Expense",-ABS(tbl_Ledger[[#This Row],[Amount]]*tbl_Ledger[[#This Row],[Rate_to_NGN]]),tbl_Ledger[[#This Row],[Amount]]*tbl_Ledger[[#This Row],[Rate_to_NGN]]) -> -862000 | R32: =_xlfn.XLOOKUP(tbl_Ledger[[#This Row],[Account_Code]], tbl_Accounts[Account_Code], tbl_Accounts[Type]) -> COGS | S32: =_xlfn.XLOOKUP(tbl_Ledger[[#This Row],[Account_Code]], tbl_Accounts[Account_Code], tbl_Accounts[PL_Bucket]) -> COGS | T32: =IF(AND(S32="Revenue",F32<>4900),ABS(Q32),-ABS(Q32)) -> -862000
A33: T101394 | B33: 45840 | C33: QuickBooks | D33: Zumi Eats | F33: 6040 | G33: Software & Tools | H33: SaaS subscriptions 2025-07 | I33: USD | J33: -820 | K33: Various SaaS | L33: SAAS-2025-07 | N33: =TEXT(tbl_Ledger[[#This Row],[Date]],"yyyy-mm") -> 2025-07 | O33: =TEXT(tbl_Ledger[[#This Row],[Date]],"yyyy-mm") & TRIM(tbl_Ledger[[#This Row],[Currency]]) -> 2025-07USD | P33: =_xlfn.XLOOKUP(tbl_Ledger[[#This Row],[Key]], tbl_FX[Key], tbl_FX[Rate_to_NGN]) -> 1530 | Q33: =IF(tbl_Ledger[[#This Row],[Account_Type]]="Expense",-ABS(tbl_Ledger[[#This Row],[Amount]]*tbl_Ledger[[#This Row],[Rate_to_NGN]]),tbl_Ledger[[#This Row],[Amount]]*tbl_Ledger[[#This Row],[Rate_to_NGN]]) -> -1254600 | R33: =_xlfn.XLOOKUP(tbl_Ledger[[#This Row],[Account_Code]], tbl_Accounts[Account_Code], tbl_Accounts[Type]) -> Opex | S33: =_xlfn.XLOOKUP(tbl_Ledger[[#This Row],[Account_Code]], tbl_Accounts[Account_Code], tbl_Accounts[PL_Bucket]) -> Opex | T33: =IF(AND(S33="Revenue",F33<>4900),ABS(Q33),-ABS(Q33)) -> -1254600
A34: T100026 | B34: 45841 | C34: POS-Square | D34: Zumi Eats | E34: Mobile App | F34: 4000 | G34: Order Revenue | H34: Mobile App daily settlement 2025-07-03 | I34: NGN | J34: 30100 | L34: INV-20250703-MOB | N34: =TEXT(tbl_Ledger[[#This Row],[Date]],"yyyy-mm") -> 2025-07 | O34: =TEXT(tbl_Ledger[[#This Row],[Date]],"yyyy-mm") & TRIM(tbl_Ledger[[#This Row],[Currency]]) -> 2025-07NGN | P34: =_xlfn.XLOOKUP(tbl_Ledger[[#This Row],[Key]], tbl_FX[Key], tbl_FX[Rate_to_NGN]) -> 1 | Q34: =IF(tbl_Ledger[[#This Row],[Account_Type]]="Expense",-ABS(tbl_Ledger[[#This Row],[Amount]]*tbl_Ledger[[#This Row],[Rate_to_NGN]]),tbl_Ledger[[#This Row],[Amount]]*tbl_Ledger[[#This Row],[Rate_to_NGN]]) -> 30100 | R34: =_xlfn.XLOOKUP(tbl_Ledger[[#This Row],[Account_Code]], tbl_Accounts[Account_Code], tbl_Accounts[Type]) -> Revenue | S34: =_xlfn.XLOOKUP(tbl_Ledger[[#This Row],[Account_Code]], tbl_Accounts[Account_Code], tbl_Accounts[PL_Bucket]) -> Revenue | T34: =IF(AND(S34="Revenue",F34<>4900),ABS(Q34),-ABS(Q34)) -> 30100
A35: T100027 | B35: 45841 | C35: POS-Square | D35: Zumi Eats | E35: Website | F35: 4000 | G35: Order Revenue | H35: Website daily settlement 2025-07-03 | I35: NGN | J35: 30400 | L35: INV-20250703-WEB | N35: =TEXT(tbl_Ledger[[#This Row],[Date]],"yyyy-mm") -> 2025-07 | O35: =TEXT(tbl_Ledger[[#This Row],[Date]],"yyyy-mm") & TRIM(tbl_Ledger[[#This Row],[Currency]]) -> 2025-07NGN | P35: =_xlfn.XLOOKUP(tbl_Ledger[[#This Row],[Key]], tbl_FX[Key], tbl_FX[Rate_to_NGN]) -> 1 | Q35: =IF(tbl_Ledger[[#This Row],[Account_Type]]="Expense",-ABS(tbl_Ledger[[#This Row],[Amount]]*tbl_Ledger[[#This Row],[Rate_to_NGN]]),tbl_Ledger[[#This Row],[Amount]]*tbl_Ledger[[#This Row],[Rate_to_NGN]]) -> 30400 | R35: =_xlfn.XLOOKUP(tbl_Ledger[[#This Row],[Account_Code]], tbl_Accounts[Account_Code], tbl_Accounts[Type]) -> Revenue | S35: =_xlfn.XLOOKUP(tbl_Ledger[[#This Row],[Account_Code]], tbl_Accounts[Account_Code], tbl_Accounts[PL_Bucket]) -> Revenue | T35: =IF(AND(S35="Revenue",F35<>4900),ABS(Q35),-ABS(Q35)) -> 30400
A36: T100028 | B36: 45841 | C36: POS-Square | D36: Zumi Eats | E36: Aggregator-Glovo | F36: 4000 | G36: Order Revenue | H36: Aggregator-Glovo daily settlement 2025-07-03 | I36: NGN | J36: 30700 | L36: INV-20250703-AGG | N36: =TEXT(tbl_Ledger[[#This Row],[Date]],"yyyy-mm") -> 2025-07 | O36: =TEXT(tbl_Ledger[[#This Row],[Date]],"yyyy-mm") & TRIM(tbl_Ledger[[#This Row],[Currency]]) -> 2025-07NGN | P36: =_xlfn.XLOOKUP(tbl_Ledger[[#This Row],[Key]], tbl_FX[Key], tbl_FX[Rate_to_NGN]) -> 1 | Q36: =IF(tbl_Ledger[[#This Row],[Account_Type]]="Expense",-ABS(tbl_Ledger[[#This Row],[Amount]]*tbl_Ledger[[#This Row],[Rate_to_NGN]]),tbl_Ledger[[#This Row],[Amount]]*tbl_Ledger[[#This Row],[Rate_to_NGN]]) -> 30700 | R36: =_xlfn.XLOOKUP(tbl_Ledger[[#This Row],[Account_Code]], tbl_Accounts[Account_Code], tbl_Accounts[Type]) -> Revenue | S36: =_xlfn.XLOOKUP(tbl_Ledger[[#This Row],[Account_Code]], tbl_Accounts[Account_Code], tbl_Accounts[PL_Bucket]) -> Revenue | T36: =IF(AND(S36="Revenue",F36<>4900),ABS(Q36),-ABS(Q36)) -> 30700
A37: T100029 | B37: 45841 | C37: POS-Square | D37: Zumi Eats | E37: Aggregator-Bolt | F37: 4000 | G37: Order Revenue | H37: Aggregator-Bolt daily settlement 2025-07-03 | I37: NGN | J37: 28100 | L37: INV-20250703-AGG | N37: =TEXT(tbl_Ledger[[#This Row],[Date]],"yyyy-mm") -> 2025-07 | O37: =TEXT(tbl_Ledger[[#This Row],[Date]],"yyyy-mm") & TRIM(tbl_Ledger[[#This Row],[Currency]]) -> 2025-07NGN | P37: =_xlfn.XLOOKUP(tbl_Ledger[[#This Row],[Key]], tbl_FX[Key], tbl_FX[Rate_to_NGN]) -> 1 | Q37: =IF(tbl_Ledger[[#This Row],[Account_Type]]="Expense",-ABS(tbl_Ledger[[#This Row],[Amount]]*tbl_Ledger[[#This Row],[Rate_to_NGN]]),tbl_Ledger[[#This Row],[Amount]]*tbl_Ledger[[#This Row],[Rate_to_NGN]]) -> 28100 | R37: =_xlfn.XLOOKUP(tbl_Ledger[[#This Row],[Account_Code]], tbl_Accounts[Account_Code], tbl_Accounts[Type]) -> Revenue | S37: =_xlfn.XLOOKUP(tbl_Ledger[[#This Row],[Account_Code]], tbl_Accounts[Account_Code], tbl_Accounts[PL_Bucket]) -> Revenue | T37: =IF(AND(S37="Revenue",F37<>4900),ABS(Q37),-ABS(Q37)) -> 28100
A38: T100030 | B38: 45841 | C38: POS-Square | D38: Zumi Mart | E38: POS-Lekki | F38: 4000 | G38: Order Revenue | H38: POS-Lekki daily settlement 2025-07-03 | I38: NGN | J38: 48100 | L38: INV-20250703-POS | N38: =TEXT(tbl_Ledger[[#This Row],[Date]],"yyyy-mm") -> 2025-07 | O38: =TEXT(tbl_Ledger[[#This Row],[Date]],"yyyy-mm") & TRIM(tbl_Ledger[[#This Row],[Currency]]) -> 2025-07NGN | P38: =_xlfn.XLOOKUP(tbl_Ledger[[#This Row],[Key]], tbl_FX[Key], tbl_FX[Rate_to_NGN]) -> 1 | Q38: =IF(tbl_Ledger[[#This Row],[Account_Type]]="Expense",-ABS(tbl_Ledger[[#This Row],[Amount]]*tbl_Ledger[[#This Row],[Rate_to_NGN]]),tbl_Ledger[[#This Row],[Amount]]*tbl_Ledger[[#This Row],[Rate_to_NGN]]) -> 48100 | R38: =_xlfn.XLOOKUP(tbl_Ledger[[#This Row],[Account_Code]], tbl_Accounts[Account_Code], tbl_Accounts[Type]) -> Revenue | S38: =_xlfn.XLOOKUP(tbl_Ledger[[#This Row],[Account_Code]], tbl_Accounts[Account_Code], tbl_Accounts[PL_Bucket]) -> Revenue | T38: =IF(AND(S38="Revenue",F38<>4900),ABS(Q38),-ABS(Q38)) -> 48100
A39: T100031 | B39: 45841 | C39: POS-Square | D39: Zumi Mart | E39: POS-VI | F39: 4000 | G39: Order Revenue | H39: POS-VI daily settlement 2025-07-03 | I39: NGN | J39: 47100 | L39: INV-20250703-POS | N39: =TEXT(tbl_Ledger[[#This Row],[Date]],"yyyy-mm") -> 2025-07 | O39: =TEXT(tbl_Ledger[[#This Row],[Date]],"yyyy-mm") & TRIM(tbl_Ledger[[#This Row],[Currency]]) -> 2025-07NGN | P39: =_xlfn.XLOOKUP(tbl_Ledger[[#This Row],[Key]], tbl_FX[Key], tbl_FX[Rate_to_NGN]) -> 1 | Q39: =IF(tbl_Ledger[[#This Row],[Account_Type]]="Expense",-ABS(tbl_Ledger[[#This Row],[Amount]]*tbl_Ledger[[#This Row],[Rate_to_NGN]]),tbl_Ledger[[#This Row],[Amount]]*tbl_Ledger[[#This Row],[Rate_to_NGN]]) -> 47100 | R39: =_xlfn.XLOOKUP(tbl_Ledger[[#This Row],[Account_Code]], tbl_Accounts[Account_Code], tbl_Accounts[Type]) -> Revenue | S39: =_xlfn.XLOOKUP(tbl_Ledger[[#This Row],[Account_Code]], tbl_Accounts[Account_Code], tbl_Accounts[PL_Bucket]) -> Revenue | T39: =IF(AND(S39="Revenue",F39<>4900),ABS(Q39),-ABS(Q39)) -> 47100
A40: T100032 | B40: 45841 | C40: POS-Square | D40: Zumi Mart | E40: POS-Ikeja | F40: 4000 | G40: Order Revenue | H40: POS-Ikeja daily settlement 2025-07-03 | I40: NGN | J40: 50400 | L40: INV-20250703-POS | N40: =TEXT(tbl_Ledger[[#This Row],[Date]],"yyyy-mm") -> 2025-07 | O40: =TEXT(tbl_Ledger[[#This Row],[Date]],"yyyy-mm") & TRIM(tbl_Ledger[[#This Row],[Currency]]) -> 2025-07NGN | P40: =_xlfn.XLOOKUP(tbl_Ledger[[#This Row],[Key]], tbl_FX[Key], tbl_FX[Rate_to_NGN]) -> 1 | Q40: =IF(tbl_Ledger[[#This Row],[Account_Type]]="Expense",-ABS(tbl_Ledger[[#This Row],[Amount]]*tbl_Ledger[[#This Row],[Rate_to_NGN]]),tbl_Ledger[[#This Row],[Amount]]*tbl_Ledger[[#This Row],[Rate_to_NGN]]) -> 50400 | R40: =_xlfn.XLOOKUP(tbl_Ledger[[#This Row],[Account_Code]], tbl_Accounts[Account_Code], tbl_Accounts[Type]) -> Revenue | S40: =_xlfn.XLOOKUP(tbl_Ledger[[#This Row],[Account_Code]], tbl_Accounts[Account_Code], tbl_Accounts[PL_Bucket]) -> Revenue | T40: =IF(AND(S40="Revenue",F40<>4900),ABS(Q40),-ABS(Q40)) -> 50400
A41: T100033 | B41: 45841 | C41: POS-Square | D41: Zumi Mart | E41: POS-Abuja | F41: 4000 | G41: Order Revenue | H41: POS-Abuja daily settlement 2025-07-03 | I41: NGN | J41: 50400 | L41: INV-20250703-POS | N41: =TEXT(tbl_Ledger[[#This Row],[Date]],"yyyy-mm") -> 2025-07 | O41: =TEXT(tbl_Ledger[[#This Row],[Date]],"yyyy-mm") & TRIM(tbl_Ledger[[#This Row],[Currency]]) -> 2025-07NGN | P41: =_xlfn.XLOOKUP(tbl_Ledger[[#This Row],[Key]], tbl_FX[Key], tbl_FX[Rate_to_NGN]) -> 1 | Q41: =IF(tbl_Ledger[[#This Row],[Account_Type]]="Expense",-ABS(tbl_Ledger[[#This Row],[Amount]]*tbl_Ledger[[#This Row],[Rate_to_NGN]]),tbl_Ledger[[#This Row],[Amount]]*tbl_Ledger[[#This Row],[Rate_to_NGN]]) -> 50400 | R41: =_xlfn.XLOOKUP(tbl_Ledger[[#This Row],[Account_Code]], tbl_Accounts[Account_Code], tbl_Accounts[Type]) -> Revenue | S41: =_xlfn.XLOOKUP(tbl_Ledger[[#This Row],[Account_Code]], tbl_Accounts[Account_Code], tbl_Accounts[PL_Bucket]) -> Revenue | T41: =IF(AND(S41="Revenue",F41<>4900),ABS(Q41),-ABS(Q41)) -> 50400
A42: T100034 | B42: 45841 | C42: POS-Square | D42: Zumi Mart | E42: Online | F42: 4000 | G42: Order Revenue | H42: Online daily settlement 2025-07-03 | I42: NGN | J42: 47300 | L42: INV-20250703-ONL | N42: =TEXT(tbl_Ledger[[#This Row],[Date]],"yyyy-mm") -> 2025-07 | O42: =TEXT(tbl_Ledger[[#This Row],[Date]],"yyyy-mm") & TRIM(tbl_Ledger[[#This Row],[Currency]]) -> 2025-07NGN | P42: =_xlfn.XLOOKUP(tbl_Ledger[[#This Row],[Key]], tbl_FX[Key], tbl_FX[Rate_to_NGN]) -> 1 | Q42: =IF(tbl_Ledger[[#This Row],[Account_Type]]="Expense",-ABS(tbl_Ledger[[#This Row],[Amount]]*tbl_Ledger[[#This Row],[Rate_to_NGN]]),tbl_Ledger[[#This Row],[Amount]]*tbl_Ledger[[#This Row],[Rate_to_NGN]]) -> 47300 | R42: =_xlfn.XLOOKUP(tbl_Ledger[[#This Row],[Account_Code]], tbl_Accounts[Account_Code], tbl_Accounts[Type]) -> Revenue | S42: =_xlfn.XLOOKUP(tbl_Ledger[[#This Row],[Account_Code]], tbl_Accounts[Account_Code], tbl_Accounts[PL_Bucket]) -> Revenue | T42: =IF(AND(S42="Revenue",F42<>4900),ABS(Q42),-ABS(Q42)) -> 47300
A43: T100035 | B43: 45841 | C43: NetSuite | D43: Zumi Logistics | E43: Contract-Dangote | F43: 4020 | G43: Logistics Contract Revenue | H43: Contract-Dangote daily settlement 2025-07-03 | I43: USD | J43: 26.99 | K43: Dangote | L43: INV-20250703-CON | N43: =TEXT(tbl_Ledger[[#This Row],[Date]],"yyyy-mm") -> 2025-07 | O43: =TEXT(tbl_Ledger[[#This Row],[Date]],"yyyy-mm") & TRIM(tbl_Ledger[[#This Row],[Currency]]) -> 2025-07USD | P43: =_xlfn.XLOOKUP(tbl_Ledger[[#This Row],[Key]], tbl_FX[Key], tbl_FX[Rate_to_NGN]) -> 1530 | Q43: =IF(tbl_Ledger[[#This Row],[Account_Type]]="Expense",-ABS(tbl_Ledger[[#This Row],[Amount]]*tbl_Ledger[[#This Row],[Rate_to_NGN]]),tbl_Ledger[[#This Row],[Amount]]*tbl_Ledger[[#This Row],[Rate_to_NGN]]) -> 41294.7 | R43: =_xlfn.XLOOKUP(tbl_Ledger[[#This Row],[Account_Code]], tbl_Accounts[Account_Code], tbl_Accounts[Type]) -> Revenue | S43: =_xlfn.XLOOKUP(tbl_Ledger[[#This Row],[Account_Code]], tbl_Accounts[Account_Code], tbl_Accounts[PL_Bucket]) -> Revenue | T43: =IF(AND(S43="Revenue",F43<>4900),ABS(Q43),-ABS(Q43)) -> 41294.7
A44: T100036 | B44: 45841 | C44: NetSuite | D44: Zumi Logistics | E44: Contract-MTN | F44: 4020 | G44: Logistics Contract Revenue | H44: Contract-MTN daily settlement 2025-07-03 | I44: NGN | J44: 40600 | K44: MTN | L44: INV-20250703-CON | N44: =TEXT(tbl_Ledger[[#This Row],[Date]],"yyyy-mm") -> 2025-07 | O44: =TEXT(tbl_Ledger[[#This Row],[Date]],"yyyy-mm") & TRIM(tbl_Ledger[[#This Row],[Currency]]) -> 2025-07NGN | P44: =_xlfn.XLOOKUP(tbl_Ledger[[#This Row],[Key]], tbl_FX[Key], tbl_FX[Rate_to_NGN]) -> 1 | Q44: =IF(tbl_Ledger[[#This Row],[Account_Type]]="Expense",-ABS(tbl_Ledger[[#This Row],[Amount]]*tbl_Ledger[[#This Row],[Rate_to_NGN]]),tbl_Ledger[[#This Row],[Amount]]*tbl_Ledger[[#This Row],[Rate_to_NGN]]) -> 40600 | R44: =_xlfn.XLOOKUP(tbl_Ledger[[#This Row],[Account_Code]], tbl_Accounts[Account_Code], tbl_Accounts[Type]) -> Revenue | S44: =_xlfn.XLOOKUP(tbl_Ledger[[#This Row],[Account_Code]], tbl_Accounts[Account_Code], tbl_Accounts[PL_Bucket]) -> Revenue | T44: =IF(AND(S44="Revenue",F44<>4900),ABS(Q44),-ABS(Q44)) -> 40600
A45: T100037 | B45: 45841 | C45: NetSuite | D45: Zumi Logistics | E45: Contract-Flutterwave | F45: 4020 | G45: Logistics Contract Revenue | H45: Contract-Flutterwave daily settlement 2025-07-03 | I45: USD | J45: 30.52 | K45: Flutterwave | L45: INV-20250703-CON | N45: =TEXT(tbl_Ledger[[#This Row],[Date]],"yyyy-mm") -> 2025-07 | O45: =TEXT(tbl_Ledger[[#This Row],[Date]],"yyyy-mm") & TRIM(tbl_Ledger[[#This Row],[Currency]]) -> 2025-07USD | P45: =_xlfn.XLOOKUP(tbl_Ledger[[#This Row],[Key]], tbl_FX[Key], tbl_FX[Rate_to_NGN]) -> 1530 | Q45: =IF(tbl_Ledger[[#This Row],[Account_Type]]="Expense",-ABS(tbl_Ledger[[#This Row],[Amount]]*tbl_Ledger[[#This Row],[Rate_to_NGN]]),tbl_Ledger[[#This Row],[Amount]]*tbl_Ledger[[#This Row],[Rate_to_NGN]]) -> 46695.6 | R45: =_xlfn.XLOOKUP(tbl_Ledger[[#This Row],[Account_Code]], tbl_Accounts[Account_Code], tbl_Accounts[Type]) -> Revenue | S45: =_xlfn.XLOOKUP(tbl_Ledger[[#This Row],[Account_Code]], tbl_Accounts[Account_Code], tbl_Accounts[PL_Bucket]) -> Revenue | T45: =IF(AND(S45="Revenue",F45<>4900),ABS(Q45),-ABS(Q45)) -> 46695.6
A46: T100038 | B46: 45841 | C46: NetSuite | D46: Zumi Logistics | E46: Spot-Market | F46: 4020 | G46: Logistics Contract Revenue | H46: Spot-Market daily settlement 2025-07-03 | I46: NGN | J46: 40000 | L46: INV-20250703-SPO | N46: =TEXT(tbl_Ledger[[#This Row],[Date]],"yyyy-mm") -> 2025-07 | O46: =TEXT(tbl_Ledger[[#This Row],[Date]],"yyyy-mm") & TRIM(tbl_Ledger[[#This Row],[Currency]]) -> 2025-07NGN | P46: =_xlfn.XLOOKUP(tbl_Ledger[[#This Row],[Key]], tbl_FX[Key], tbl_FX[Rate_to_NGN]) -> 1 | Q46: =IF(tbl_Ledger[[#This Row],[Account_Type]]="Expense",-ABS(tbl_Ledger[[#This Row],[Amount]]*tbl_Ledger[[#This Row],[Rate_to_NGN]]),tbl_Ledger[[#This Row],[Amount]]*tbl_Ledger[[#This Row],[Rate_to_NGN]]) -> 40000 | R46: =_xlfn.XLOOKUP(tbl_Ledger[[#This Row],[Account_Code]], tbl_Accounts[Account_Code], tbl_Accounts[Type]) -> Revenue | S46: =_xlfn.XLOOKUP(tbl_Ledger[[#This Row],[Account_Code]], tbl_Accounts[Account_Code], tbl_Accounts[PL_Bucket]) -> Revenue | T46: =IF(AND(S46="Revenue",F46<>4900),ABS(Q46),-ABS(Q46)) -> 40000
A47: T101200 | B47: 45841 | C47: POS-Square | D47: Zumi Mart | E47: POS-Lekki | F47: 4900 | G47: Refunds & Chargebacks | H47: Customer refund order #263503 | I47: NGN | J47: 146038 | L47: RFD-4122 | M47: FLAG: booked positive | N47: =TEXT(tbl_Ledger[[#This Row],[Date]],"yyyy-mm") -> 2025-07 | O47: =TEXT(tbl_Ledger[[#This Row],[Date]],"yyyy-mm") & TRIM(tbl_Ledger[[#This Row],[Currency]]) -> 2025-07NGN | P47: =_xlfn.XLOOKUP(tbl_Ledger[[#This Row],[Key]], tbl_FX[Key], tbl_FX[Rate_to_NGN]) -> 1 | Q47: =IF(tbl_Ledger[[#This Row],[Account_Type]]="Expense",-ABS(tbl_Ledger[[#This Row],[Amount]]*tbl_Ledger[[#This Row],[Rate_to_NGN]]),tbl_Ledger[[#This Row],[Amount]]*tbl_Ledger[[#This Row],[Rate_to_NGN]]) -> 146038 | R47: =_xlfn.XLOOKUP(tbl_Ledger[[#This Row],[Account_Code]], tbl_Accounts[Account_Code], tbl_Accounts[Type]) -> Revenue | S47: =_xlfn.XLOOKUP(tbl_Ledger[[#This Row],[Account_Code]], tbl_Accounts[Account_Code], tbl_Accounts[PL_Bucket]) -> Revenue | T47: =IF(AND(S47="Revenue",F47<>4900),ABS(Q47),-ABS(Q47)) -> 146038
A48: T100039 | B48: 45842 | C48: POS-Square | D48: Zumi Eats | E48: Mobile App | F48: 4000 | G48: Order Revenue | H48: Mobile App daily settlement 2025-07-04 | I48: NGN | J48: 30400 | L48: INV-20250704-MOB | N48: =TEXT(tbl_Ledger[[#This Row],[Date]],"yyyy-mm") -> 2025-07 | O48: =TEXT(tbl_Ledger[[#This Row],[Date]],"yyyy-mm") & TRIM(tbl_Ledger[[#This Row],[Currency]]) -> 2025-07NGN | P48: =_xlfn.XLOOKUP(tbl_Ledger[[#This Row],[Key]], tbl_FX[Key], tbl_FX[Rate_to_NGN]) -> 1 | Q48: =IF(tbl_Ledger[[#This Row],[Account_Type]]="Expense",-ABS(tbl_Ledger[[#This Row],[Amount]]*tbl_Ledger[[#This Row],[Rate_to_NGN]]),tbl_Ledger[[#This Row],[Amount]]*tbl_Ledger[[#This Row],[Rate_to_NGN]]) -> 30400 | R48: =_xlfn.XLOOKUP(tbl_Ledger[[#This Row],[Account_Code]], tbl_Accounts[Account_Code], tbl_Accounts[Type]) -> Revenue | S48: =_xlfn.XLOOKUP(tbl_Ledger[[#This Row],[Account_Code]], tbl_Accounts[Account_Code], tbl_Accounts[PL_Bucket]) -> Revenue | T48: =IF(AND(S48="Revenue",F48<>4900),ABS(Q48),-ABS(Q48)) -> 30400
A49: T100040 | B49: 45842 | C49: POS-Square | D49: Zumi Eats | E49: Website | F49: 4000 | G49: Order Revenue | H49: Website daily settlement 2025-07-04 | I49: NGN | J49: 29300 | L49: INV-20250704-WEB | N49: =TEXT(tbl_Ledger[[#This Row],[Date]],"yyyy-mm") -> 2025-07 | O49: =TEXT(tbl_Ledger[[#This Row],[Date]],"yyyy-mm") & TRIM(tbl_Ledger[[#This Row],[Currency]]) -> 2025-07NGN | P49: =_xlfn.XLOOKUP(tbl_Ledger[[#This Row],[Key]], tbl_FX[Key], tbl_FX[Rate_to_NGN]) -> 1 | Q49: =IF(tbl_Ledger[[#This Row],[Account_Type]]="Expense",-ABS(tbl_Ledger[[#This Row],[Amount]]*tbl_Ledger[[#This Row],[Rate_to_NGN]]),tbl_Ledger[[#This Row],[Amount]]*tbl_Ledger[[#This Row],[Rate_to_NGN]]) -> 29300 | R49: =_xlfn.XLOOKUP(tbl_Ledger[[#This Row],[Account_Code]], tbl_Accounts[Account_Code], tbl_Accounts[Type]) -> Revenue | S49: =_xlfn.XLOOKUP(tbl_Ledger[[#This Row],[Account_Code]], tbl_Accounts[Account_Code], tbl_Accounts[PL_Bucket]) -> Revenue | T49: =IF(AND(S49="Revenue",F49<>4900),ABS(Q49),-ABS(Q49)) -> 29300
A50: T100041 | B50: 45842 | C50: POS-Square | D50: Zumi Eats | E50: Aggregator-Glovo | F50: 4000 | G50: Order Revenue | H50: Aggregator-Glovo daily settlement 2025-07-04 | I50: NGN | J50: 29200 | L50: INV-20250704-AGG | N50: =TEXT(tbl_Ledger[[#This Row],[Date]],"yyyy-mm") -> 2025-07 | O50: =TEXT(tbl_Ledger[[#This Row],[Date]],"yyyy-mm") & TRIM(tbl_Ledger[[#This Row],[Currency]]) -> 2025-07NGN | P50: =_xlfn.XLOOKUP(tbl_Ledger[[#This Row],[Key]], tbl_FX[Key], tbl_FX[Rate_to_NGN]) -> 1 | Q50: =IF(tbl_Ledger[[#This Row],[Account_Type]]="Expense",-ABS(tbl_Ledger[[#This Row],[Amount]]*tbl_Ledger[[#This Row],[Rate_to_NGN]]),tbl_Ledger[[#This Row],[Amount]]*tbl_Ledger[[#This Row],[Rate_to_NGN]]) -> 29200 | R50: =_xlfn.XLOOKUP(tbl_Ledger[[#This Row],[Account_Code]], tbl_Accounts[Account_Code], tbl_Accounts[Type]) -> Revenue | S50: =_xlfn.XLOOKUP(tbl_Ledger[[#This Row],[Account_Code]], tbl_Accounts[Account_Code], tbl_Accounts[PL_Bucket]) -> Revenue | T50: =IF(AND(S50="Revenue",F50<>4900),ABS(Q50),-ABS(Q50)) -> 29200
A51: T100042 | B51: 45842 | C51: POS-Square | D51: Zumi Eats | E51: Aggregator-Bolt | F51: 4000 | G51: Order Revenue | H51: Aggregator-Bolt daily settlement 2025-07-04 | I51: NGN | J51: 27300 | L51: INV-20250704-AGG | N51: =TEXT(tbl_Ledger[[#This Row],[Date]],"yyyy-mm") -> 2025-07 | O51: =TEXT(tbl_Ledger[[#This Row],[Date]],"yyyy-mm") & TRIM(tbl_Ledger[[#This Row],[Currency]]) -> 2025-07NGN | P51: =_xlfn.XLOOKUP(tbl_Ledger[[#This Row],[Key]], tbl_FX[Key], tbl_FX[Rate_to_NGN]) -> 1 | Q51: =IF(tbl_Ledger[[#This Row],[Account_Type]]="Expense",-ABS(tbl_Ledger[[#This Row],[Amount]]*tbl_Ledger[[#This Row],[Rate_to_NGN]]),tbl_Ledger[[#This Row],[Amount]]*tbl_Ledger[[#This Row],[Rate_to_NGN]]) -> 27300 | R51: =_xlfn.XLOOKUP(tbl_Ledger[[#This Row],[Account_Code]], tbl_Accounts[Account_Code], tbl_Accounts[Type]) -> Revenue | S51: =_xlfn.XLOOKUP(tbl_Ledger[[#This Row],[Account_Code]], tbl_Accounts[Account_Code], tbl_Accounts[PL_Bucket]) -> Revenue | T51: =IF(AND(S51="Revenue",F51<>4900),ABS(Q51),-ABS(Q51)) -> 27300
A52: T100043 | B52: 45842 | C52: POS-Square | D52: Zumi Eats | E52: Walk-in | F52: 4000 | G52: Order Revenue | H52: Walk-in daily settlement 2025-07-04 | I52: NGN | J52: 27600 | L52: INV-20250704-WAL | N52: =TEXT(tbl_Ledger[[#This Row],[Date]],"yyyy-mm") -> 2025-07 | O52: =TEXT(tbl_Ledger[[#This Row],[Date]],"yyyy-mm") & TRIM(tbl_Ledger[[#This Row],[Currency]]) -> 2025-07NGN | P52: =_xlfn.XLOOKUP(tbl_Ledger[[#This Row],[Key]], tbl_FX[Key], tbl_FX[Rate_to_NGN]) -> 1 | Q52: =IF(tbl_Ledger[[#This Row],[Account_Type]]="Expense",-ABS(tbl_Ledger[[#This Row],[Amount]]*tbl_Ledger[[#This Row],[Rate_to_NGN]]),tbl_Ledger[[#This Row],[Amount]]*tbl_Ledger[[#This Row],[Rate_to_NGN]]) -> 27600 | R52: =_xlfn.XLOOKUP(tbl_Ledger[[#This Row],[Account_Code]], tbl_Accounts[Account_Code], tbl_Accounts[Type]) -> Revenue | S52: =_xlfn.XLOOKUP(tbl_Ledger[[#This Row],[Account_Code]], tbl_Accounts[Account_Code], tbl_Accounts[PL_Bucket]) -> Revenue | T52: =IF(AND(S52="Revenue",F52<>4900),ABS(Q52),-ABS(Q52)) -> 27600
A53: T100044 | B53: 45842 | C53: POS-Square | D53: Zumi Mart | E53: POS-Lekki | F53: 4000 | G53: Order Revenue | H53: POS-Lekki daily settlement 2025-07-04 | I53: NGN | J53: 49800 | L53: INV-20250704-POS | N53: =TEXT(tbl_Ledger[[#This Row],[Date]],"yyyy-mm") -> 2025-07 | O53: =TEXT(tbl_Ledger[[#This Row],[Date]],"yyyy-mm") & TRIM(tbl_Ledger[[#This Row],[Currency]]) -> 2025-07NGN | P53: =_xlfn.XLOOKUP(tbl_Ledger[[#This Row],[Key]], tbl_FX[Key], tbl_FX[Rate_to_NGN]) -> 1 | Q53: =IF(tbl_Ledger[[#This Row],[Account_Type]]="Expense",-ABS(tbl_Ledger[[#This Row],[Amount]]*tbl_Ledger[[#This Row],[Rate_to_NGN]]),tbl_Ledger[[#This Row],[Amount]]*tbl_Ledger[[#This Row],[Rate_to_NGN]]) -> 49800 | R53: =_xlfn.XLOOKUP(tbl_Ledger[[#This Row],[Account_Code]], tbl_Accounts[Account_Code], tbl_Accounts[Type]) -> Revenue | S53: =_xlfn.XLOOKUP(tbl_Ledger[[#This Row],[Account_Code]], tbl_Accounts[Account_Code], tbl_Accounts[PL_Bucket]) -> Revenue | T53: =IF(AND(S53="Revenue",F53<>4900),ABS(Q53),-ABS(Q53)) -> 49800
A54: T100045 | B54: 45842 | C54: POS-Square | D54: Zumi Mart | E54: POS-VI | F54: 4000 | G54: Order Revenue | H54: POS-VI daily settlement 2025-07-04 | I54: NGN | J54: 50600 | L54: INV-20250704-POS | N54: =TEXT(tbl_Ledger[[#This Row],[Date]],"yyyy-mm") -> 2025-07 | O54: =TEXT(tbl_Ledger[[#This Row],[Date]],"yyyy-mm") & TRIM(tbl_Ledger[[#This Row],[Currency]]) -> 2025-07NGN | P54: =_xlfn.XLOOKUP(tbl_Ledger[[#This Row],[Key]], tbl_FX[Key], tbl_FX[Rate_to_NGN]) -> 1 | Q54: =IF(tbl_Ledger[[#This Row],[Account_Type]]="Expense",-ABS(tbl_Ledger[[#This Row],[Amount]]*tbl_Ledger[[#This Row],[Rate_to_NGN]]),tbl_Ledger[[#This Row],[Amount]]*tbl_Ledger[[#This Row],[Rate_to_NGN]]) -> 50600 | R54: =_xlfn.XLOOKUP(tbl_Ledger[[#This Row],[Account_Code]], tbl_Accounts[Account_Code], tbl_Accounts[Type]) -> Revenue | S54: =_xlfn.XLOOKUP(tbl_Ledger[[#This Row],[Account_Code]], tbl_Accounts[Account_Code], tbl_Accounts[PL_Bucket]) -> Revenue | T54: =IF(AND(S54="Revenue",F54<>4900),ABS(Q54),-ABS(Q54)) -> 50600
A55: T100046 | B55: 45842 | C55: POS-Square | D55: Zumi Mart | E55: POS-Ikeja | F55: 4000 | G55: Order Revenue | H55: POS-Ikeja daily settlement 2025-07-04 | I55: NGN | J55: 46100 | L55: INV-20250704-POS | N55: =TEXT(tbl_Ledger[[#This Row],[Date]],"yyyy-mm") -> 2025-07 | O55: =TEXT(tbl_Ledger[[#This Row],[Date]],"yyyy-mm") & TRIM(tbl_Ledger[[#This Row],[Currency]]) -> 2025-07NGN | P55: =_xlfn.XLOOKUP(tbl_Ledger[[#This Row],[Key]], tbl_FX[Key], tbl_FX[Rate_to_NGN]) -> 1 | Q55: =IF(tbl_Ledger[[#This Row],[Account_Type]]="Expense",-ABS(tbl_Ledger[[#This Row],[Amount]]*tbl_Ledger[[#This Row],[Rate_to_NGN]]),tbl_Ledger[[#This Row],[Amount]]*tbl_Ledger[[#This Row],[Rate_to_NGN]]) -> 46100 | R55: =_xlfn.XLOOKUP(tbl_Ledger[[#This Row],[Account_Code]], tbl_Accounts[Account_Code], tbl_Accounts[Type]) -> Revenue | S55: =_xlfn.XLOOKUP(tbl_Ledger[[#This Row],[Account_Code]], tbl_Accounts[Account_Code], tbl_Accounts[PL_Bucket]) -> Revenue | T55: =IF(AND(S55="Revenue",F55<>4900),ABS(Q55),-ABS(Q55)) -> 46100
A56: T100047 | B56: 45842 | C56: POS-Square | D56: Zumi Mart | E56: POS-Abuja | F56: 4000 | G56: Order Revenue | H56: POS-Abuja daily settlement 2025-07-04 | I56: NGN | J56: 46200 | L56: INV-20250704-POS | N56: =TEXT(tbl_Ledger[[#This Row],[Date]],"yyyy-mm") -> 2025-07 | O56: =TEXT(tbl_Ledger[[#This Row],[Date]],"yyyy-mm") & TRIM(tbl_Ledger[[#This Row],[Currency]]) -> 2025-07NGN | P56: =_xlfn.XLOOKUP(tbl_Ledger[[#This Row],[Key]], tbl_FX[Key], tbl_FX[Rate_to_NGN]) -> 1 | Q56: =IF(tbl_Ledger[[#This Row],[Account_Type]]="Expense",-ABS(tbl_Ledger[[#This Row],[Amount]]*tbl_Ledger[[#This Row],[Rate_to_NGN]]),tbl_Ledger[[#This Row],[Amount]]*tbl_Ledger[[#This Row],[Rate_to_NGN]]) -> 46200 | R56: =_xlfn.XLOOKUP(tbl_Ledger[[#This Row],[Account_Code]], tbl_Accounts[Account_Code], tbl_Accounts[Type]) -> Revenue | S56: =_xlfn.XLOOKUP(tbl_Ledger[[#This Row],[Account_Code]], tbl_Accounts[Account_Code], tbl_Accounts[PL_Bucket]) -> Revenue | T56: =IF(AND(S56="Revenue",F56<>4900),ABS(Q56),-ABS(Q56)) -> 46200
A57: T100048 | B57: 45842 | C57: POS-Square | D57: Zumi Mart | E57: Online | F57: 4000 | G57: Order Revenue | H57: Online daily settlement 2025-07-04 | I57: NGN | J57: 46900 | L57: INV-20250704-ONL | N57: =TEXT(tbl_Ledger[[#This Row],[Date]],"yyyy-mm") -> 2025-07 | O57: =TEXT(tbl_Ledger[[#This Row],[Date]],"yyyy-mm") & TRIM(tbl_Ledger[[#This Row],[Currency]]) -> 2025-07NGN | P57: =_xlfn.XLOOKUP(tbl_Ledger[[#This Row],[Key]], tbl_FX[Key], tbl_FX[Rate_to_NGN]) -> 1 | Q57: =IF(tbl_Ledger[[#This Row],[Account_Type]]="Expense",-ABS(tbl_Ledger[[#This Row],[Amount]]*tbl_Ledger[[#This Row],[Rate_to_NGN]]),tbl_Ledger[[#This Row],[Amount]]*tbl_Ledger[[#This Row],[Rate_to_NGN]]) -> 46900 | R57: =_xlfn.XLOOKUP(tbl_Ledger[[#This Row],[Account_Code]], tbl_Accounts[Account_Code], tbl_Accounts[Type]) -> Revenue | S57: =_xlfn.XLOOKUP(tbl_Ledger[[#This Row],[Account_Code]], tbl_Accounts[Account_Code], tbl_Accounts[PL_Bucket]) -> Revenue | T57: =IF(AND(S57="Revenue",F57<>4900),ABS(Q57),-ABS(Q57)) -> 46900
A58: T100049 | B58: 45842 | C58: NetSuite | D58: Zumi Logistics | E58: Contract-Dangote | F58: 4020 | G58: Logistics Contract Revenue | H58: Contract-Dangote daily settlement 2025-07-04 | I58: NGN | J58: 44700 | K58: Dangote | L58: INV-20250704-CON | N58: =TEXT(tbl_Ledger[[#This Row],[Date]],"yyyy-mm") -> 2025-07 | O58: =TEXT(tbl_Ledger[[#This Row],[Date]],"yyyy-mm") & TRIM(tbl_Ledger[[#This Row],[Currency]]) -> 2025-07NGN | P58: =_xlfn.XLOOKUP(tbl_Ledger[[#This Row],[Key]], tbl_FX[Key], tbl_FX[Rate_to_NGN]) -> 1 | Q58: =IF(tbl_Ledger[[#This Row],[Account_Type]]="Expense",-ABS(tbl_Ledger[[#This Row],[Amount]]*tbl_Ledger[[#This Row],[Rate_to_NGN]]),tbl_Ledger[[#This Row],[Amount]]*tbl_Ledger[[#This Row],[Rate_to_NGN]]) -> 44700 | R58: =_xlfn.XLOOKUP(tbl_Ledger[[#This Row],[Account_Code]], tbl_Accounts[Account_Code], tbl_Accounts[Type]) -> Revenue | S58: =_xlfn.XLOOKUP(tbl_Ledger[[#This Row],[Account_Code]], tbl_Accounts[Account_Code], tbl_Accounts[PL_Bucket]) -> Revenue | T58: =IF(AND(S58="Revenue",F58<>4900),ABS(Q58),-ABS(Q58)) -> 44700
A59: T100050 | B59: 45842 | C59: NetSuite | D59: Zumi Logistics | E59: Contract-MTN | F59: 4020 | G59: Logistics Contract Revenue | H59: Contract-MTN daily settlement 2025-07-04 | I59: NGN | J59: 39700 | K59: MTN | L59: INV-20250704-CON | N59: =TEXT(tbl_Ledger[[#This Row],[Date]],"yyyy-mm") -> 2025-07 | O59: =TEXT(tbl_Ledger[[#This Row],[Date]],"yyyy-mm") & TRIM(tbl_Ledger[[#This Row],[Currency]]) -> 2025-07NGN | P59: =_xlfn.XLOOKUP(tbl_Ledger[[#This Row],[Key]], tbl_FX[Key], tbl_FX[Rate_to_NGN]) -> 1 | Q59: =IF(tbl_Ledger[[#This Row],[Account_Type]]="Expense",-ABS(tbl_Ledger[[#This Row],[Amount]]*tbl_Ledger[[#This Row],[Rate_to_NGN]]),tbl_Ledger[[#This Row],[Amount]]*tbl_Ledger[[#This Row],[Rate_to_NGN]]) -> 39700 | R59: =_xlfn.XLOOKUP(tbl_Ledger[[#This Row],[Account_Code]], tbl_Accounts[Account_Code], tbl_Accounts[Type]) -> Revenue | S59: =_xlfn.XLOOKUP(tbl_Ledger[[#This Row],[Account_Code]], tbl_Accounts[Account_Code], tbl_Accounts[PL_Bucket]) -> Revenue | T59: =IF(AND(S59="Revenue",F59<>4900),ABS(Q59),-ABS(Q59)) -> 39700
A60: T100051 | B60: 45842 | C60: NetSuite | D60: Zumi Logistics | E60: Contract-Flutterwave | F60: 4020 | G60: Logistics Contract Revenue | H60: Contract-Flutterwave daily settlement 2025-07-04 | I60: NGN | J60: 41800 | K60: Flutterwave | L60: INV-20250704-CON | N60: =TEXT(tbl_Ledger[[#This Row],[Date]],"yyyy-mm") -> 2025-07 | O60: =TEXT(tbl_Ledger[[#This Row],[Date]],"yyyy-mm") & TRIM(tbl_Ledger[[#This Row],[Currency]]) -> 2025-07NGN | P60: =_xlfn.XLOOKUP(tbl_Ledger[[#This Row],[Key]], tbl_FX[Key], tbl_FX[Rate_to_NGN]) -> 1 | Q60: =IF(tbl_Ledger[[#This Row],[Account_Type]]="Expense",-ABS(tbl_Ledger[[#This Row],[Amount]]*tbl_Ledger[[#This Row],[Rate_to_NGN]]),tbl_Ledger[[#This Row],[Amount]]*tbl_Ledger[[#This Row],[Rate_to_NGN]]) -> 41800 | R60: =_xlfn.XLOOKUP(tbl_Ledger[[#This Row],[Account_Code]], tbl_Accounts[Account_Code], tbl_Accounts[Type]) -> Revenue | S60: =_xlfn.XLOOKUP(tbl_Ledger[[#This Row],[Account_Code]], tbl_Accounts[Account_Code], tbl_Accounts[PL_Bucket]) -> Revenue | T60: =IF(AND(S60="Revenue",F60<>4900),ABS(Q60),-ABS(Q60)) -> 41800
A61: T100052 | B61: 45842 | C61: NetSuite | D61: Zumi Logistics | E61: Spot-Market | F61: 4020 | G61: Logistics Contract Revenue | H61: Spot-Market daily settlement 2025-07-04 | I61: NGN | J61: 41500 | L61: INV-20250704-SPO | N61: =TEXT(tbl_Ledger[[#This Row],[Date]],"yyyy-mm") -> 2025-07 | O61: =TEXT(tbl_Ledger[[#This Row],[Date]],"yyyy-mm") & TRIM(tbl_Ledger[[#This Row],[Currency]]) -> 2025-07NGN | P61: =_xlfn.XLOOKUP(tbl_Ledger[[#This Row],[Key]], tbl_FX[Key], tbl_FX[Rate_to_NGN]) -> 1 | Q61: =IF(tbl_Ledger[[#This Row],[Account_Type]]="Expense",-ABS(tbl_Ledger[[#This Row],[Amount]]*tbl_Ledger[[#This Row],[Rate_to_NGN]]),tbl_Ledger[[#This Row],[Amount]]*tbl_Ledger[[#This Row],[Rate_to_NGN]]) -> 41500 | R61: =_xlfn.XLOOKUP(tbl_Ledger[[#This Row],[Account_Code]], tbl_Accounts[Account_Code], tbl_Accounts[Type]) -> Revenue | S61: =_xlfn.XLOOKUP(tbl_Ledger[[#This Row],[Account_Code]], tbl_Accounts[Account_Code], tbl_Accounts[PL_Bucket]) -> Revenue | T61: =IF(AND(S61="Revenue",F61<>4900),ABS(Q61),-ABS(Q61)) -> 41500
A62: T101233 | B62: 45842 | C62: QuickBooks | D62: Zumi Eats | F62: 5020 | G62: Packaging | H62: PackPro Ltd invoice 2025-07 | I62: NGN | J62: -127000 | K62: PackPro Ltd | L62: BILL-83931 | N62: =TEXT(tbl_Ledger[[#This Row],[Date]],"yyyy-mm") -> 2025-07 | O62: =TEXT(tbl_Ledger[[#This Row],[Date]],"yyyy-mm") & TRIM(tbl_Ledger[[#This Row],[Currency]]) -> 2025-07NGN | P62: =_xlfn.XLOOKUP(tbl_Ledger[[#This Row],[Key]], tbl_FX[Key], tbl_FX[Rate_to_NGN]) -> 1 | Q62: =IF(tbl_Ledger[[#This Row],[Account_Type]]="Expense",-ABS(tbl_Ledger[[#This Row],[Amount]]*tbl_Ledger[[#This Row],[Rate_to_NGN]]),tbl_Ledger[[#This Row],[Amount]]*tbl_Ledger[[#This Row],[Rate_to_NGN]]) -> -127000 | R62: =_xlfn.XLOOKUP(tbl_Ledger[[#This Row],[Account_Code]], tbl_Accounts[Account_Code], tbl_Accounts[Type]) -> COGS | S62: =_xlfn.XLOOKUP(tbl_Ledger[[#This Row],[Account_Code]], tbl_Accounts[Account_Code], tbl_Accounts[PL_Bucket]) -> COGS | T62: =IF(AND(S62="Revenue",F62<>4900),ABS(Q62),-ABS(Q62)) -> -127000
A63: T101270 | B63: 45842 | C63: QuickBooks | D63: Zumi Logistics | F63: 5030 | G63: Fuel & Vehicle | H63: Vehicle Maintenance Co invoice 2025-07 | I63: NGN | J63: -324000 | K63: Vehicle Maintenance Co | L63: BILL-84425 | N63: =TEXT(tbl_Ledger[[#This Row],[Date]],"yyyy-mm") -> 2025-07 | O63: =TEXT(tbl_Ledger[[#This Row],[Date]],"yyyy-mm") & TRIM(tbl_Ledger[[#This Row],[Currency]]) -> 2025-07NGN | P63: =_xlfn.XLOOKUP(tbl_Ledger[[#This Row],[Key]], tbl_FX[Key], tbl_FX[Rate_to_NGN]) -> 1 | Q63: =IF(tbl_Ledger[[#This Row],[Account_Type]]="Expense",-ABS(tbl_Ledger[[#This Row],[Amount]]*tbl_Ledger[[#This Row],[Rate_to_NGN]]),tbl_Ledger[[#This Row],[Amount]]*tbl_Ledger[[#This Row],[Rate_to_NGN]]) -> -324000 | R63: =_xlfn.XLOOKUP(tbl_Ledger[[#This Row],[Account_Code]], tbl_Accounts[Account_Code], tbl_Accounts[Type]) -> COGS | S63: =_xlfn.XLOOKUP(tbl_Ledger[[#This Row],[Account_Code]], tbl_Accounts[Account_Code], tbl_Accounts[PL_Bucket]) -> COGS | T63: =IF(AND(S63="Revenue",F63<>4900),ABS(Q63),-ABS(Q63)) -> -324000
A64: T100053 | B64: 45843 | C64: POS-Square | D64: Zumi Eats | E64: Mobile App | F64: 4000 | G64: Order Revenue | H64: Mobile App daily settlement 2025-07-05 | I64: NGN | J64: 35200 | L64: INV-20250705-MOB | N64: =TEXT(tbl_Ledger[[#This Row],[Date]],"yyyy-mm") -> 2025-07 | O64: =TEXT(tbl_Ledger[[#This Row],[Date]],"yyyy-mm") & TRIM(tbl_Ledger[[#This Row],[Currency]]) -> 2025-07NGN | P64: =_xlfn.XLOOKUP(tbl_Ledger[[#This Row],[Key]], tbl_FX[Key], tbl_FX[Rate_to_NGN]) -> 1 | Q64: =IF(tbl_Ledger[[#This Row],[Account_Type]]="Expense",-ABS(tbl_Ledger[[#This Row],[Amount]]*tbl_Ledger[[#This Row],[Rate_to_NGN]]),tbl_Ledger[[#This Row],[Amount]]*tbl_Ledger[[#This Row],[Rate_to_NGN]]) -> 35200 | R64: =_xlfn.XLOOKUP(tbl_Ledger[[#This Row],[Account_Code]], tbl_Accounts[Account_Code], tbl_Accounts[Type]) -> Revenue | S64: =_xlfn.XLOOKUP(tbl_Ledger[[#This Row],[Account_Code]], tbl_Accounts[Account_Code], tbl_Accounts[PL_Bucket]) -> Revenue | T64: =IF(AND(S64="Revenue",F64<>4900),ABS(Q64),-ABS(Q64)) -> 35200
A65: T100054 | B65: 45843 | C65: POS-Square | D65: Zumi Eats | E65: Website | F65: 4000 | G65: Order Revenue | H65: Website daily settlement 2025-07-05 | I65: NGN | J65: 34900 | L65: INV-20250705-WEB | N65: =TEXT(tbl_Ledger[[#This Row],[Date]],"yyyy-mm") -> 2025-07 | O65: =TEXT(tbl_Ledger[[#This Row],[Date]],"yyyy-mm") & TRIM(tbl_Ledger[[#This Row],[Currency]]) -> 2025-07NGN | P65: =_xlfn.XLOOKUP(tbl_Ledger[[#This Row],[Key]], tbl_FX[Key], tbl_FX[Rate_to_NGN]) -> 1 | Q65: =IF(tbl_Ledger[[#This Row],[Account_Type]]="Expense",-ABS(tbl_Ledger[[#This Row],[Amount]]*tbl_Ledger[[#This Row],[Rate_to_NGN]]),tbl_Ledger[[#This Row],[Amount]]*tbl_Ledger[[#This Row],[Rate_to_NGN]]) -> 34900 | R65: =_xlfn.XLOOKUP(tbl_Ledger[[#This Row],[Account_Code]], tbl_Accounts[Account_Code], tbl_Accounts[Type]) -> Revenue | S65: =_xlfn.XLOOKUP(tbl_Ledger[[#This Row],[Account_Code]], tbl_Accounts[Account_Code], tbl_Accounts[PL_Bucket]) -> Revenue | T65: =IF(AND(S65="Revenue",F65<>4900),ABS(Q65),-ABS(Q65)) -> 34900
A66: T100055 | B66: 45843 | C66: POS-Square | D66: Zumi Eats | E66: Aggregator-Glovo | F66: 4000 | G66: Order Revenue | H66: Aggregator-Glovo daily settlement 2025-07-05 | I66: NGN | J66: 35900 | L66: INV-20250705-AGG | N66: =TEXT(tbl_Ledger[[#This Row],[Date]],"yyyy-mm") -> 2025-07 | O66: =TEXT(tbl_Ledger[[#This Row],[Date]],"yyyy-mm") & TRIM(tbl_Ledger[[#This Row],[Currency]]) -> 2025-07NGN | P66: =_xlfn.XLOOKUP(tbl_Ledger[[#This Row],[Key]], tbl_FX[Key], tbl_FX[Rate_to_NGN]) -> 1 | Q66: =IF(tbl_Ledger[[#This Row],[Account_Type]]="Expense",-ABS(tbl_Ledger[[#This Row],[Amount]]*tbl_Ledger[[#This Row],[Rate_to_NGN]]),tbl_Ledger[[#This Row],[Amount]]*tbl_Ledger[[#This Row],[Rate_to_NGN]]) -> 35900 | R66: =_xlfn.XLOOKUP(tbl_Ledger[[#This Row],[Account_Code]], tbl_Accounts[Account_Code], tbl_Accounts[Type]) -> Revenue | S66: =_xlfn.XLOOKUP(tbl_Ledger[[#This Row],[Account_Code]], tbl_Accounts[Account_Code], tbl_Accounts[PL_Bucket]) -> Revenue | T66: =IF(AND(S66="Revenue",F66<>4900),ABS(Q66),-ABS(Q66)) -> 35900
A67: T100056 | B67: 45843 | C67: POS-Square | D67: Zumi Eats | E67: Aggregator-Bolt | F67: 4000 | G67: Order Revenue | H67: Aggregator-Bolt daily settlement 2025-07-05 | I67: NGN | J67: 33100 | L67: INV-20250705-AGG | N67: =TEXT(tbl_Ledger[[#This Row],[Date]],"yyyy-mm") -> 2025-07 | O67: =TEXT(tbl_Ledger[[#This Row],[Date]],"yyyy-mm") & TRIM(tbl_Ledger[[#This Row],[Currency]]) -> 2025-07NGN | P67: =_xlfn.XLOOKUP(tbl_Ledger[[#This Row],[Key]], tbl_FX[Key], tbl_FX[Rate_to_NGN]) -> 1 | Q67: =IF(tbl_Ledger[[#This Row],[Account_Type]]="Expense",-ABS(tbl_Ledger[[#This Row],[Amount]]*tbl_Ledger[[#This Row],[Rate_to_NGN]]),tbl_Ledger[[#This Row],[Amount]]*tbl_Ledger[[#This Row],[Rate_to_NGN]]) -> 33100 | R67: =_xlfn.XLOOKUP(tbl_Ledger[[#This Row],[Account_Code]], tbl_Accounts[Account_Code], tbl_Accounts[Type]) -> Revenue | S67: =_xlfn.XLOOKUP(tbl_Ledger[[#This Row],[Account_Code]], tbl_Accounts[Account_Code], tbl_Accounts[PL_Bucket]) -> Revenue | T67: =IF(AND(S67="Revenue",F67<>4900),ABS(Q67),-ABS(Q67)) -> 33100
A68: T100057 | B68: 45843 | C68: POS-Square | D68: Zumi Eats | E68: Walk-in | F68: 4000 | G68: Order Revenue | H68: Walk-in daily settlement 2025-07-05 | I68: NGN | J68: 39100 | L68: INV-20250705-WAL | N68: =TEXT(tbl_Ledger[[#This Row],[Date]],"yyyy-mm") -> 2025-07 | O68: =TEXT(tbl_Ledger[[#This Row],[Date]],"yyyy-mm") & TRIM(tbl_Ledger[[#This Row],[Currency]]) -> 2025-07NGN | P68: =_xlfn.XLOOKUP(tbl_Ledger[[#This Row],[Key]], tbl_FX[Key], tbl_FX[Rate_to_NGN]) -> 1 | Q68: =IF(tbl_Ledger[[#This Row],[Account_Type]]="Expense",-ABS(tbl_Ledger[[#This Row],[Amount]]*tbl_Ledger[[#This Row],[Rate_to_NGN]]),tbl_Ledger[[#This Row],[Amount]]*tbl_Ledger[[#This Row],[Rate_to_NGN]]) -> 39100 | R68: =_xlfn.XLOOKUP(tbl_Ledger[[#This Row],[Account_Code]], tbl_Accounts[Account_Code], tbl_Accounts[Type]) -> Revenue | S68: =_xlfn.XLOOKUP(tbl_Ledger[[#This Row],[Account_Code]], tbl_Accounts[Account_Code], tbl_Accounts[PL_Bucket]) -> Revenue | T68: =IF(AND(S68="Revenue",F68<>4900),ABS(Q68),-ABS(Q68)) -> 39100
A69: T100058 | B69: 45843 | C69: POS-Square | D69: Zumi Mart | E69: POS-Lekki | F69: 4000 | G69: Order Revenue | H69: POS-Lekki daily settlement 2025-07-05 | I69: NGN | J69: 59500 | L69: INV-20250705-POS | N69: =TEXT(tbl_Ledger[[#This Row],[Date]],"yyyy-mm") -> 2025-07 | O69: =TEXT(tbl_Ledger[[#This Row],[Date]],"yyyy-mm") & TRIM(tbl_Ledger[[#This Row],[Currency]]) -> 2025-07NGN | P69: =_xlfn.XLOOKUP(tbl_Ledger[[#This Row],[Key]], tbl_FX[Key], tbl_FX[Rate_to_NGN]) -> 1 | Q69: =IF(tbl_Ledger[[#This Row],[Account_Type]]="Expense",-ABS(tbl_Ledger[[#This Row],[Amount]]*tbl_Ledger[[#This Row],[Rate_to_NGN]]),tbl_Ledger[[#This Row],[Amount]]*tbl_Ledger[[#This Row],[Rate_to_NGN]]) -> 59500 | R69: =_xlfn.XLOOKUP(tbl_Ledger[[#This Row],[Account_Code]], tbl_Accounts[Account_Code], tbl_Accounts[Type]) -> Revenue | S69: =_xlfn.XLOOKUP(tbl_Ledger[[#This Row],[Account_Code]], tbl_Accounts[Account_Code], tbl_Accounts[PL_Bucket]) -> Revenue | T69: =IF(AND(S69="Revenue",F69<>4900),ABS(Q69),-ABS(Q69)) -> 59500
A70: T100059 | B70: 45843 | C70: POS-Square | D70: Zumi Mart | E70: POS-VI | F70: 4000 | G70: Order Revenue | H70: POS-VI daily settlement 2025-07-05 | I70: NGN | J70: 62700 | L70: INV-20250705-POS | N70: =TEXT(tbl_Ledger[[#This Row],[Date]],"yyyy-mm") -> 2025-07 | O70: =TEXT(tbl_Ledger[[#This Row],[Date]],"yyyy-mm") & TRIM(tbl_Ledger[[#This Row],[Currency]]) -> 2025-07NGN | P70: =_xlfn.XLOOKUP(tbl_Ledger[[#This Row],[Key]], tbl_FX[Key], tbl_FX[Rate_to_NGN]) -> 1 | Q70: =IF(tbl_Ledger[[#This Row],[Account_Type]]="Expense",-ABS(tbl_Ledger[[#This Row],[Amount]]*tbl_Ledger[[#This Row],[Rate_to_NGN]]),tbl_Ledger[[#This Row],[Amount]]*tbl_Ledger[[#This Row],[Rate_to_NGN]]) -> 62700 | R70: =_xlfn.XLOOKUP(tbl_Ledger[[#This Row],[Account_Code]], tbl_Accounts[Account_Code], tbl_Accounts[Type]) -> Revenue | S70: =_xlfn.XLOOKUP(tbl_Ledger[[#This Row],[Account_Code]], tbl_Accounts[Account_Code], tbl_Accounts[PL_Bucket]) -> Revenue | T70: =IF(AND(S70="Revenue",F70<>4900),ABS(Q70),-ABS(Q70)) -> 62700
A71: T100060 | B71: 45843 | C71: POS-Square | D71: Zumi Mart | E71: POS-Abuja | F71: 4000 | G71: Order Revenue | H71: POS-Abuja daily settlement 2025-07-05 | I71: NGN | J71: 58500 | L71: INV-20250705-POS | N71: =TEXT(tbl_Ledger[[#This Row],[Date]],"yyyy-mm") -> 2025-07 | O71: =TEXT(tbl_Ledger[[#This Row],[Date]],"yyyy-mm") & TRIM(tbl_Ledger[[#This Row],[Currency]]) -> 2025-07NGN | P71: =_xlfn.XLOOKUP(tbl_Ledger[[#This Row],[Key]], tbl_FX[Key], tbl_FX[Rate_to_NGN]) -> 1 | Q71: =IF(tbl_Ledger[[#This Row],[Account_Type]]="Expense",-ABS(tbl_Ledger[[#This Row],[Amount]]*tbl_Ledger[[#This Row],[Rate_to_NGN]]),tbl_Ledger[[#This Row],[Amount]]*tbl_Ledger[[#This Row],[Rate_to_NGN]]) -> 58500 | R71: =_xlfn.XLOOKUP(tbl_Ledger[[#This Row],[Account_Code]], tbl_Accounts[Account_Code], tbl_Accounts[Type]) -> Revenue | S71: =_xlfn.XLOOKUP(tbl_Ledger[[#This Row],[Account_Code]], tbl_Accounts[Account_Code], tbl_Accounts[PL_Bucket]) -> Revenue | T71: =IF(AND(S71="Revenue",F71<>4900),ABS(Q71),-ABS(Q71)) -> 58500
A72: T100061 | B72: 45843 | C72: POS-Square | D72: Zumi Mart | E72: Online | F72: 4000 | G72: Order Revenue | H72: Online daily settlement 2025-07-05 | I72: NGN | J72: 62300 | L72: INV-20250705-ONL | N72: =TEXT(tbl_Ledger[[#This Row],[Date]],"yyyy-mm") -> 2025-07 | O72: =TEXT(tbl_Ledger[[#This Row],[Date]],"yyyy-mm") & TRIM(tbl_Ledger[[#This Row],[Currency]]) -> 2025-07NGN | P72: =_xlfn.XLOOKUP(tbl_Ledger[[#This Row],[Key]], tbl_FX[Key], tbl_FX[Rate_to_NGN]) -> 1 | Q72: =IF(tbl_Ledger[[#This Row],[Account_Type]]="Expense",-ABS(tbl_Ledger[[#This Row],[Amount]]*tbl_Ledger[[#This Row],[Rate_to_NGN]]),tbl_Ledger[[#This Row],[Amount]]*tbl_Ledger[[#This Row],[Rate_to_NGN]]) -> 62300 | R72: =_xlfn.XLOOKUP(tbl_Ledger[[#This Row],[Account_Code]], tbl_Accounts[Account_Code], tbl_Accounts[Type]) -> Revenue | S72: =_xlfn.XLOOKUP(tbl_Ledger[[#This Row],[Account_Code]], tbl_Accounts[Account_Code], tbl_Accounts[PL_Bucket]) -> Revenue | T72: =IF(AND(S72="Revenue",F72<>4900),ABS(Q72),-ABS(Q72)) -> 62300
A73: T100062 | B73: 45843 | C73: NetSuite | D73: Zumi Logistics | E73: Contract-MTN | F73: 4020 | G73: Logistics Contract Revenue | H73: Contract-MTN daily settlement 2025-07-05 | I73: USD | J73: 29.28 | K73: MTN | L73: INV-20250705-CON | N73: =TEXT(tbl_Ledger[[#This Row],[Date]],"yyyy-mm") -> 2025-07 | O73: =TEXT(tbl_Ledger[[#This Row],[Date]],"yyyy-mm") & TRIM(tbl_Ledger[[#This Row],[Currency]]) -> 2025-07USD | P73: =_xlfn.XLOOKUP(tbl_Ledger[[#This Row],[Key]], tbl_FX[Key], tbl_FX[Rate_to_NGN]) -> 1530 | Q73: =IF(tbl_Ledger[[#This Row],[Account_Type]]="Expense",-ABS(tbl_Ledger[[#This Row],[Amount]]*tbl_Ledger[[#This Row],[Rate_to_NGN]]),tbl_Ledger[[#This Row],[Amount]]*tbl_Ledger[[#This Row],[Rate_to_NGN]]) -> 44798.4 | R73: =_xlfn.XLOOKUP(tbl_Ledger[[#This Row],[Account_Code]], tbl_Accounts[Account_Code], tbl_Accounts[Type]) -> Revenue | S73: =_xlfn.XLOOKUP(tbl_Ledger[[#This Row],[Account_Code]], tbl_Accounts[Account_Code], tbl_Accounts[PL_Bucket]) -> Revenue | T73: =IF(AND(S73="Revenue",F73<>4900),ABS(Q73),-ABS(Q73)) -> 44798.4
A74: T100063 | B74: 45843 | C74: NetSuite | D74: Zumi Logistics | E74: Contract-Flutterwave | F74: 4020 | G74: Logistics Contract Revenue | H74: Contract-Flutterwave daily settlement 2025-07-05 | I74: USD | J74: 28.24 | K74: Flutterwave | L74: INV-20250705-CON | N74: =TEXT(tbl_Ledger[[#This Row],[Date]],"yyyy-mm") -> 2025-07 | O74: =TEXT(tbl_Ledger[[#This Row],[Date]],"yyyy-mm") & TRIM(tbl_Ledger[[#This Row],[Currency]]) -> 2025-07USD | P74: =_xlfn.XLOOKUP(tbl_Ledger[[#This Row],[Key]], tbl_FX[Key], tbl_FX[Rate_to_NGN]) -> 1530 | Q74: =IF(tbl_Ledger[[#This Row],[Account_Type]]="Expense",-ABS(tbl_Ledger[[#This Row],[Amount]]*tbl_Ledger[[#This Row],[Rate_to_NGN]]),tbl_Ledger[[#This Row],[Amount]]*tbl_Ledger[[#This Row],[Rate_to_NGN]]) -> 43207.2 | R74: =_xlfn.XLOOKUP(tbl_Ledger[[#This Row],[Account_Code]], tbl_Accounts[Account_Code], tbl_Accounts[Type]) -> Revenue | S74: =_xlfn.XLOOKUP(tbl_Ledger[[#This Row],[Account_Code]], tbl_Accounts[Account_Code], tbl_Accounts[PL_Bucket]) -> Revenue | T74: =IF(AND(S74="Revenue",F74<>4900),ABS(Q74),-ABS(Q74)) -> 43207.2
A75: T100064 | B75: 45843 | C75: NetSuite | D75: Zumi Logistics | E75: Spot-Market | F75: 4020 | G75: Logistics Contract Revenue | H75: Spot-Market daily settlement 2025-07-05 | I75: NGN | J75: 42200 | L75: INV-20250705-SPO | N75: =TEXT(tbl_Ledger[[#This Row],[Date]],"yyyy-mm") -> 2025-07 | O75: =TEXT(tbl_Ledger[[#This Row],[Date]],"yyyy-mm") & TRIM(tbl_Ledger[[#This Row],[Currency]]) -> 2025-07NGN | P75: =_xlfn.XLOOKUP(tbl_Ledger[[#This Row],[Key]], tbl_FX[Key], tbl_FX[Rate_to_NGN]) -> 1 | Q75: =IF(tbl_Ledger[[#This Row],[Account_Type]]="Expense",-ABS(tbl_Ledger[[#This Row],[Amount]]*tbl_Ledger[[#This Row],[Rate_to_NGN]]),tbl_Ledger[[#This Row],[Amount]]*tbl_Ledger[[#This Row],[Rate_to_NGN]]) -> 42200 | R75: =_xlfn.XLOOKUP(tbl_Ledger[[#This Row],[Account_Code]], tbl_Accounts[Account_Code], tbl_Accounts[Type]) -> Revenue | S75: =_xlfn.XLOOKUP(tbl_Ledger[[#This Row],[Account_Code]], tbl_Accounts[Account_Code], tbl_Accounts[PL_Bucket]) -> Revenue | T75: =IF(AND(S75="Revenue",F75<>4900),ABS(Q75),-ABS(Q75)) -> 42200
A76: T101225 | B76: 45843 | C76: QuickBooks | D76: Zumi Eats | F76: 5000 | G76: Food Cost | H76: FreshFarms NG invoice 2025-07 | I76: NGN | J76: -453000 | K76: FreshFarms NG | L76: BILL-1434 | N76: =TEXT(tbl_Ledger[[#This Row],[Date]],"yyyy-mm") -> 2025-07 | O76: =TEXT(tbl_Ledger[[#This Row],[Date]],"yyyy-mm") & TRIM(tbl_Ledger[[#This Row],[Currency]]) -> 2025-07NGN | P76: =_xlfn.XLOOKUP(tbl_Ledger[[#This Row],[Key]], tbl_FX[Key], tbl_FX[Rate_to_NGN]) -> 1 | Q76: =IF(tbl_Ledger[[#This Row],[Account_Type]]="Expense",-ABS(tbl_Ledger[[#This Row],[Amount]]*tbl_Ledger[[#This Row],[Rate_to_NGN]]),tbl_Ledger[[#This Row],[Amount]]*tbl_Ledger[[#This Row],[Rate_to_NGN]]) -> -453000 | R76: =_xlfn.XLOOKUP(tbl_Ledger[[#This Row],[Account_Code]], tbl_Accounts[Account_Code], tbl_Accounts[Type]) -> COGS | S76: =_xlfn.XLOOKUP(tbl_Ledger[[#This Row],[Account_Code]], tbl_Accounts[Account_Code], tbl_Accounts[PL_Bucket]) -> COGS | T76: =IF(AND(S76="Revenue",F76<>4900),ABS(Q76),-ABS(Q76)) -> -453000
A77: T101386 | B77: 45843 | C77: QuickBooks | D77: Zumi Eats | F77: 6010 | G77: Rent | H77: Office & store rent 2025-07 | I77: NGN | J77: -720000 | K77: Property Holdings Ltd | L77: RENT-2025-07-EAT | N77: =TEXT(tbl_Ledger[[#This Row],[Date]],"yyyy-mm") -> 2025-07 | O77: =TEXT(tbl_Ledger[[#This Row],[Date]],"yyyy-mm") & TRIM(tbl_Ledger[[#This Row],[Currency]]) -> 2025-07NGN | P77: =_xlfn.XLOOKUP(tbl_Ledger[[#This Row],[Key]], tbl_FX[Key], tbl_FX[Rate_to_NGN]) -> 1 | Q77: =IF(tbl_Ledger[[#This Row],[Account_Type]]="Expense",-ABS(tbl_Ledger[[#This Row],[Amount]]*tbl_Ledger[[#This Row],[Rate_to_NGN]]),tbl_Ledger[[#This Row],[Amount]]*tbl_Ledger[[#This Row],[Rate_to_NGN]]) -> -720000 | R77: =_xlfn.XLOOKUP(tbl_Ledger[[#This Row],[Account_Code]], tbl_Accounts[Account_Code], tbl_Accounts[Type]) -> Opex | S77: =_xlfn.XLOOKUP(tbl_Ledger[[#This Row],[Account_Code]], tbl_Accounts[Account_Code], tbl_Accounts[PL_Bucket]) -> Opex | T77: =IF(AND(S77="Revenue",F77<>4900),ABS(Q77),-ABS(Q77)) -> -720000
A78: T101388 | B78: 45843 | C78: QuickBooks | D78: Zumi Mart | F78: 6010 | G78: Rent | H78: Office & store rent 2025-07 | I78: NGN | J78: -1400000 | K78: Property Holdings Ltd | L78: RENT-2025-07-MAR | N78: =TEXT(tbl_Ledger[[#This Row],[Date]],"yyyy-mm") -> 2025-07 | O78: =TEXT(tbl_Ledger[[#This Row],[Date]],"yyyy-mm") & TRIM(tbl_Ledger[[#This Row],[Currency]]) -> 2025-07NGN | P78: =_xlfn.XLOOKUP(tbl_Ledger[[#This Row],[Key]], tbl_FX[Key], tbl_FX[Rate_to_NGN]) -> 1 | Q78: =IF(tbl_Ledger[[#This Row],[Account_Type]]="Expense",-ABS(tbl_Ledger[[#This Row],[Amount]]*tbl_Ledger[[#This Row],[Rate_to_NGN]]),tbl_Ledger[[#This Row],[Amount]]*tbl_Ledger[[#This Row],[Rate_to_NGN]]) -> -1400000 | R78: =_xlfn.XLOOKUP(tbl_Ledger[[#This Row],[Account_Code]], tbl_Accounts[Account_Code], tbl_Accounts[Type]) -> Opex | S78: =_xlfn.XLOOKUP(tbl_Ledger[[#This Row],[Account_Code]], tbl_Accounts[Account_Code], tbl_Accounts[PL_Bucket]) -> Opex | T78: =IF(AND(S78="Revenue",F78<>4900),ABS(Q78),-ABS(Q78)) -> -1400000
A79: T101390 | B79: 45843 | C79: QuickBooks | D79: Zumi Logistics | F79: 6010 | G79: Rent | H79: Office & store rent 2025-07 | I79: NGN | J79: -380000 | K79: Property Holdings Ltd | L79: RENT-2025-07-LOG | N79: =TEXT(tbl_Ledger[[#This Row],[Date]],"yyyy-mm") -> 2025-07 | O79: =TEXT(tbl_Ledger[[#This Row],[Date]],"yyyy-mm") & TRIM(tbl_Ledger[[#This Row],[Currency]]) -> 2025-07NGN | P79: =_xlfn.XLOOKUP(tbl_Ledger[[#This Row],[Key]], tbl_FX[Key], tbl_FX[Rate_to_NGN]) -> 1 | Q79: =IF(tbl_Ledger[[#This Row],[Account_Type]]="Expense",-ABS(tbl_Ledger[[#This Row],[Amount]]*tbl_Ledger[[#This Row],[Rate_to_NGN]]),tbl_Ledger[[#This Row],[Amount]]*tbl_Ledger[[#This Row],[Rate_to_NGN]]) -> -380000 | R79: =_xlfn.XLOOKUP(tbl_Ledger[[#This Row],[Account_Code]], tbl_Accounts[Account_Code], tbl_Accounts[Type]) -> Opex | S79: =_xlfn.XLOOKUP(tbl_Ledger[[#This Row],[Account_Code]], tbl_Accounts[Account_Code], tbl_Accounts[PL_Bucket]) -> Opex | T79: =IF(AND(S79="Revenue",F79<>4900),ABS(Q79),-ABS(Q79)) -> -380000
A80: T100065 | B80: 45844 | C80: POS-Square | D80: Zumi Eats | E80: Website | F80: 4000 | G80: Order Revenue | H80: Website daily settlement 2025-07-06 | I80: NGN | J80: 33300 | L80: INV-20250706-WEB | N80: =TEXT(tbl_Ledger[[#This Row],[Date]],"yyyy-mm") -> 2025-07 | O80: =TEXT(tbl_Ledger[[#This Row],[Date]],"yyyy-mm") & TRIM(tbl_Ledger[[#This Row],[Currency]]) -> 2025-07NGN | P80: =_xlfn.XLOOKUP(tbl_Ledger[[#This Row],[Key]], tbl_FX[Key], tbl_FX[Rate_to_NGN]) -> 1 | Q80: =IF(tbl_Ledger[[#This Row],[Account_Type]]="Expense",-ABS(tbl_Ledger[[#This Row],[Amount]]*tbl_Ledger[[#This Row],[Rate_to_NGN]]),tbl_Ledger[[#This Row],[Amount]]*tbl_Ledger[[#This Row],[Rate_to_NGN]]) -> 33300 | R80: =_xlfn.XLOOKUP(tbl_Ledger[[#This Row],[Account_Code]], tbl_Accounts[Account_Code], tbl_Accounts[Type]) -> Revenue | S80: =_xlfn.XLOOKUP(tbl_Ledger[[#This Row],[Account_Code]], tbl_Accounts[Account_Code], tbl_Accounts[PL_Bucket]) -> Revenue | T80: =IF(AND(S80="Revenue",F80<>4900),ABS(Q80),-ABS(Q80)) -> 33300
A81: T100066 | B81: 45844 | C81: POS-Square | D81: Zumi Eats | E81: Aggregator-Glovo | F81: 4000 | G81: Order Revenue | H81: Aggregator-Glovo daily settlement 2025-07-06 | I81: NGN | J81: 35100 | L81: INV-20250706-AGG | N81: =TEXT(tbl_Ledger[[#This Row],[Date]],"yyyy-mm") -> 2025-07 | O81: =TEXT(tbl_Ledger[[#This Row],[Date]],"yyyy-mm") & TRIM(tbl_Ledger[[#This Row],[Currency]]) -> 2025-07NGN | P81: =_xlfn.XLOOKUP(tbl_Ledger[[#This Row],[Key]], tbl_FX[Key], tbl_FX[Rate_to_NGN]) -> 1 | Q81: =IF(tbl_Ledger[[#This Row],[Account_Type]]="Expense",-ABS(tbl_Ledger[[#This Row],[Amount]]*tbl_Ledger[[#This Row],[Rate_to_NGN]]),tbl_Ledger[[#This Row],[Amount]]*tbl_Ledger[[#This Row],[Rate_to_NGN]]) -> 35100 | R81: =_xlfn.XLOOKUP(tbl_Ledger[[#This Row],[Account_Code]], tbl_Accounts[Account_Code], tbl_Accounts[Type]) -> Revenue | S81: =_xlfn.XLOOKUP(tbl_Ledger[[#This Row],[Account_Code]], tbl_Accounts[Account_Code], tbl_Accounts[PL_Bucket]) -> Revenue | T81: =IF(AND(S81="Revenue",F81<>4900),ABS(Q81),-ABS(Q81)) -> 35100
A82: T100067 | B82: 45844 | C82: POS-Square | D82: Zumi Eats | E82: Aggregator-Bolt | F82: 4000 | G82: Order Revenue | H82: Aggregator-Bolt daily settlement 2025-07-06 | I82: NGN | J82: 39000 | L82: INV-20250706-AGG | N82: =TEXT(tbl_Ledger[[#This Row],[Date]],"yyyy-mm") -> 2025-07 | O82: =TEXT(tbl_Ledger[[#This Row],[Date]],"yyyy-mm") & TRIM(tbl_Ledger[[#This Row],[Currency]]) -> 2025-07NGN | P82: =_xlfn.XLOOKUP(tbl_Ledger[[#This Row],[Key]], tbl_FX[Key], tbl_FX[Rate_to_NGN]) -> 1 | Q82: =IF(tbl_Ledger[[#This Row],[Account_Type]]="Expense",-ABS(tbl_Ledger[[#This Row],[Amount]]*tbl_Ledger[[#This Row],[Rate_to_NGN]]),tbl_Ledger[[#This Row],[Amount]]*tbl_Ledger[[#This Row],[Rate_to_NGN]]) -> 39000 | R82: =_xlfn.XLOOKUP(tbl_Ledger[[#This Row],[Account_Code]], tbl_Accounts[Account_Code], tbl_Accounts[Type]) -> Revenue | S82: =_xlfn.XLOOKUP(tbl_Ledger[[#This Row],[Account_Code]], tbl_Accounts[Account_Code], tbl_Accounts[PL_Bucket]) -> Revenue | T82: =IF(AND(S82="Revenue",F82<>4900),ABS(Q82),-ABS(Q82)) -> 39000
A83: T100068 | B83: 45844 | C83: POS-Square | D83: Zumi Eats | E83: Walk-in | F83: 4000 | G83: Order Revenue | H83: Walk-in daily settlement 2025-07-06 | I83: NGN | J83: 36900 | L83: INV-20250706-WAL | N83: =TEXT(tbl_Ledger[[#This Row],[Date]],"yyyy-mm") -> 2025-07 | O83: =TEXT(tbl_Ledger[[#This Row],[Date]],"yyyy-mm") & TRIM(tbl_Ledger[[#This Row],[Currency]]) -> 2025-07NGN | P83: =_xlfn.XLOOKUP(tbl_Ledger[[#This Row],[Key]], tbl_FX[Key], tbl_FX[Rate_to_NGN]) -> 1 | Q83: =IF(tbl_Ledger[[#This Row],[Account_Type]]="Expense",-ABS(tbl_Ledger[[#This Row],[Amount]]*tbl_Ledger[[#This Row],[Rate_to_NGN]]),tbl_Ledger[[#This Row],[Amount]]*tbl_Ledger[[#This Row],[Rate_to_NGN]]) -> 36900 | R83: =_xlfn.XLOOKUP(tbl_Ledger[[#This Row],[Account_Code]], tbl_Accounts[Account_Code], tbl_Accounts[Type]) -> Revenue | S83: =_xlfn.XLOOKUP(tbl_Ledger[[#This Row],[Account_Code]], tbl_Accounts[Account_Code], tbl_Accounts[PL_Bucket]) -> Revenue | T83: =IF(AND(S83="Revenue",F83<>4900),ABS(Q83),-ABS(Q83)) -> 36900
A84: T100069 | B84: 45844 | C84: POS-Square | D84: Zumi Mart | E84: POS-VI | F84: 4000 | G84: Order Revenue | H84: POS-VI daily settlement 2025-07-06 | I84: NGN | J84: 59700 | L84: INV-20250706-POS | N84: =TEXT(tbl_Ledger[[#This Row],[Date]],"yyyy-mm") -> 2025-07 | O84: =TEXT(tbl_Ledger[[#This Row],[Date]],"yyyy-mm") & TRIM(tbl_Ledger[[#This Row],[Currency]]) -> 2025-07NGN | P84: =_xlfn.XLOOKUP(tbl_Ledger[[#This Row],[Key]], tbl_FX[Key], tbl_FX[Rate_to_NGN]) -> 1 | Q84: =IF(tbl_Ledger[[#This Row],[Account_Type]]="Expense",-ABS(tbl_Ledger[[#This Row],[Amount]]*tbl_Ledger[[#This Row],[Rate_to_NGN]]),tbl_Ledger[[#This Row],[Amount]]*tbl_Ledger[[#This Row],[Rate_to_NGN]]) -> 59700 | R84: =_xlfn.XLOOKUP(tbl_Ledger[[#This Row],[Account_Code]], tbl_Accounts[Account_Code], tbl_Accounts[Type]) -> Revenue | S84: =_xlfn.XLOOKUP(tbl_Ledger[[#This Row],[Account_Code]], tbl_Accounts[Account_Code], tbl_Accounts[PL_Bucket]) -> Revenue | T84: =IF(AND(S84="Revenue",F84<>4900),ABS(Q84),-ABS(Q84)) -> 59700
A85: T100070 | B85: 45844 | C85: POS-Square | D85: Zumi Mart | E85: POS-Ikeja | F85: 4000 | G85: Order Revenue | H85: POS-Ikeja daily settlement 2025-07-06 | I85: NGN | J85: 59500 | L85: INV-20250706-POS | N85: =TEXT(tbl_Ledger[[#This Row],[Date]],"yyyy-mm") -> 2025-07 | O85: =TEXT(tbl_Ledger[[#This Row],[Date]],"yyyy-mm") & TRIM(tbl_Ledger[[#This Row],[Currency]]) -> 2025-07NGN | P85: =_xlfn.XLOOKUP(tbl_Ledger[[#This Row],[Key]], tbl_FX[Key], tbl_FX[Rate_to_NGN]) -> 1 | Q85: =IF(tbl_Ledger[[#This Row],[Account_Type]]="Expense",-ABS(tbl_Ledger[[#This Row],[Amount]]*tbl_Ledger[[#This Row],[Rate_to_NGN]]),tbl_Ledger[[#This Row],[Amount]]*tbl_Ledger[[#This Row],[Rate_to_NGN]]) -> 59500 | R85: =_xlfn.XLOOKUP(tbl_Ledger[[#This Row],[Account_Code]], tbl_Accounts[Account_Code], tbl_Accounts[Type]) -> Revenue | S85: =_xlfn.XLOOKUP(tbl_Ledger[[#This Row],[Account_Code]], tbl_Accounts[Account_Code], tbl_Accounts[PL_Bucket]) -> Revenue | T85: =IF(AND(S85="Revenue",F85<>4900),ABS(Q85),-ABS(Q85)) -> 59500
A86: T100071 | B86: 45844 | C86: POS-Square | D86: Zumi Mart | E86: POS-Abuja | F86: 4000 | G86: Order Revenue | H86: POS-Abuja daily settlement 2025-07-06 | I86: NGN | J86: 58400 | L86: INV-20250706-POS | N86: =TEXT(tbl_Ledger[[#This Row],[Date]],"yyyy-mm") -> 2025-07 | O86: =TEXT(tbl_Ledger[[#This Row],[Date]],"yyyy-mm") & TRIM(tbl_Ledger[[#This Row],[Currency]]) -> 2025-07NGN | P86: =_xlfn.XLOOKUP(tbl_Ledger[[#This Row],[Key]], tbl_FX[Key], tbl_FX[Rate_to_NGN]) -> 1 | Q86: =IF(tbl_Ledger[[#This Row],[Account_Type]]="Expense",-ABS(tbl_Ledger[[#This Row],[Amount]]*tbl_Ledger[[#This Row],[Rate_to_NGN]]),tbl_Ledger[[#This Row],[Amount]]*tbl_Ledger[[#This Row],[Rate_to_NGN]]) -> 58400 | R86: =_xlfn.XLOOKUP(tbl_Ledger[[#This Row],[Account_Code]], tbl_Accounts[Account_Code], tbl_Accounts[Type]) -> Revenue | S86: =_xlfn.XLOOKUP(tbl_Ledger[[#This Row],[Account_Code]], tbl_Accounts[Account_Code], tbl_Accounts[PL_Bucket]) -> Revenue | T86: =IF(AND(S86="Revenue",F86<>4900),ABS(Q86),-ABS(Q86)) -> 58400
A87: T100072 | B87: 45844 | C87: POS-Square | D87: Zumi Mart | E87: Online | F87: 4000 | G87: Order Revenue | H87: Online daily settlement 2025-07-06 | I87: NGN | J87: 62500 | L87: INV-20250706-ONL | N87: =TEXT(tbl_Ledger[[#This Row],[Date]],"yyyy-mm") -> 2025-07 | O87: =TEXT(tbl_Ledger[[#This Row],[Date]],"yyyy-mm") & TRIM(tbl_Ledger[[#This Row],[Currency]]) -> 2025-07NGN | P87: =_xlfn.XLOOKUP(tbl_Ledger[[#This Row],[Key]], tbl_FX[Key], tbl_FX[Rate_to_NGN]) -> 1 | Q87: =IF(tbl_Ledger[[#This Row],[Account_Type]]="Expense",-ABS(tbl_Ledger[[#This Row],[Amount]]*tbl_Ledger[[#This Row],[Rate_to_NGN]]),tbl_Ledger[[#This Row],[Amount]]*tbl_Ledger[[#This Row],[Rate_to_NGN]]) -> 62500 | R87: =_xlfn.XLOOKUP(tbl_Ledger[[#This Row],[Account_Code]], tbl_Accounts[Account_Code], tbl_Accounts[Type]) -> Revenue | S87: =_xlfn.XLOOKUP(tbl_Ledger[[#This Row],[Account_Code]], tbl_Accounts[Account_Code], tbl_Accounts[PL_Bucket]) -> Revenue | T87: =IF(AND(S87="Revenue",F87<>4900),ABS(Q87),-ABS(Q87)) -> 62500
A88: T100073 | B88: 45844 | C88: NetSuite | D88: Zumi Logistics | E88: Contract-Dangote | F88: 4020 | G88: Logistics Contract Revenue | H88: Contract-Dangote daily settlement 2025-07-06 | I88: USD | J88: 30.07 | K88: Dangote | L88: INV-20250706-CON | N88: =TEXT(tbl_Ledger[[#This Row],[Date]],"yyyy-mm") -> 2025-07 | O88: =TEXT(tbl_Ledger[[#This Row],[Date]],"yyyy-mm") & TRIM(tbl_Ledger[[#This Row],[Currency]]) -> 2025-07USD | P88: =_xlfn.XLOOKUP(tbl_Ledger[[#This Row],[Key]], tbl_FX[Key], tbl_FX[Rate_to_NGN]) -> 1530 | Q88: =IF(tbl_Ledger[[#This Row],[Account_Type]]="Expense",-ABS(tbl_Ledger[[#This Row],[Amount]]*tbl_Ledger[[#This Row],[Rate_to_NGN]]),tbl_Ledger[[#This Row],[Amount]]*tbl_Ledger[[#This Row],[Rate_to_NGN]]) -> 46007.1 | R88: =_xlfn.XLOOKUP(tbl_Ledger[[#This Row],[Account_Code]], tbl_Accounts[Account_Code], tbl_Accounts[Type]) -> Revenue | S88: =_xlfn.XLOOKUP(tbl_Ledger[[#This Row],[Account_Code]], tbl_Accounts[Account_Code], tbl_Accounts[PL_Bucket]) -> Revenue | T88: =IF(AND(S88="Revenue",F88<>4900),ABS(Q88),-ABS(Q88)) -> 46007.1
A89: T100074 | B89: 45844 | C89: NetSuite | D89: Zumi Logistics | E89: Contract-MTN | F89: 4020 | G89: Logistics Contract Revenue | H89: Contract-MTN daily settlement 2025-07-06 | I89: USD | J89: 28.04 | K89: MTN | L89: INV-20250706-CON | N89: =TEXT(tbl_Ledger[[#This Row],[Date]],"yyyy-mm") -> 2025-07 | O89: =TEXT(tbl_Ledger[[#This Row],[Date]],"yyyy-mm") & TRIM(tbl_Ledger[[#This Row],[Currency]]) -> 2025-07USD | P89: =_xlfn.XLOOKUP(tbl_Ledger[[#This Row],[Key]], tbl_FX[Key], tbl_FX[Rate_to_NGN]) -> 1530 | Q89: =IF(tbl_Ledger[[#This Row],[Account_Type]]="Expense",-ABS(tbl_Ledger[[#This Row],[Amount]]*tbl_Ledger[[#This Row],[Rate_to_NGN]]),tbl_Ledger[[#This Row],[Amount]]*tbl_Ledger[[#This Row],[Rate_to_NGN]]) -> 42901.2 | R89: =_xlfn.XLOOKUP(tbl_Ledger[[#This Row],[Account_Code]], tbl_Accounts[Account_Code], tbl_Accounts[Type]) -> Revenue | S89: =_xlfn.XLOOKUP(tbl_Ledger[[#This Row],[Account_Code]], tbl_Accounts[Account_Code], tbl_Accounts[PL_Bucket]) -> Revenue | T89: =IF(AND(S89="Revenue",F89<>4900),ABS(Q89),-ABS(Q89)) -> 42901.2
A90: T100075 | B90: 45844 | C90: NetSuite | D90: Zumi Logistics | E90: Contract-Flutterwave | F90: 4020 | G90: Logistics Contract Revenue | H90: Contract-Flutterwave daily settlement 2025-07-06 | I90: NGN | J90: 47000 | K90: Flutterwave | L90: INV-20250706-CON | N90: =TEXT(tbl_Ledger[[#This Row],[Date]],"yyyy-mm") -> 2025-07 | O90: =TEXT(tbl_Ledger[[#This Row],[Date]],"yyyy-mm") & TRIM(tbl_Ledger[[#This Row],[Currency]]) -> 2025-07NGN | P90: =_xlfn.XLOOKUP(tbl_Ledger[[#This Row],[Key]], tbl_FX[Key], tbl_FX[Rate_to_NGN]) -> 1 | Q90: =IF(tbl_Ledger[[#This Row],[Account_Type]]="Expense",-ABS(tbl_Ledger[[#This Row],[Amount]]*tbl_Ledger[[#This Row],[Rate_to_NGN]]),tbl_Ledger[[#This Row],[Amount]]*tbl_Ledger[[#This Row],[Rate_to_NGN]]) -> 47000 | R90: =_xlfn.XLOOKUP(tbl_Ledger[[#This Row],[Account_Code]], tbl_Accounts[Account_Code], tbl_Accounts[Type]) -> Revenue | S90: =_xlfn.XLOOKUP(tbl_Ledger[[#This Row],[Account_Code]], tbl_Accounts[Account_Code], tbl_Accounts[PL_Bucket]) -> Revenue | T90: =IF(AND(S90="Revenue",F90<>4900),ABS(Q90),-ABS(Q90)) -> 47000
A91: T100076 | B91: 45844 | C91: NetSuite | D91: Zumi Logistics | E91: Spot-Market | F91: 4020 | G91: Logistics Contract Revenue | H91: Spot-Market daily settlement 2025-07-06 | I91: NGN | J91: 41500 | L91: INV-20250706-SPO | N91: =TEXT(tbl_Ledger[[#This Row],[Date]],"yyyy-mm") -> 2025-07 | O91: =TEXT(tbl_Ledger[[#This Row],[Date]],"yyyy-mm") & TRIM(tbl_Ledger[[#This Row],[Currency]]) -> 2025-07NGN | P91: =_xlfn.XLOOKUP(tbl_Ledger[[#This Row],[Key]], tbl_FX[Key], tbl_FX[Rate_to_NGN]) -> 1 | Q91: =IF(tbl_Ledger[[#This Row],[Account_Type]]="Expense",-ABS(tbl_Ledger[[#This Row],[Amount]]*tbl_Ledger[[#This Row],[Rate_to_NGN]]),tbl_Ledger[[#This Row],[Amount]]*tbl_Ledger[[#This Row],[Rate_to_NGN]]) -> 41500 | R91: =_xlfn.XLOOKUP(tbl_Ledger[[#This Row],[Account_Code]], tbl_Accounts[Account_Code], tbl_Accounts[Type]) -> Revenue | S91: =_xlfn.XLOOKUP(tbl_Ledger[[#This Row],[Account_Code]], tbl_Accounts[Account_Code], tbl_Accounts[PL_Bucket]) -> Revenue | T91: =IF(AND(S91="Revenue",F91<>4900),ABS(Q91),-ABS(Q91)) -> 41500
A92: T101205 | B92: 45844 | C92: POS-Square | D92: Zumi Mart | E92: POS-Lekki | F92: 4900 | G92: Refunds & Chargebacks | H92: Customer refund order #180159 | I92: NGN | J92: 68559 | L92: RFD-5431 | M92: FLAG: booked positive | N92: =TEXT(tbl_Ledger[[#This Row],[Date]],"yyyy-mm") -> 2025-07 | O92: =TEXT(tbl_Ledger[[#This Row],[Date]],"yyyy-mm") & TRIM(tbl_Ledger[[#This Row],[Currency]]) -> 2025-07NGN | P92: =_xlfn.XLOOKUP(tbl_Ledger[[#This Row],[Key]], tbl_FX[Key], tbl_FX[Rate_to_NGN]) -> 1 | Q92: =IF(tbl_Ledger[[#This Row],[Account_Type]]="Expense",-ABS(tbl_Ledger[[#This Row],[Amount]]*tbl_Ledger[[#This Row],[Rate_to_NGN]]),tbl_Ledger[[#This Row],[Amount]]*tbl_Ledger[[#This Row],[Rate_to_NGN]]) -> 68559 | R92: =_xlfn.XLOOKUP(tbl_Ledger[[#This Row],[Account_Code]], tbl_Accounts[Account_Code], tbl_Accounts[Type]) -> Revenue | S92: =_xlfn.XLOOKUP(tbl_Ledger[[#This Row],[Account_Code]], tbl_Accounts[Account_Code], tbl_Accounts[PL_Bucket]) -> Revenue | T92: =IF(AND(S92="Revenue",F92<>4900),ABS(Q92),-ABS(Q92)) -> 68559
A93: T101263 | B93: 45844 | C93: QuickBooks | D93: Zumi Logistics | F93: 5030 | G93: Fuel & Vehicle | H93: NNPC Retail invoice 2025-07 | I93: NGN | J93: -562000 | K93: NNPC Retail | L93: BILL-25529 | N93: =TEXT(tbl_Ledger[[#This Row],[Date]],"yyyy-mm") -> 2025-07 | O93: =TEXT(tbl_Ledger[[#This Row],[Date]],"yyyy-mm") & TRIM(tbl_Ledger[[#This Row],[Currency]]) -> 2025-07NGN | P93: =_xlfn.XLOOKUP(tbl_Ledger[[#This Row],[Key]], tbl_FX[Key], tbl_FX[Rate_to_NGN]) -> 1 | Q93: =IF(tbl_Ledger[[#This Row],[Account_Type]]="Expense",-ABS(tbl_Ledger[[#This Row],[Amount]]*tbl_Ledger[[#This Row],[Rate_to_NGN]]),tbl_Ledger[[#This Row],[Amount]]*tbl_Ledger[[#This Row],[Rate_to_NGN]]) -> -562000 | R93: =_xlfn.XLOOKUP(tbl_Ledger[[#This Row],[Account_Code]], tbl_Accounts[Account_Code], tbl_Accounts[Type]) -> COGS | S93: =_xlfn.XLOOKUP(tbl_Ledger[[#This Row],[Account_Code]], tbl_Accounts[Account_Code], tbl_Accounts[PL_Bucket]) -> COGS | T93: =IF(AND(S93="Revenue",F93<>4900),ABS(Q93),-ABS(Q93)) -> -562000
A94: T100077 | B94: 45845 | C94: POS-Square | D94: Zumi Eats | E94: Mobile App | F94: 4000 | G94: Order Revenue | H94: Mobile App daily settlement 2025-07-07 | I94: NGN | J94: 26500 | L94: INV-20250707-MOB | N94: =TEXT(tbl_Ledger[[#This Row],[Date]],"yyyy-mm") -> 2025-07 | O94: =TEXT(tbl_Ledger[[#This Row],[Date]],"yyyy-mm") & TRIM(tbl_Ledger[[#This Row],[Currency]]) -> 2025-07NGN | P94: =_xlfn.XLOOKUP(tbl_Ledger[[#This Row],[Key]], tbl_FX[Key], tbl_FX[Rate_to_NGN]) -> 1 | Q94: =IF(tbl_Ledger[[#This Row],[Account_Type]]="Expense",-ABS(tbl_Ledger[[#This Row],[Amount]]*tbl_Ledger[[#This Row],[Rate_to_NGN]]),tbl_Ledger[[#This Row],[Amount]]*tbl_Ledger[[#This Row],[Rate_to_NGN]]) -> 26500 | R94: =_xlfn.XLOOKUP(tbl_Ledger[[#This Row],[Account_Code]], tbl_Accounts[Account_Code], tbl_Accounts[Type]) -> Revenue | S94: =_xlfn.XLOOKUP(tbl_Ledger[[#This Row],[Account_Code]], tbl_Accounts[Account_Code], tbl_Accounts[PL_Bucket]) -> Revenue | T94: =IF(AND(S94="Revenue",F94<>4900),ABS(Q94),-ABS(Q94)) -> 26500
A95: T100078 | B95: 45845 | C95: POS-Square | D95: Zumi Eats | E95: Website | F95: 4000 | G95: Order Revenue | H95: Website daily settlement 2025-07-07 | I95: NGN | J95: 27800 | L95: INV-20250707-WEB | N95: =TEXT(tbl_Ledger[[#This Row],[Date]],"yyyy-mm") -> 2025-07 | O95: =TEXT(tbl_Ledger[[#This Row],[Date]],"yyyy-mm") & TRIM(tbl_Ledger[[#This Row],[Currency]]) -> 2025-07NGN | P95: =_xlfn.XLOOKUP(tbl_Ledger[[#This Row],[Key]], tbl_FX[Key], tbl_FX[Rate_to_NGN]) -> 1 | Q95: =IF(tbl_Ledger[[#This Row],[Account_Type]]="Expense",-ABS(tbl_Ledger[[#This Row],[Amount]]*tbl_Ledger[[#This Row],[Rate_to_NGN]]),tbl_Ledger[[#This Row],[Amount]]*tbl_Ledger[[#This Row],[Rate_to_NGN]]) -> 27800 | R95: =_xlfn.XLOOKUP(tbl_Ledger[[#This Row],[Account_Code]], tbl_Accounts[Account_Code], tbl_Accounts[Type]) -> Revenue | S95: =_xlfn.XLOOKUP(tbl_Ledger[[#This Row],[Account_Code]], tbl_Accounts[Account_Code], tbl_Accounts[PL_Bucket]) -> Revenue | T95: =IF(AND(S95="Revenue",F95<>4900),ABS(Q95),-ABS(Q95)) -> 27800
A96: T100079 | B96: 45845 | C96: POS-Square | D96: Zumi Eats | E96: Aggregator-Glovo | F96: 4000 | G96: Order Revenue | H96: Aggregator-Glovo daily settlement 2025-07-07 | I96: NGN | J96: 28300 | L96: INV-20250707-AGG | N96: =TEXT(tbl_Ledger[[#This Row],[Date]],"yyyy-mm") -> 2025-07 | O96: =TEXT(tbl_Ledger[[#This Row],[Date]],"yyyy-mm") & TRIM(tbl_Ledger[[#This Row],[Currency]]) -> 2025-07NGN | P96: =_xlfn.XLOOKUP(tbl_Ledger[[#This Row],[Key]], tbl_FX[Key], tbl_FX[Rate_to_NGN]) -> 1 | Q96: =IF(tbl_Ledger[[#This Row],[Account_Type]]="Expense",-ABS(tbl_Ledger[[#This Row],[Amount]]*tbl_Ledger[[#This Row],[Rate_to_NGN]]),tbl_Ledger[[#This Row],[Amount]]*tbl_Ledger[[#This Row],[Rate_to_NGN]]) -> 28300 | R96: =_xlfn.XLOOKUP(tbl_Ledger[[#This Row],[Account_Code]], tbl_Accounts[Account_Code], tbl_Accounts[Type]) -> Revenue | S96: =_xlfn.XLOOKUP(tbl_Ledger[[#This Row],[Account_Code]], tbl_Accounts[Account_Code], tbl_Accounts[PL_Bucket]) -> Revenue | T96: =IF(AND(S96="Revenue",F96<>4900),ABS(Q96),-ABS(Q96)) -> 28300
A97: T100080 | B97: 45845 | C97: POS-Square | D97: Zumi Eats | E97: Aggregator-Bolt | F97: 4000 | G97: Order Revenue | H97: Aggregator-Bolt daily settlement 2025-07-07 | I97: NGN | J97: 30700 | L97: INV-20250707-AGG | N97: =TEXT(tbl_Ledger[[#This Row],[Date]],"yyyy-mm") -> 2025-07 | O97: =TEXT(tbl_Ledger[[#This Row],[Date]],"yyyy-mm") & TRIM(tbl_Ledger[[#This Row],[Currency]]) -> 2025-07NGN | P97: =_xlfn.XLOOKUP(tbl_Ledger[[#This Row],[Key]], tbl_FX[Key], tbl_FX[Rate_to_NGN]) -> 1 | Q97: =IF(tbl_Ledger[[#This Row],[Account_Type]]="Expense",-ABS(tbl_Ledger[[#This Row],[Amount]]*tbl_Ledger[[#This Row],[Rate_to_NGN]]),tbl_Ledger[[#This Row],[Amount]]*tbl_Ledger[[#This Row],[Rate_to_NGN]]) -> 30700 | R97: =_xlfn.XLOOKUP(tbl_Ledger[[#This Row],[Account_Code]], tbl_Accounts[Account_Code], tbl_Accounts[Type]) -> Revenue | S97: =_xlfn.XLOOKUP(tbl_Ledger[[#This Row],[Account_Code]], tbl_Accounts[Account_Code], tbl_Accounts[PL_Bucket]) -> Revenue | T97: =IF(AND(S97="Revenue",F97<>4900),ABS(Q97),-ABS(Q97)) -> 30700
A98: T100081 | B98: 45845 | C98: POS-Square | D98: Zumi Eats | E98: Walk-in | F98: 4000 | G98: Order Revenue | H98: Walk-in daily settlement 2025-07-07 | I98: NGN | J98: 30500 | L98: INV-20250707-WAL | N98: =TEXT(tbl_Ledger[[#This Row],[Date]],"yyyy-mm") -> 2025-07 | O98: =TEXT(tbl_Ledger[[#This Row],[Date]],"yyyy-mm") & TRIM(tbl_Ledger[[#This Row],[Currency]]) -> 2025-07NGN | P98: =_xlfn.XLOOKUP(tbl_Ledger[[#This Row],[Key]], tbl_FX[Key], tbl_FX[Rate_to_NGN]) -> 1 | Q98: =IF(tbl_Ledger[[#This Row],[Account_Type]]="Expense",-ABS(tbl_Ledger[[#This Row],[Amount]]*tbl_Ledger[[#This Row],[Rate_to_NGN]]),tbl_Ledger[[#This Row],[Amount]]*tbl_Ledger[[#This Row],[Rate_to_NGN]]) -> 30500 | R98: =_xlfn.XLOOKUP(tbl_Ledger[[#This Row],[Account_Code]], tbl_Accounts[Account_Code], tbl_Accounts[Type]) -> Revenue | S98: =_xlfn.XLOOKUP(tbl_Ledger[[#This Row],[Account_Code]], tbl_Accounts[Account_Code], tbl_Accounts[PL_Bucket]) -> Revenue | T98: =IF(AND(S98="Revenue",F98<>4900),ABS(Q98),-ABS(Q98)) -> 30500
A99: T100082 | B99: 45845 | C99: POS-Square | D99: Zumi Mart | E99: POS-VI | F99: 4000 | G99: Order Revenue | H99: POS-VI daily settlement 2025-07-07 | I99: NGN | J99: 50500 | L99: INV-20250707-POS | N99: =TEXT(tbl_Ledger[[#This Row],[Date]],"yyyy-mm") -> 2025-07 | O99: =TEXT(tbl_Ledger[[#This Row],[Date]],"yyyy-mm") & TRIM(tbl_Ledger[[#This Row],[Currency]]) -> 2025-07NGN | P99: =_xlfn.XLOOKUP(tbl_Ledger[[#This Row],[Key]], tbl_FX[Key], tbl_FX[Rate_to_NGN]) -> 1 | Q99: =IF(tbl_Ledger[[#This Row],[Account_Type]]="Expense",-ABS(tbl_Ledger[[#This Row],[Amount]]*tbl_Ledger[[#This Row],[Rate_to_NGN]]),tbl_Ledger[[#This Row],[Amount]]*tbl_Ledger[[#This Row],[Rate_to_NGN]]) -> 50500 | R99: =_xlfn.XLOOKUP(tbl_Ledger[[#This Row],[Account_Code]], tbl_Accounts[Account_Code], tbl_Accounts[Type]) -> Revenue | S99: =_xlfn.XLOOKUP(tbl_Ledger[[#This Row],[Account_Code]], tbl_Accounts[Account_Code], tbl_Accounts[PL_Bucket]) -> Revenue | T99: =IF(AND(S99="Revenue",F99<>4900),ABS(Q99),-ABS(Q99)) -> 50500
A100: T100083 | B100: 45845 | C100: POS-Square | D100: Zumi Mart | E100: POS-Ikeja | F100: 4000 | G100: Order Revenue | H100: POS-Ikeja daily settlement 2025-07-07 | I100: NGN | J100: 47700 | L100: INV-20250707-POS | N100: =TEXT(tbl_Ledger[[#This Row],[Date]],"yyyy-mm") -> 2025-07 | O100: =TEXT(tbl_Ledger[[#This Row],[Date]],"yyyy-mm") & TRIM(tbl_Ledger[[#This Row],[Currency]]) -> 2025-07NGN | P100: =_xlfn.XLOOKUP(tbl_Ledger[[#This Row],[Key]], tbl_FX[Key], tbl_FX[Rate_to_NGN]) -> 1 | Q100: =IF(tbl_Ledger[[#This Row],[Account_Type]]="Expense",-ABS(tbl_Ledger[[#This Row],[Amount]]*tbl_Ledger[[#This Row],[Rate_to_NGN]]),tbl_Ledger[[#This Row],[Amount]]*tbl_Ledger[[#This Row],[Rate_to_NGN]]) -> 47700 | R100: =_xlfn.XLOOKUP(tbl_Ledger[[#This Row],[Account_Code]], tbl_Accounts[Account_Code], tbl_Accounts[Type]) -> Revenue | S100: =_xlfn.XLOOKUP(tbl_Ledger[[#This Row],[Account_Code]], tbl_Accounts[Account_Code], tbl_Accounts[PL_Bucket]) -> Revenue | T100: =IF(AND(S100="Revenue",F100<>4900),ABS(Q100),-ABS(Q100)) -> 47700
...

Sheet Issues_Log
A1: Issue_# | B1: Txn_ID | C1: Date | D1: Brand | E1: Amount_NGN | F1: Issue_Type | G1: Action_Taken
A2: 1 | B2: T101433 | C2: =_xlfn.XLOOKUP(B2,tbl_Ledger[Txn_ID],tbl_Ledger[Date]) -> 45881 | D2: =_xlfn.XLOOKUP(B2,tbl_Ledger[Txn_ID],tbl_Ledger[Brand]) -> Zumi Mart | E2: =_xlfn.XLOOKUP(B2,tbl_Ledger[Txn_ID],tbl_Ledger[Adjusted_Amount_NGN]) -> -1840000 | F2: Duplicate Vendor Invoice | G2: Excluded - Distell Wholesale paid twice same week, same amount
A3: 2 | B3: T101402 | C3: =_xlfn.XLOOKUP(B3,tbl_Ledger[Txn_ID],tbl_Ledger[Date]) -> 45894 | D3: =_xlfn.XLOOKUP(B3,tbl_Ledger[Txn_ID],tbl_Ledger[Brand]) -> Zumi Mart | E3: =_xlfn.XLOOKUP(B3,tbl_Ledger[Txn_ID],tbl_Ledger[Adjusted_Amount_NGN]) -> -680000 | F3: Duplicate Payroll Entry | G3: Excluded - same employee same month, already captured in T101401
A4: 3 | B4: T101419 | C4: =_xlfn.XLOOKUP(B4,tbl_Ledger[Txn_ID],tbl_Ledger[Date]) -> 45925 | D4: =_xlfn.XLOOKUP(B4,tbl_Ledger[Txn_ID],tbl_Ledger[Brand]) -> Zumi Eats | E4: =_xlfn.XLOOKUP(B4,tbl_Ledger[Txn_ID],tbl_Ledger[Adjusted_Amount_NGN]) -> -540000 | F4: Misclassified Brand | G4: Reclassified from Zumi Eats to Zumi Logistics - rider supervisor belongs to Logistics
A5: 4 | B5: T101435 | C5: 45922 | D5: =_xlfn.XLOOKUP(B5,tbl_Ledger[Txn_ID],tbl_Ledger[Brand]) -> Zumi Eats | E5: =_xlfn.XLOOKUP(B5,tbl_Ledger[Txn_ID],tbl_Ledger[Adjusted_Amount_NGN]) -> -180000 | F5: Uncategorized Cash Withdrawal | G5: Parked separately - no GL code, excluded from OpEx, flagged for CEO review
A6: 5 | B6: T101434 | C6: Unknown | D6: =_xlfn.XLOOKUP(B6,tbl_Ledger[Txn_ID],tbl_Ledger[Brand]) -> Zumi Logistics | E6: =_xlfn.XLOOKUP(B6,tbl_Ledger[Txn_ID],tbl_Ledger[Adjusted_Amount_NGN]) -> -240000 | F6: Missing Transaction Date | G6: Excluded from P&L - date stored as Excel serial number 45839, cannot assign to month
A7: 6 | B7: Multiple - Account 4900 | C7: 2025-07 to 2025-09 | D7: All Brands | E7: =SUMIFS(tbl_Cleaned[Clean_Amount],tbl_Cleaned[Account_Name],"Refunds & Chargebacks") -> -2962453 | F7: Refunds Booked as Positive | G7: Fixed in Clean_Amount formula - all Account 4900 rows forced negative via IF/ABS formula
A9: Total NGN Impact of Issues | E9: =SUM(E2:E7) -> -6442453

Sheet tbl_Cleaned
A1: Txn_ID | B1: Date | C1: Source_System | D1: Brand | E1: Channel | F1: Account_Code | G1: Account_Name | H1: Description | I1: Currency | J1: Amount | K1: Vendor_or_Customer | L1: Reference | M1: Notes | N1: Month | O1: Key | P1: Rate_to_NGN | Q1: Adjusted_Amount_NGN | R1: Account_Type | S1: PL_Bucket | T1: Clean_Amount
A2: T100001 | B2: 45839 | C2: POS-Square | D2: Zumi Eats | E2: Mobile App | F2: 4000 | G2: Order Revenue | H2: Mobile App daily settlement 2025-07-01 | I2: NGN | J2: 27600 | L2: INV-20250701-MOB | N2: 2025-07 | O2: 2025-07NGN | P2: 1 | Q2: 27600 | R2: Revenue | S2: Revenue | T2: =IF(AND(S2="Revenue",G2<>"Refunds & Chargebacks"),ABS(Q2),-ABS(Q2)) -> 27600
A3: T100002 | B3: 45839 | C3: POS-Square | D3: Zumi Eats | E3: Website | F3: 4000 | G3: Order Revenue | H3: Website daily settlement 2025-07-01 | I3: NGN | J3: 29800 | L3: INV-20250701-WEB | N3: 2025-07 | O3: 2025-07NGN | P3: 1 | Q3: 29800 | R3: Revenue | S3: Revenue | T3: =IF(AND(S3="Revenue",G3<>"Refunds & Chargebacks"),ABS(Q3),-ABS(Q3)) -> 29800
A4: T100003 | B4: 45839 | C4: POS-Square | D4: Zumi Eats | E4: Aggregator-Glovo | F4: 4000 | G4: Order Revenue | H4: Aggregator-Glovo daily settlement 2025-07-01 | I4: NGN | J4: 29500 | L4: INV-20250701-AGG | N4: 2025-07 | O4: 2025-07NGN | P4: 1 | Q4: 29500 | R4: Revenue | S4: Revenue | T4: =IF(AND(S4="Revenue",G4<>"Refunds & Chargebacks"),ABS(Q4),-ABS(Q4)) -> 29500
A5: T100004 | B5: 45839 | C5: POS-Square | D5: Zumi Eats | E5: Walk-in | F5: 4000 | G5: Order Revenue | H5: Walk-in daily settlement 2025-07-01 | I5: NGN | J5: 31400 | L5: INV-20250701-WAL | N5: 2025-07 | O5: 2025-07NGN | P5: 1 | Q5: 31400 | R5: Revenue | S5: Revenue | T5: =IF(AND(S5="Revenue",G5<>"Refunds & Chargebacks"),ABS(Q5),-ABS(Q5)) -> 31400
A6: T100005 | B6: 45839 | C6: POS-Square | D6: Zumi Mart | E6: POS-Lekki | F6: 4000 | G6: Order Revenue | H6: POS-Lekki daily settlement 2025-07-01 | I6: NGN | J6: 48600 | L6: INV-20250701-POS | N6: 2025-07 | O6: 2025-07NGN | P6: 1 | Q6: 48600 | R6: Revenue | S6: Revenue | T6: =IF(AND(S6="Revenue",G6<>"Refunds & Chargebacks"),ABS(Q6),-ABS(Q6)) -> 48600
A7: T100006 | B7: 45839 | C7: POS-Square | D7: Zumi Mart | E7: POS-VI | F7: 4000 | G7: Order Revenue | H7: POS-VI daily settlement 2025-07-01 | I7: NGN | J7: 45700 | L7: INV-20250701-POS | N7: 2025-07 | O7: 2025-07NGN | P7: 1 | Q7: 45700 | R7: Revenue | S7: Revenue | T7: =IF(AND(S7="Revenue",G7<>"Refunds & Chargebacks"),ABS(Q7),-ABS(Q7)) -> 45700
A8: T100007 | B8: 45839 | C8: POS-Square | D8: Zumi Mart | E8: POS-Ikeja | F8: 4000 | G8: Order Revenue | H8: POS-Ikeja daily settlement 2025-07-01 | I8: NGN | J8: 46300 | L8: INV-20250701-POS | N8: 2025-07 | O8: 2025-07NGN | P8: 1 | Q8: 46300 | R8: Revenue | S8: Revenue | T8: =IF(AND(S8="Revenue",G8<>"Refunds & Chargebacks"),ABS(Q8),-ABS(Q8)) -> 46300
A9: T100008 | B9: 45839 | C9: POS-Square | D9: Zumi Mart | E9: Online | F9: 4000 | G9: Order Revenue | H9: Online daily settlement 2025-07-01 | I9: NGN | J9: 49000 | L9: INV-20250701-ONL | N9: 2025-07 | O9: 2025-07NGN | P9: 1 | Q9: 49000 | R9: Revenue | S9: Revenue | T9: =IF(AND(S9="Revenue",G9<>"Refunds & Chargebacks"),ABS(Q9),-ABS(Q9)) -> 49000
A10: T100009 | B10: 45839 | C10: NetSuite | D10: Zumi Logistics | E10: Contract-Dangote | F10: 4020 | G10: Logistics Contract Revenue | H10: Contract-Dangote daily settlement 2025-07-01 | I10: NGN | J10: 41900 | K10: Dangote | L10: INV-20250701-CON | N10: 2025-07 | O10: 2025-07NGN | P10: 1 | Q10: 41900 | R10: Revenue | S10: Revenue | T10: =IF(AND(S10="Revenue",G10<>"Refunds & Chargebacks"),ABS(Q10),-ABS(Q10)) -> 41900
A11: T100010 | B11: 45839 | C11: NetSuite | D11: Zumi Logistics | E11: Contract-MTN | F11: 4020 | G11: Logistics Contract Revenue | H11: Contract-MTN daily settlement 2025-07-01 | I11: USD | J11: 28.04 | K11: MTN | L11: INV-20250701-CON | N11: 2025-07 | O11: 2025-07USD | P11: 1530 | Q11: 42901.2 | R11: Revenue | S11: Revenue | T11: =IF(AND(S11="Revenue",G11<>"Refunds & Chargebacks"),ABS(Q11),-ABS(Q11)) -> 42901.2
A12: T100011 | B12: 45839 | C12: NetSuite | D12: Zumi Logistics | E12: Contract-Flutterwave | F12: 4020 | G12: Logistics Contract Revenue | H12: Contract-Flutterwave daily settlement 2025-07-01 | I12: USD | J12: 28.95 | K12: Flutterwave | L12: INV-20250701-CON | N12: 2025-07 | O12: 2025-07USD | P12: 1530 | Q12: 44293.5 | R12: Revenue | S12: Revenue | T12: =IF(AND(S12="Revenue",G12<>"Refunds & Chargebacks"),ABS(Q12),-ABS(Q12)) -> 44293.5
A13: T100012 | B13: 45839 | C13: NetSuite | D13: Zumi Logistics | E13: Spot-Market | F13: 4020 | G13: Logistics Contract Revenue | H13: Spot-Market daily settlement 2025-07-01 | I13: NGN | J13: 47700 | L13: INV-20250701-SPO | N13: 2025-07 | O13: 2025-07NGN | P13: 1 | Q13: 47700 | R13: Revenue | S13: Revenue | T13: =IF(AND(S13="Revenue",G13<>"Refunds & Chargebacks"),ABS(Q13),-ABS(Q13)) -> 47700
A14: T101249 | B14: 45839 | C14: QuickBooks | D14: Zumi Mart | F14: 5010 | G14: Inventory Purchases | H14: Distell Wholesale invoice 2025-07 | I14: NGN | J14: -1691000 | K14: Distell Wholesale | L14: BILL-13747 | N14: 2025-07 | O14: 2025-07NGN | P14: 1 | Q14: -1691000 | R14: COGS | S14: COGS | T14: =IF(AND(S14="Revenue",G14<>"Refunds & Chargebacks"),ABS(Q14),-ABS(Q14)) -> -1691000
A15: T101265 | B15: 45839 | C15: QuickBooks | D15: Zumi Logistics | F15: 5030 | G15: Fuel & Vehicle | H15: NNPC Retail invoice 2025-07 | I15: NGN | J15: -522000 | K15: NNPC Retail | L15: BILL-18601 | N15: 2025-07 | O15: 2025-07NGN | P15: 1 | Q15: -522000 | R15: COGS | S15: COGS | T15: =IF(AND(S15="Revenue",G15<>"Refunds & Chargebacks"),ABS(Q15),-ABS(Q15)) -> -522000
A16: T100013 | B16: 45840 | C16: POS-Square | D16: Zumi Eats | E16: Mobile App | F16: 4000 | G16: Order Revenue | H16: Mobile App daily settlement 2025-07-02 | I16: NGN | J16: 31500 | L16: INV-20250702-MOB | N16: 2025-07 | O16: 2025-07NGN | P16: 1 | Q16: 31500 | R16: Revenue | S16: Revenue | T16: =IF(AND(S16="Revenue",G16<>"Refunds & Chargebacks"),ABS(Q16),-ABS(Q16)) -> 31500
A17: T100014 | B17: 45840 | C17: POS-Square | D17: Zumi Eats | E17: Website | F17: 4000 | G17: Order Revenue | H17: Website daily settlement 2025-07-02 | I17: NGN | J17: 27600 | L17: INV-20250702-WEB | N17: 2025-07 | O17: 2025-07NGN | P17: 1 | Q17: 27600 | R17: Revenue | S17: Revenue | T17: =IF(AND(S17="Revenue",G17<>"Refunds & Chargebacks"),ABS(Q17),-ABS(Q17)) -> 27600
A18: T100015 | B18: 45840 | C18: POS-Square | D18: Zumi Eats | E18: Aggregator-Glovo | F18: 4000 | G18: Order Revenue | H18: Aggregator-Glovo daily settlement 2025-07-02 | I18: NGN | J18: 27700 | L18: INV-20250702-AGG | N18: 2025-07 | O18: 2025-07NGN | P18: 1 | Q18: 27700 | R18: Revenue | S18: Revenue | T18: =IF(AND(S18="Revenue",G18<>"Refunds & Chargebacks"),ABS(Q18),-ABS(Q18)) -> 27700
A19: T100016 | B19: 45840 | C19: POS-Square | D19: Zumi Eats | E19: Aggregator-Bolt | F19: 4000 | G19: Order Revenue | H19: Aggregator-Bolt daily settlement 2025-07-02 | I19: NGN | J19: 27000 | L19: INV-20250702-AGG | N19: 2025-07 | O19: 2025-07NGN | P19: 1 | Q19: 27000 | R19: Revenue | S19: Revenue | T19: =IF(AND(S19="Revenue",G19<>"Refunds & Chargebacks"),ABS(Q19),-ABS(Q19)) -> 27000
A20: T100017 | B20: 45840 | C20: POS-Square | D20: Zumi Mart | E20: POS-Lekki | F20: 4000 | G20: Order Revenue | H20: POS-Lekki daily settlement 2025-07-02 | I20: NGN | J20: 50900 | L20: INV-20250702-POS | N20: 2025-07 | O20: 2025-07NGN | P20: 1 | Q20: 50900 | R20: Revenue | S20: Revenue | T20: =IF(AND(S20="Revenue",G20<>"Refunds & Chargebacks"),ABS(Q20),-ABS(Q20)) -> 50900
A21: T100018 | B21: 45840 | C21: POS-Square | D21: Zumi Mart | E21: POS-VI | F21: 4000 | G21: Order Revenue | H21: POS-VI daily settlement 2025-07-02 | I21: NGN | J21: 45500 | L21: INV-20250702-POS | N21: 2025-07 | O21: 2025-07NGN | P21: 1 | Q21: 45500 | R21: Revenue | S21: Revenue | T21: =IF(AND(S21="Revenue",G21<>"Refunds & Chargebacks"),ABS(Q21),-ABS(Q21)) -> 45500
A22: T100019 | B22: 45840 | C22: POS-Square | D22: Zumi Mart | E22: POS-Ikeja | F22: 4000 | G22: Order Revenue | H22: POS-Ikeja daily settlement 2025-07-02 | I22: NGN | J22: 48200 | L22: INV-20250702-POS | N22: 2025-07 | O22: 2025-07NGN | P22: 1 | Q22: 48200 | R22: Revenue | S22: Revenue | T22: =IF(AND(S22="Revenue",G22<>"Refunds & Chargebacks"),ABS(Q22),-ABS(Q22)) -> 48200
A23: T100020 | B23: 45840 | C23: POS-Square | D23: Zumi Mart | E23: POS-Abuja | F23: 4000 | G23: Order Revenue | H23: POS-Abuja daily settlement 2025-07-02 | I23: NGN | J23: 46900 | L23: INV-20250702-POS | N23: 2025-07 | O23: 2025-07NGN | P23: 1 | Q23: 46900 | R23: Revenue | S23: Revenue | T23: =IF(AND(S23="Revenue",G23<>"Refunds & Chargebacks"),ABS(Q23),-ABS(Q23)) -> 46900
A24: T100021 | B24: 45840 | C24: POS-Square | D24: Zumi Mart | E24: Online | F24: 4000 | G24: Order Revenue | H24: Online daily settlement 2025-07-02 | I24: NGN | J24: 49800 | L24: INV-20250702-ONL | N24: 2025-07 | O24: 2025-07NGN | P24: 1 | Q24: 49800 | R24: Revenue | S24: Revenue | T24: =IF(AND(S24="Revenue",G24<>"Refunds & Chargebacks"),ABS(Q24),-ABS(Q24)) -> 49800
A25: T100022 | B25: 45840 | C25: NetSuite | D25: Zumi Logistics | E25: Contract-Dangote | F25: 4020 | G25: Logistics Contract Revenue | H25: Contract-Dangote daily settlement 2025-07-02 | I25: USD | J25: 28.56 | K25: Dangote | L25: INV-20250702-CON | N25: 2025-07 | O25: 2025-07USD | P25: 1530 | Q25: 43696.8 | R25: Revenue | S25: Revenue | T25: =IF(AND(S25="Revenue",G25<>"Refunds & Chargebacks"),ABS(Q25),-ABS(Q25)) -> 43696.8
A26: T100023 | B26: 45840 | C26: NetSuite | D26: Zumi Logistics | E26: Contract-MTN | F26: 4020 | G26: Logistics Contract Revenue | H26: Contract-MTN daily settlement 2025-07-02 | I26: NGN | J26: 49900 | K26: MTN | L26: INV-20250702-CON | N26: 2025-07 | O26: 2025-07NGN | P26: 1 | Q26: 49900 | R26: Revenue | S26: Revenue | T26: =IF(AND(S26="Revenue",G26<>"Refunds & Chargebacks"),ABS(Q26),-ABS(Q26)) -> 49900
A27: T100024 | B27: 45840 | C27: NetSuite | D27: Zumi Logistics | E27: Contract-Flutterwave | F27: 4020 | G27: Logistics Contract Revenue | H27: Contract-Flutterwave daily settlement 2025-07-02 | I27: NGN | J27: 48500 | K27: Flutterwave | L27: INV-20250702-CON | N27: 2025-07 | O27: 2025-07NGN | P27: 1 | Q27: 48500 | R27: Revenue | S27: Revenue | T27: =IF(AND(S27="Revenue",G27<>"Refunds & Chargebacks"),ABS(Q27),-ABS(Q27)) -> 48500
A28: T100025 | B28: 45840 | C28: NetSuite | D28: Zumi Logistics | E28: Spot-Market | F28: 4020 | G28: Logistics Contract Revenue | H28: Spot-Market daily settlement 2025-07-02 | I28: NGN | J28: 48000 | L28: INV-20250702-SPO | N28: 2025-07 | O28: 2025-07NGN | P28: 1 | Q28: 48000 | R28: Revenue | S28: Revenue | T28: =IF(AND(S28="Revenue",G28<>"Refunds & Chargebacks"),ABS(Q28),-ABS(Q28)) -> 48000
A29: T101239 | B29: 45840 | C29: QuickBooks | D29: Zumi Eats | F29: 5040 | G29: Rider Payouts | H29: Rider Payroll invoice 2025-07 | I29: NGN | J29: -562000 | K29: Rider Payroll | L29: BILL-47775 | N29: 2025-07 | O29: 2025-07NGN | P29: 1 | Q29: -562000 | R29: COGS | S29: COGS | T29: =IF(AND(S29="Revenue",G29<>"Refunds & Chargebacks"),ABS(Q29),-ABS(Q29)) -> -562000
A30: T101243 | B30: 45840 | C30: QuickBooks | D30: Zumi Eats | F30: 5050 | G30: Aggregator Commission | H30: Bolt Food invoice 2025-07 | I30: NGN | J30: -255000 | K30: Bolt Food | L30: BILL-82046 | N30: 2025-07 | O30: 2025-07NGN | P30: 1 | Q30: -255000 | R30: COGS | S30: COGS | T30: =IF(AND(S30="Revenue",G30<>"Refunds & Chargebacks"),ABS(Q30),-ABS(Q30)) -> -255000
A31: T101254 | B31: 45840 | C31: QuickBooks | D31: Zumi Mart | F31: 5010 | G31: Inventory Purchases | H31: Dangote Sugar invoice 2025-07 | I31: NGN | J31: -862000 | K31: Dangote Sugar | L31: BILL-69162 | N31: 2025-07 | O31: 2025-07NGN | P31: 1 | Q31: -862000 | R31: COGS | S31: COGS | T31: =IF(AND(S31="Revenue",G31<>"Refunds & Chargebacks"),ABS(Q31),-ABS(Q31)) -> -862000
A32: T101394 | B32: 45840 | C32: QuickBooks | D32: Zumi Eats | F32: 6040 | G32: Software & Tools | H32: SaaS subscriptions 2025-07 | I32: USD | J32: -820 | K32: Various SaaS | L32: SAAS-2025-07 | N32: 2025-07 | O32: 2025-07USD | P32: 1530 | Q32: -1254600 | R32: Opex | S32: Opex | T32: =IF(AND(S32="Revenue",G32<>"Refunds & Chargebacks"),ABS(Q32),-ABS(Q32)) -> -1254600
A33: T100026 | B33: 45841 | C33: POS-Square | D33: Zumi Eats | E33: Mobile App | F33: 4000 | G33: Order Revenue | H33: Mobile App daily settlement 2025-07-03 | I33: NGN | J33: 30100 | L33: INV-20250703-MOB | N33: 2025-07 | O33: 2025-07NGN | P33: 1 | Q33: 30100 | R33: Revenue | S33: Revenue | T33: =IF(AND(S33="Revenue",G33<>"Refunds & Chargebacks"),ABS(Q33),-ABS(Q33)) -> 30100
A34: T100027 | B34: 45841 | C34: POS-Square | D34: Zumi Eats | E34: Website | F34: 4000 | G34: Order Revenue | H34: Website daily settlement 2025-07-03 | I34: NGN | J34: 30400 | L34: INV-20250703-WEB | N34: 2025-07 | O34: 2025-07NGN | P34: 1 | Q34: 30400 | R34: Revenue | S34: Revenue | T34: =IF(AND(S34="Revenue",G34<>"Refunds & Chargebacks"),ABS(Q34),-ABS(Q34)) -> 30400
A35: T100028 | B35: 45841 | C35: POS-Square | D35: Zumi Eats | E35: Aggregator-Glovo | F35: 4000 | G35: Order Revenue | H35: Aggregator-Glovo daily settlement 2025-07-03 | I35: NGN | J35: 30700 | L35: INV-20250703-AGG | N35: 2025-07 | O35: 2025-07NGN | P35: 1 | Q35: 30700 | R35: Revenue | S35: Revenue | T35: =IF(AND(S35="Revenue",G35<>"Refunds & Chargebacks"),ABS(Q35),-ABS(Q35)) -> 30700
A36: T100029 | B36: 45841 | C36: POS-Square | D36: Zumi Eats | E36: Aggregator-Bolt | F36: 4000 | G36: Order Revenue | H36: Aggregator-Bolt daily settlement 2025-07-03 | I36: NGN | J36: 28100 | L36: INV-20250703-AGG | N36: 2025-07 | O36: 2025-07NGN | P36: 1 | Q36: 28100 | R36: Revenue | S36: Revenue | T36: =IF(AND(S36="Revenue",G36<>"Refunds & Chargebacks"),ABS(Q36),-ABS(Q36)) -> 28100
A37: T100030 | B37: 45841 | C37: POS-Square | D37: Zumi Mart | E37: POS-Lekki | F37: 4000 | G37: Order Revenue | H37: POS-Lekki daily settlement 2025-07-03 | I37: NGN | J37: 48100 | L37: INV-20250703-POS | N37: 2025-07 | O37: 2025-07NGN | P37: 1 | Q37: 48100 | R37: Revenue | S37: Revenue | T37: =IF(AND(S37="Revenue",G37<>"Refunds & Chargebacks"),ABS(Q37),-ABS(Q37)) -> 48100
A38: T100031 | B38: 45841 | C38: POS-Square | D38: Zumi Mart | E38: POS-VI | F38: 4000 | G38: Order Revenue | H38: POS-VI daily settlement 2025-07-03 | I38: NGN | J38: 47100 | L38: INV-20250703-POS | N38: 2025-07 | O38: 2025-07NGN | P38: 1 | Q38: 47100 | R38: Revenue | S38: Revenue | T38: =IF(AND(S38="Revenue",G38<>"Refunds & Chargebacks"),ABS(Q38),-ABS(Q38)) -> 47100
A39: T100032 | B39: 45841 | C39: POS-Square | D39: Zumi Mart | E39: POS-Ikeja | F39: 4000 | G39: Order Revenue | H39: POS-Ikeja daily settlement 2025-07-03 | I39: NGN | J39: 50400 | L39: INV-20250703-POS | N39: 2025-07 | O39: 2025-07NGN | P39: 1 | Q39: 50400 | R39: Revenue | S39: Revenue | T39: =IF(AND(S39="Revenue",G39<>"Refunds & Chargebacks"),ABS(Q39),-ABS(Q39)) -> 50400
A40: T100033 | B40: 45841 | C40: POS-Square | D40: Zumi Mart | E40: POS-Abuja | F40: 4000 | G40: Order Revenue | H40: POS-Abuja daily settlement 2025-07-03 | I40: NGN | J40: 50400 | L40: INV-20250703-POS | N40: 2025-07 | O40: 2025-07NGN | P40: 1 | Q40: 50400 | R40: Revenue | S40: Revenue | T40: =IF(AND(S40="Revenue",G40<>"Refunds & Chargebacks"),ABS(Q40),-ABS(Q40)) -> 50400
A41: T100034 | B41: 45841 | C41: POS-Square | D41: Zumi Mart | E41: Online | F41: 4000 | G41: Order Revenue | H41: Online daily settlement 2025-07-03 | I41: NGN | J41: 47300 | L41: INV-20250703-ONL | N41: 2025-07 | O41: 2025-07NGN | P41: 1 | Q41: 47300 | R41: Revenue | S41: Revenue | T41: =IF(AND(S41="Revenue",G41<>"Refunds & Chargebacks"),ABS(Q41),-ABS(Q41)) -> 47300
A42: T100035 | B42: 45841 | C42: NetSuite | D42: Zumi Logistics | E42: Contract-Dangote | F42: 4020 | G42: Logistics Contract Revenue | H42: Contract-Dangote daily settlement 2025-07-03 | I42: USD | J42: 26.99 | K42: Dangote | L42: INV-20250703-CON | N42: 2025-07 | O42: 2025-07USD | P42: 1530 | Q42: 41294.7 | R42: Revenue | S42: Revenue | T42: =IF(AND(S42="Revenue",G42<>"Refunds & Chargebacks"),ABS(Q42),-ABS(Q42)) -> 41294.7
A43: T100036 | B43: 45841 | C43: NetSuite | D43: Zumi Logistics | E43: Contract-MTN | F43: 4020 | G43: Logistics Contract Revenue | H43: Contract-MTN daily settlement 2025-07-03 | I43: NGN | J43: 40600 | K43: MTN | L43: INV-20250703-CON | N43: 2025-07 | O43: 2025-07NGN | P43: 1 | Q43: 40600 | R43: Revenue | S43: Revenue | T43: =IF(AND(S43="Revenue",G43<>"Refunds & Chargebacks"),ABS(Q43),-ABS(Q43)) -> 40600
A44: T100037 | B44: 45841 | C44: NetSuite | D44: Zumi Logistics | E44: Contract-Flutterwave | F44: 4020 | G44: Logistics Contract Revenue | H44: Contract-Flutterwave daily settlement 2025-07-03 | I44: USD | J44: 30.52 | K44: Flutterwave | L44: INV-20250703-CON | N44: 2025-07 | O44: 2025-07USD | P44: 1530 | Q44: 46695.6 | R44: Revenue | S44: Revenue | T44: =IF(AND(S44="Revenue",G44<>"Refunds & Chargebacks"),ABS(Q44),-ABS(Q44)) -> 46695.6
A45: T100038 | B45: 45841 | C45: NetSuite | D45: Zumi Logistics | E45: Spot-Market | F45: 4020 | G45: Logistics Contract Revenue | H45: Spot-Market daily settlement 2025-07-03 | I45: NGN | J45: 40000 | L45: INV-20250703-SPO | N45: 2025-07 | O45: 2025-07NGN | P45: 1 | Q45: 40000 | R45: Revenue | S45: Revenue | T45: =IF(AND(S45="Revenue",G45<>"Refunds & Chargebacks"),ABS(Q45),-ABS(Q45)) -> 40000
A46: T101200 | B46: 45841 | C46: POS-Square | D46: Zumi Mart | E46: POS-Lekki | F46: 4900 | G46: Refunds & Chargebacks | H46: Customer refund order #263503 | I46: NGN | J46: 146038 | L46: RFD-4122 | M46: FLAG: booked positive | N46: 2025-07 | O46: 2025-07NGN | P46: 1 | Q46: 146038 | R46: Revenue | S46: Revenue | T46: =IF(AND(S46="Revenue",G46<>"Refunds & Chargebacks"),ABS(Q46),-ABS(Q46)) -> -146038
A47: T100039 | B47: 45842 | C47: POS-Square | D47: Zumi Eats | E47: Mobile App | F47: 4000 | G47: Order Revenue | H47: Mobile App daily settlement 2025-07-04 | I47: NGN | J47: 30400 | L47: INV-20250704-MOB | N47: 2025-07 | O47: 2025-07NGN | P47: 1 | Q47: 30400 | R47: Revenue | S47: Revenue | T47: =IF(AND(S47="Revenue",G47<>"Refunds & Chargebacks"),ABS(Q47),-ABS(Q47)) -> 30400
A48: T100040 | B48: 45842 | C48: POS-Square | D48: Zumi Eats | E48: Website | F48: 4000 | G48: Order Revenue | H48: Website daily settlement 2025-07-04 | I48: NGN | J48: 29300 | L48: INV-20250704-WEB | N48: 2025-07 | O48: 2025-07NGN | P48: 1 | Q48: 29300 | R48: Revenue | S48: Revenue | T48: =IF(AND(S48="Revenue",G48<>"Refunds & Chargebacks"),ABS(Q48),-ABS(Q48)) -> 29300
A49: T100041 | B49: 45842 | C49: POS-Square | D49: Zumi Eats | E49: Aggregator-Glovo | F49: 4000 | G49: Order Revenue | H49: Aggregator-Glovo daily settlement 2025-07-04 | I49: NGN | J49: 29200 | L49: INV-20250704-AGG | N49: 2025-07 | O49: 2025-07NGN | P49: 1 | Q49: 29200 | R49: Revenue | S49: Revenue | T49: =IF(AND(S49="Revenue",G49<>"Refunds & Chargebacks"),ABS(Q49),-ABS(Q49)) -> 29200
A50: T100042 | B50: 45842 | C50: POS-Square | D50: Zumi Eats | E50: Aggregator-Bolt | F50: 4000 | G50: Order Revenue | H50: Aggregator-Bolt daily settlement 2025-07-04 | I50: NGN | J50: 27300 | L50: INV-20250704-AGG | N50: 2025-07 | O50: 2025-07NGN | P50: 1 | Q50: 27300 | R50: Revenue | S50: Revenue | T50: =IF(AND(S50="Revenue",G50<>"Refunds & Chargebacks"),ABS(Q50),-ABS(Q50)) -> 27300
A51: T100043 | B51: 45842 | C51: POS-Square | D51: Zumi Eats | E51: Walk-in | F51: 4000 | G51: Order Revenue | H51: Walk-in daily settlement 2025-07-04 | I51: NGN | J51: 27600 | L51: INV-20250704-WAL | N51: 2025-07 | O51: 2025-07NGN | P51: 1 | Q51: 27600 | R51: Revenue | S51: Revenue | T51: =IF(AND(S51="Revenue",G51<>"Refunds & Chargebacks"),ABS(Q51),-ABS(Q51)) -> 27600
A52: T100044 | B52: 45842 | C52: POS-Square | D52: Zumi Mart | E52: POS-Lekki | F52: 4000 | G52: Order Revenue | H52: POS-Lekki daily settlement 2025-07-04 | I52: NGN | J52: 49800 | L52: INV-20250704-POS | N52: 2025-07 | O52: 2025-07NGN | P52: 1 | Q52: 49800 | R52: Revenue | S52: Revenue | T52: =IF(AND(S52="Revenue",G52<>"Refunds & Chargebacks"),ABS(Q52),-ABS(Q52)) -> 49800
A53: T100045 | B53: 45842 | C53: POS-Square | D53: Zumi Mart | E53: POS-VI | F53: 4000 | G53: Order Revenue | H53: POS-VI daily settlement 2025-07-04 | I53: NGN | J53: 50600 | L53: INV-20250704-POS | N53: 2025-07 | O53: 2025-07NGN | P53: 1 | Q53: 50600 | R53: Revenue | S53: Revenue | T53: =IF(AND(S53="Revenue",G53<>"Refunds & Chargebacks"),ABS(Q53),-ABS(Q53)) -> 50600
A54: T100046 | B54: 45842 | C54: POS-Square | D54: Zumi Mart | E54: POS-Ikeja | F54: 4000 | G54: Order Revenue | H54: POS-Ikeja daily settlement 2025-07-04 | I54: NGN | J54: 46100 | L54: INV-20250704-POS | N54: 2025-07 | O54: 2025-07NGN | P54: 1 | Q54: 46100 | R54: Revenue | S54: Revenue | T54: =IF(AND(S54="Revenue",G54<>"Refunds & Chargebacks"),ABS(Q54),-ABS(Q54)) -> 46100
A55: T100047 | B55: 45842 | C55: POS-Square | D55: Zumi Mart | E55: POS-Abuja | F55: 4000 | G55: Order Revenue | H55: POS-Abuja daily settlement 2025-07-04 | I55: NGN | J55: 46200 | L55: INV-20250704-POS | N55: 2025-07 | O55: 2025-07NGN | P55: 1 | Q55: 46200 | R55: Revenue | S55: Revenue | T55: =IF(AND(S55="Revenue",G55<>"Refunds & Chargebacks"),ABS(Q55),-ABS(Q55)) -> 46200
A56: T100048 | B56: 45842 | C56: POS-Square | D56: Zumi Mart | E56: Online | F56: 4000 | G56: Order Revenue | H56: Online daily settlement 2025-07-04 | I56: NGN | J56: 46900 | L56: INV-20250704-ONL | N56: 2025-07 | O56: 2025-07NGN | P56: 1 | Q56: 46900 | R56: Revenue | S56: Revenue | T56: =IF(AND(S56="Revenue",G56<>"Refunds & Chargebacks"),ABS(Q56),-ABS(Q56)) -> 46900
A57: T100049 | B57: 45842 | C57: NetSuite | D57: Zumi Logistics | E57: Contract-Dangote | F57: 4020 | G57: Logistics Contract Revenue | H57: Contract-Dangote daily settlement 2025-07-04 | I57: NGN | J57: 44700 | K57: Dangote | L57: INV-20250704-CON | N57: 2025-07 | O57: 2025-07NGN | P57: 1 | Q57: 44700 | R57: Revenue | S57: Revenue | T57: =IF(AND(S57="Revenue",G57<>"Refunds & Chargebacks"),ABS(Q57),-ABS(Q57)) -> 44700
A58: T100050 | B58: 45842 | C58: NetSuite | D58: Zumi Logistics | E58: Contract-MTN | F58: 4020 | G58: Logistics Contract Revenue | H58: Contract-MTN daily settlement 2025-07-04 | I58: NGN | J58: 39700 | K58: MTN | L58: INV-20250704-CON | N58: 2025-07 | O58: 2025-07NGN | P58: 1 | Q58: 39700 | R58: Revenue | S58: Revenue | T58: =IF(AND(S58="Revenue",G58<>"Refunds & Chargebacks"),ABS(Q58),-ABS(Q58)) -> 39700
A59: T100051 | B59: 45842 | C59: NetSuite | D59: Zumi Logistics | E59: Contract-Flutterwave | F59: 4020 | G59: Logistics Contract Revenue | H59: Contract-Flutterwave daily settlement 2025-07-04 | I59: NGN | J59: 41800 | K59: Flutterwave | L59: INV-20250704-CON | N59: 2025-07 | O59: 2025-07NGN | P59: 1 | Q59: 41800 | R59: Revenue | S59: Revenue | T59: =IF(AND(S59="Revenue",G59<>"Refunds & Chargebacks"),ABS(Q59),-ABS(Q59)) -> 41800
A60: T100052 | B60: 45842 | C60: NetSuite | D60: Zumi Logistics | E60: Spot-Market | F60: 4020 | G60: Logistics Contract Revenue | H60: Spot-Market daily settlement 2025-07-04 | I60: NGN | J60: 41500 | L60: INV-20250704-SPO | N60: 2025-07 | O60: 2025-07NGN | P60: 1 | Q60: 41500 | R60: Revenue | S60: Revenue | T60: =IF(AND(S60="Revenue",G60<>"Refunds & Chargebacks"),ABS(Q60),-ABS(Q60)) -> 41500
A61: T101233 | B61: 45842 | C61: QuickBooks | D61: Zumi Eats | F61: 5020 | G61: Packaging | H61: PackPro Ltd invoice 2025-07 | I61: NGN | J61: -127000 | K61: PackPro Ltd | L61: BILL-83931 | N61: 2025-07 | O61: 2025-07NGN | P61: 1 | Q61: -127000 | R61: COGS | S61: COGS | T61: =IF(AND(S61="Revenue",G61<>"Refunds & Chargebacks"),ABS(Q61),-ABS(Q61)) -> -127000
A62: T101270 | B62: 45842 | C62: QuickBooks | D62: Zumi Logistics | F62: 5030 | G62: Fuel & Vehicle | H62: Vehicle Maintenance Co invoice 2025-07 | I62: NGN | J62: -324000 | K62: Vehicle Maintenance Co | L62: BILL-84425 | N62: 2025-07 | O62: 2025-07NGN | P62: 1 | Q62: -324000 | R62: COGS | S62: COGS | T62: =IF(AND(S62="Revenue",G62<>"Refunds & Chargebacks"),ABS(Q62),-ABS(Q62)) -> -324000
A63: T100053 | B63: 45843 | C63: POS-Square | D63: Zumi Eats | E63: Mobile App | F63: 4000 | G63: Order Revenue | H63: Mobile App daily settlement 2025-07-05 | I63: NGN | J63: 35200 | L63: INV-20250705-MOB | N63: 2025-07 | O63: 2025-07NGN | P63: 1 | Q63: 35200 | R63: Revenue | S63: Revenue | T63: =IF(AND(S63="Revenue",G63<>"Refunds & Chargebacks"),ABS(Q63),-ABS(Q63)) -> 35200
A64: T100054 | B64: 45843 | C64: POS-Square | D64: Zumi Eats | E64: Website | F64: 4000 | G64: Order Revenue | H64: Website daily settlement 2025-07-05 | I64: NGN | J64: 34900 | L64: INV-20250705-WEB | N64: 2025-07 | O64: 2025-07NGN | P64: 1 | Q64: 34900 | R64: Revenue | S64: Revenue | T64: =IF(AND(S64="Revenue",G64<>"Refunds & Chargebacks"),ABS(Q64),-ABS(Q64)) -> 34900
A65: T100055 | B65: 45843 | C65: POS-Square | D65: Zumi Eats | E65: Aggregator-Glovo | F65: 4000 | G65: Order Revenue | H65: Aggregator-Glovo daily settlement 2025-07-05 | I65: NGN | J65: 35900 | L65: INV-20250705-AGG | N65: 2025-07 | O65: 2025-07NGN | P65: 1 | Q65: 35900 | R65: Revenue | S65: Revenue | T65: =IF(AND(S65="Revenue",G65<>"Refunds & Chargebacks"),ABS(Q65),-ABS(Q65)) -> 35900
A66: T100056 | B66: 45843 | C66: POS-Square | D66: Zumi Eats | E66: Aggregator-Bolt | F66: 4000 | G66: Order Revenue | H66: Aggregator-Bolt daily settlement 2025-07-05 | I66: NGN | J66: 33100 | L66: INV-20250705-AGG | N66: 2025-07 | O66: 2025-07NGN | P66: 1 | Q66: 33100 | R66: Revenue | S66: Revenue | T66: =IF(AND(S66="Revenue",G66<>"Refunds & Chargebacks"),ABS(Q66),-ABS(Q66)) -> 33100
A67: T100057 | B67: 45843 | C67: POS-Square | D67: Zumi Eats | E67: Walk-in | F67: 4000 | G67: Order Revenue | H67: Walk-in daily settlement 2025-07-05 | I67: NGN | J67: 39100 | L67: INV-20250705-WAL | N67: 2025-07 | O67: 2025-07NGN | P67: 1 | Q67: 39100 | R67: Revenue | S67: Revenue | T67: =IF(AND(S67="Revenue",G67<>"Refunds & Chargebacks"),ABS(Q67),-ABS(Q67)) -> 39100
A68: T100058 | B68: 45843 | C68: POS-Square | D68: Zumi Mart | E68: POS-Lekki | F68: 4000 | G68: Order Revenue | H68: POS-Lekki daily settlement 2025-07-05 | I68: NGN | J68: 59500 | L68: INV-20250705-POS | N68: 2025-07 | O68: 2025-07NGN | P68: 1 | Q68: 59500 | R68: Revenue | S68: Revenue | T68: =IF(AND(S68="Revenue",G68<>"Refunds & Chargebacks"),ABS(Q68),-ABS(Q68)) -> 59500
A69: T100059 | B69: 45843 | C69: POS-Square | D69: Zumi Mart | E69: POS-VI | F69: 4000 | G69: Order Revenue | H69: POS-VI daily settlement 2025-07-05 | I69: NGN | J69: 62700 | L69: INV-20250705-POS | N69: 2025-07 | O69: 2025-07NGN | P69: 1 | Q69: 62700 | R69: Revenue | S69: Revenue | T69: =IF(AND(S69="Revenue",G69<>"Refunds & Chargebacks"),ABS(Q69),-ABS(Q69)) -> 62700
A70: T100060 | B70: 45843 | C70: POS-Square | D70: Zumi Mart | E70: POS-Abuja | F70: 4000 | G70: Order Revenue | H70: POS-Abuja daily settlement 2025-07-05 | I70: NGN | J70: 58500 | L70: INV-20250705-POS | N70: 2025-07 | O70: 2025-07NGN | P70: 1 | Q70: 58500 | R70: Revenue | S70: Revenue | T70: =IF(AND(S70="Revenue",G70<>"Refunds & Chargebacks"),ABS(Q70),-ABS(Q70)) -> 58500
A71: T100061 | B71: 45843 | C71: POS-Square | D71: Zumi Mart | E71: Online | F71: 4000 | G71: Order Revenue | H71: Online daily settlement 2025-07-05 | I71: NGN | J71: 62300 | L71: INV-20250705-ONL | N71: 2025-07 | O71: 2025-07NGN | P71: 1 | Q71: 62300 | R71: Revenue | S71: Revenue | T71: =IF(AND(S71="Revenue",G71<>"Refunds & Chargebacks"),ABS(Q71),-ABS(Q71)) -> 62300
A72: T100062 | B72: 45843 | C72: NetSuite | D72: Zumi Logistics | E72: Contract-MTN | F72: 4020 | G72: Logistics Contract Revenue | H72: Contract-MTN daily settlement 2025-07-05 | I72: USD | J72: 29.28 | K72: MTN | L72: INV-20250705-CON | N72: 2025-07 | O72: 2025-07USD | P72: 1530 | Q72: 44798.4 | R72: Revenue | S72: Revenue | T72: =IF(AND(S72="Revenue",G72<>"Refunds & Chargebacks"),ABS(Q72),-ABS(Q72)) -> 44798.4
A73: T100063 | B73: 45843 | C73: NetSuite | D73: Zumi Logistics | E73: Contract-Flutterwave | F73: 4020 | G73: Logistics Contract Revenue | H73: Contract-Flutterwave daily settlement 2025-07-05 | I73: USD | J73: 28.24 | K73: Flutterwave | L73: INV-20250705-CON | N73: 2025-07 | O73: 2025-07USD | P73: 1530 | Q73: 43207.2 | R73: Revenue | S73: Revenue | T73: =IF(AND(S73="Revenue",G73<>"Refunds & Chargebacks"),ABS(Q73),-ABS(Q73)) -> 43207.2
A74: T100064 | B74: 45843 | C74: NetSuite | D74: Zumi Logistics | E74: Spot-Market | F74: 4020 | G74: Logistics Contract Revenue | H74: Spot-Market daily settlement 2025-07-05 | I74: NGN | J74: 42200 | L74: INV-20250705-SPO | N74: 2025-07 | O74: 2025-07NGN | P74: 1 | Q74: 42200 | R74: Revenue | S74: Revenue | T74: =IF(AND(S74="Revenue",G74<>"Refunds & Chargebacks"),ABS(Q74),-ABS(Q74)) -> 42200
A75: T101225 | B75: 45843 | C75: QuickBooks | D75: Zumi Eats | F75: 5000 | G75: Food Cost | H75: FreshFarms NG invoice 2025-07 | I75: NGN | J75: -453000 | K75: FreshFarms NG | L75: BILL-1434 | N75: 2025-07 | O75: 2025-07NGN | P75: 1 | Q75: -453000 | R75: COGS | S75: COGS | T75: =IF(AND(S75="Revenue",G75<>"Refunds & Chargebacks"),ABS(Q75),-ABS(Q75)) -> -453000
A76: T101386 | B76: 45843 | C76: QuickBooks | D76: Zumi Eats | F76: 6010 | G76: Rent | H76: Office & store rent 2025-07 | I76: NGN | J76: -720000 | K76: Property Holdings Ltd | L76: RENT-2025-07-EAT | N76: 2025-07 | O76: 2025-07NGN | P76: 1 | Q76: -720000 | R76: Opex | S76: Opex | T76: =IF(AND(S76="Revenue",G76<>"Refunds & Chargebacks"),ABS(Q76),-ABS(Q76)) -> -720000
A77: T101388 | B77: 45843 | C77: QuickBooks | D77: Zumi Mart | F77: 6010 | G77: Rent | H77: Office & store rent 2025-07 | I77: NGN | J77: -1400000 | K77: Property Holdings Ltd | L77: RENT-2025-07-MAR | N77: 2025-07 | O77: 2025-07NGN | P77: 1 | Q77: -1400000 | R77: Opex | S77: Opex | T77: =IF(AND(S77="Revenue",G77<>"Refunds & Chargebacks"),ABS(Q77),-ABS(Q77)) -> -1400000
A78: T101390 | B78: 45843 | C78: QuickBooks | D78: Zumi Logistics | F78: 6010 | G78: Rent | H78: Office & store rent 2025-07 | I78: NGN | J78: -380000 | K78: Property Holdings Ltd | L78: RENT-2025-07-LOG | N78: 2025-07 | O78: 2025-07NGN | P78: 1 | Q78: -380000 | R78: Opex | S78: Opex | T78: =IF(AND(S78="Revenue",G78<>"Refunds & Chargebacks"),ABS(Q78),-ABS(Q78)) -> -380000
A79: T100065 | B79: 45844 | C79: POS-Square | D79: Zumi Eats | E79: Website | F79: 4000 | G79: Order Revenue | H79: Website daily settlement 2025-07-06 | I79: NGN | J79: 33300 | L79: INV-20250706-WEB | N79: 2025-07 | O79: 2025-07NGN | P79: 1 | Q79: 33300 | R79: Revenue | S79: Revenue | T79: =IF(AND(S79="Revenue",G79<>"Refunds & Chargebacks"),ABS(Q79),-ABS(Q79)) -> 33300
A80: T100066 | B80: 45844 | C80: POS-Square | D80: Zumi Eats | E80: Aggregator-Glovo | F80: 4000 | G80: Order Revenue | H80: Aggregator-Glovo daily settlement 2025-07-06 | I80: NGN | J80: 35100 | L80: INV-20250706-AGG | N80: 2025-07 | O80: 2025-07NGN | P80: 1 | Q80: 35100 | R80: Revenue | S80: Revenue | T80: =IF(AND(S80="Revenue",G80<>"Refunds & Chargebacks"),ABS(Q80),-ABS(Q80)) -> 35100
A81: T100067 | B81: 45844 | C81: POS-Square | D81: Zumi Eats | E81: Aggregator-Bolt | F81: 4000 | G81: Order Revenue | H81: Aggregator-Bolt daily settlement 2025-07-06 | I81: NGN | J81: 39000 | L81: INV-20250706-AGG | N81: 2025-07 | O81: 2025-07NGN | P81: 1 | Q81: 39000 | R81: Revenue | S81: Revenue | T81: =IF(AND(S81="Revenue",G81<>"Refunds & Chargebacks"),ABS(Q81),-ABS(Q81)) -> 39000
A82: T100068 | B82: 45844 | C82: POS-Square | D82: Zumi Eats | E82: Walk-in | F82: 4000 | G82: Order Revenue | H82: Walk-in daily settlement 2025-07-06 | I82: NGN | J82: 36900 | L82: INV-20250706-WAL | N82: 2025-07 | O82: 2025-07NGN | P82: 1 | Q82: 36900 | R82: Revenue | S82: Revenue | T82: =IF(AND(S82="Revenue",G82<>"Refunds & Chargebacks"),ABS(Q82),-ABS(Q82)) -> 36900
A83: T100069 | B83: 45844 | C83: POS-Square | D83: Zumi Mart | E83: POS-VI | F83: 4000 | G83: Order Revenue | H83: POS-VI daily settlement 2025-07-06 | I83: NGN | J83: 59700 | L83: INV-20250706-POS | N83: 2025-07 | O83: 2025-07NGN | P83: 1 | Q83: 59700 | R83: Revenue | S83: Revenue | T83: =IF(AND(S83="Revenue",G83<>"Refunds & Chargebacks"),ABS(Q83),-ABS(Q83)) -> 59700
A84: T100070 | B84: 45844 | C84: POS-Square | D84: Zumi Mart | E84: POS-Ikeja | F84: 4000 | G84: Order Revenue | H84: POS-Ikeja daily settlement 2025-07-06 | I84: NGN | J84: 59500 | L84: INV-20250706-POS | N84: 2025-07 | O84: 2025-07NGN | P84: 1 | Q84: 59500 | R84: Revenue | S84: Revenue | T84: =IF(AND(S84="Revenue",G84<>"Refunds & Chargebacks"),ABS(Q84),-ABS(Q84)) -> 59500
A85: T100071 | B85: 45844 | C85: POS-Square | D85: Zumi Mart | E85: POS-Abuja | F85: 4000 | G85: Order Revenue | H85: POS-Abuja daily settlement 2025-07-06 | I85: NGN | J85: 58400 | L85: INV-20250706-POS | N85: 2025-07 | O85: 2025-07NGN | P85: 1 | Q85: 58400 | R85: Revenue | S85: Revenue | T85: =IF(AND(S85="Revenue",G85<>"Refunds & Chargebacks"),ABS(Q85),-ABS(Q85)) -> 58400
A86: T100072 | B86: 45844 | C86: POS-Square | D86: Zumi Mart | E86: Online | F86: 4000 | G86: Order Revenue | H86: Online daily settlement 2025-07-06 | I86: NGN | J86: 62500 | L86: INV-20250706-ONL | N86: 2025-07 | O86: 2025-07NGN | P86: 1 | Q86: 62500 | R86: Revenue | S86: Revenue | T86: =IF(AND(S86="Revenue",G86<>"Refunds & Chargebacks"),ABS(Q86),-ABS(Q86)) -> 62500
A87: T100073 | B87: 45844 | C87: NetSuite | D87: Zumi Logistics | E87: Contract-Dangote | F87: 4020 | G87: Logistics Contract Revenue | H87: Contract-Dangote daily settlement 2025-07-06 | I87: USD | J87: 30.07 | K87: Dangote | L87: INV-20250706-CON | N87: 2025-07 | O87: 2025-07USD | P87: 1530 | Q87: 46007.1 | R87: Revenue | S87: Revenue | T87: =IF(AND(S87="Revenue",G87<>"Refunds & Chargebacks"),ABS(Q87),-ABS(Q87)) -> 46007.1
A88: T100074 | B88: 45844 | C88: NetSuite | D88: Zumi Logistics | E88: Contract-MTN | F88: 4020 | G88: Logistics Contract Revenue | H88: Contract-MTN daily settlement 2025-07-06 | I88: USD | J88: 28.04 | K88: MTN | L88: INV-20250706-CON | N88: 2025-07 | O88: 2025-07USD | P88: 1530 | Q88: 42901.2 | R88: Revenue | S88: Revenue | T88: =IF(AND(S88="Revenue",G88<>"Refunds & Chargebacks"),ABS(Q88),-ABS(Q88)) -> 42901.2
A89: T100075 | B89: 45844 | C89: NetSuite | D89: Zumi Logistics | E89: Contract-Flutterwave | F89: 4020 | G89: Logistics Contract Revenue | H89: Contract-Flutterwave daily settlement 2025-07-06 | I89: NGN | J89: 47000 | K89: Flutterwave | L89: INV-20250706-CON | N89: 2025-07 | O89: 2025-07NGN | P89: 1 | Q89: 47000 | R89: Revenue | S89: Revenue | T89: =IF(AND(S89="Revenue",G89<>"Refunds & Chargebacks"),ABS(Q89),-ABS(Q89)) -> 47000
A90: T100076 | B90: 45844 | C90: NetSuite | D90: Zumi Logistics | E90: Spot-Market | F90: 4020 | G90: Logistics Contract Revenue | H90: Spot-Market daily settlement 2025-07-06 | I90: NGN | J90: 41500 | L90: INV-20250706-SPO | N90: 2025-07 | O90: 2025-07NGN | P90: 1 | Q90: 41500 | R90: Revenue | S90: Revenue | T90: =IF(AND(S90="Revenue",G90<>"Refunds & Chargebacks"),ABS(Q90),-ABS(Q90)) -> 41500
A91: T101205 | B91: 45844 | C91: POS-Square | D91: Zumi Mart | E91: POS-Lekki | F91: 4900 | G91: Refunds & Chargebacks | H91: Customer refund order #180159 | I91: NGN | J91: 68559 | L91: RFD-5431 | M91: FLAG: booked positive | N91: 2025-07 | O91: 2025-07NGN | P91: 1 | Q91: 68559 | R91: Revenue | S91: Revenue | T91: =IF(AND(S91="Revenue",G91<>"Refunds & Chargebacks"),ABS(Q91),-ABS(Q91)) -> -68559
A92: T101263 | B92: 45844 | C92: QuickBooks | D92: Zumi Logistics | F92: 5030 | G92: Fuel & Vehicle | H92: NNPC Retail invoice 2025-07 | I92: NGN | J92: -562000 | K92: NNPC Retail | L92: BILL-25529 | N92: 2025-07 | O92: 2025-07NGN | P92: 1 | Q92: -562000 | R92: COGS | S92: COGS | T92: =IF(AND(S92="Revenue",G92<>"Refunds & Chargebacks"),ABS(Q92),-ABS(Q92)) -> -562000
A93: T100077 | B93: 45845 | C93: POS-Square | D93: Zumi Eats | E93: Mobile App | F93: 4000 | G93: Order Revenue | H93: Mobile App daily settlement 2025-07-07 | I93: NGN | J93: 26500 | L93: INV-20250707-MOB | N93: 2025-07 | O93: 2025-07NGN | P93: 1 | Q93: 26500 | R93: Revenue | S93: Revenue | T93: =IF(AND(S93="Revenue",G93<>"Refunds & Chargebacks"),ABS(Q93),-ABS(Q93)) -> 26500
A94: T100078 | B94: 45845 | C94: POS-Square | D94: Zumi Eats | E94: Website | F94: 4000 | G94: Order Revenue | H94: Website daily settlement 2025-07-07 | I94: NGN | J94: 27800 | L94: INV-20250707-WEB | N94: 2025-07 | O94: 2025-07NGN | P94: 1 | Q94: 27800 | R94: Revenue | S94: Revenue | T94: =IF(AND(S94="Revenue",G94<>"Refunds & Chargebacks"),ABS(Q94),-ABS(Q94)) -> 27800
A95: T100079 | B95: 45845 | C95: POS-Square | D95: Zumi Eats | E95: Aggregator-Glovo | F95: 4000 | G95: Order Revenue | H95: Aggregator-Glovo daily settlement 2025-07-07 | I95: NGN | J95: 28300 | L95: INV-20250707-AGG | N95: 2025-07 | O95: 2025-07NGN | P95: 1 | Q95: 28300 | R95: Revenue | S95: Revenue | T95: =IF(AND(S95="Revenue",G95<>"Refunds & Chargebacks"),ABS(Q95),-ABS(Q95)) -> 28300
A96: T100080 | B96: 45845 | C96: POS-Square | D96: Zumi Eats | E96: Aggregator-Bolt | F96: 4000 | G96: Order Revenue | H96: Aggregator-Bolt daily settlement 2025-07-07 | I96: NGN | J96: 30700 | L96: INV-20250707-AGG | N96: 2025-07 | O96: 2025-07NGN | P96: 1 | Q96: 30700 | R96: Revenue | S96: Revenue | T96: =IF(AND(S96="Revenue",G96<>"Refunds & Chargebacks"),ABS(Q96),-ABS(Q96)) -> 30700
A97: T100081 | B97: 45845 | C97: POS-Square | D97: Zumi Eats | E97: Walk-in | F97: 4000 | G97: Order Revenue | H97: Walk-in daily settlement 2025-07-07 | I97: NGN | J97: 30500 | L97: INV-20250707-WAL | N97: 2025-07 | O97: 2025-07NGN | P97: 1 | Q97: 30500 | R97: Revenue | S97: Revenue | T97: =IF(AND(S97="Revenue",G97<>"Refunds & Chargebacks"),ABS(Q97),-ABS(Q97)) -> 30500
A98: T100082 | B98: 45845 | C98: POS-Square | D98: Zumi Mart | E98: POS-VI | F98: 4000 | G98: Order Revenue | H98: POS-VI daily settlement 2025-07-07 | I98: NGN | J98: 50500 | L98: INV-20250707-POS | N98: 2025-07 | O98: 2025-07NGN | P98: 1 | Q98: 50500 | R98: Revenue | S98: Revenue | T98: =IF(AND(S98="Revenue",G98<>"Refunds & Chargebacks"),ABS(Q98),-ABS(Q98)) -> 50500
A99: T100083 | B99: 45845 | C99: POS-Square | D99: Zumi Mart | E99: POS-Ikeja | F99: 4000 | G99: Order Revenue | H99: POS-Ikeja daily settlement 2025-07-07 | I99: NGN | J99: 47700 | L99: INV-20250707-POS | N99: 2025-07 | O99: 2025-07NGN | P99: 1 | Q99: 47700 | R99: Revenue | S99: Revenue | T99: =IF(AND(S99="Revenue",G99<>"Refunds & Chargebacks"),ABS(Q99),-ABS(Q99)) -> 47700
A100: T100084 | B100: 45845 | C100: POS-Square | D100: Zumi Mart | E100: POS-Abuja | F100: 4000 | G100: Order Revenue | H100: POS-Abuja daily settlement 2025-07-07 | I100: NGN | J100: 49900 | L100: INV-20250707-POS | N100: 2025-07 | O100: 2025-07NGN | P100: 1 | Q100: 49900 | R100: Revenue | S100: Revenue | T100: =IF(AND(S100="Revenue",G100<>"Refunds & Chargebacks"),ABS(Q100),-ABS(Q100)) -> 49900
...

Sheet PL_By_Brand_Month
B1: Zumi Eats | C1: Zumi Mart | D1: Zumi Logistics | E1: TOTAL
A2: REVENUE
A3: Order Revenue | B3: =SUMIFS(tbl_Cleaned[Clean_Amount],tbl_Cleaned[Brand],B$1,tbl_Cleaned[Account_Name],$A3) -> 13928000 | C3: =SUMIFS(tbl_Cleaned[Clean_Amount],tbl_Cleaned[Brand],C$1,tbl_Cleaned[Account_Name],$A3) -> 22377901 | D3: =SUMIFS(tbl_Cleaned[Clean_Amount],tbl_Cleaned[Brand],D$1,tbl_Cleaned[Account_Name],$A3) -> 0 | E3: =SUM(B3:D3) -> 36305901
A4: Logistics Contract Revenue | B4: =SUMIFS(tbl_Cleaned[Clean_Amount],tbl_Cleaned[Brand],B$1,tbl_Cleaned[Account_Name],$A4) -> 0 | C4: =SUMIFS(tbl_Cleaned[Clean_Amount],tbl_Cleaned[Brand],C$1,tbl_Cleaned[Account_Name],$A4) -> 0 | D4: =SUMIFS(tbl_Cleaned[Clean_Amount],tbl_Cleaned[Brand],D$1,tbl_Cleaned[Account_Name],$A4) -> 16728931 | E4: =SUM(B4:D4) -> 16728931
A5: Refunds & Chargebacks | B5: =SUMIFS(tbl_Cleaned[Clean_Amount],tbl_Cleaned[Brand],B$1,tbl_Cleaned[Account_Name],$A5) -> -847608 | C5: =SUMIFS(tbl_Cleaned[Clean_Amount],tbl_Cleaned[Brand],C$1,tbl_Cleaned[Account_Name],$A5) -> -2114845 | D5: =SUMIFS(tbl_Cleaned[Clean_Amount],tbl_Cleaned[Brand],D$1,tbl_Cleaned[Account_Name],$A5) -> 0 | E5: =SUM(B5:D5) -> -2962453
A6: NET REVENUE | B6: =SUM(B3:B5) -> 13080392 | C6: =SUM(C3:C5) -> 20263056 | D6: =SUM(D3:D5) -> 16728931 | E6: =SUM(B6:D6) -> 50072379
B7: =SUMIFS(tbl_Cleaned[Clean_Amount],tbl_Cleaned[Brand],B$1,tbl_Cleaned[Account_Name],$A7) -> 0 | C7: =SUMIFS(tbl_Cleaned[Clean_Amount],tbl_Cleaned[Brand],C$1,tbl_Cleaned[Account_Name],$A7) -> 0 | D7: =SUMIFS(tbl_Cleaned[Clean_Amount],tbl_Cleaned[Brand],D$1,tbl_Cleaned[Account_Name],$A7) -> 0 | E7: =SUM(B7:D7) -> 0
A8: COST OF GOODS SOLD | B8: =SUMIFS(tbl_Cleaned[Clean_Amount],tbl_Cleaned[Brand],B$1,tbl_Cleaned[Account_Name],$A8) -> 0 | C8: =SUMIFS(tbl_Cleaned[Clean_Amount],tbl_Cleaned[Brand],C$1,tbl_Cleaned[Account_Name],$A8) -> 0 | D8: =SUMIFS(tbl_Cleaned[Clean_Amount],tbl_Cleaned[Brand],D$1,tbl_Cleaned[Account_Name],$A8) -> 0 | E8: =SUM(B8:D8) -> 0
A9: Food Cost | B9: =SUMIFS(tbl_Cleaned[Clean_Amount],tbl_Cleaned[Brand],B$1,tbl_Cleaned[Account_Name],$A9) -> -13484000 | C9: =SUMIFS(tbl_Cleaned[Clean_Amount],tbl_Cleaned[Brand],C$1,tbl_Cleaned[Account_Name],$A9) -> 0 | D9: =SUMIFS(tbl_Cleaned[Clean_Amount],tbl_Cleaned[Brand],D$1,tbl_Cleaned[Account_Name],$A9) -> 0 | E9: =SUM(B9:D9) -> -13484000
A10: Inventory Purchases | B10: =SUMIFS(tbl_Cleaned[Clean_Amount],tbl_Cleaned[Brand],B$1,tbl_Cleaned[Account_Name],$A10) -> 0 | C10: =SUMIFS(tbl_Cleaned[Clean_Amount],tbl_Cleaned[Brand],C$1,tbl_Cleaned[Account_Name],$A10) -> -46579000 | D10: =SUMIFS(tbl_Cleaned[Clean_Amount],tbl_Cleaned[Brand],D$1,tbl_Cleaned[Account_Name],$A10) -> 0 | E10: =SUM(B10:D10) -> -46579000
A11: Rider Payouts | B11: =SUMIFS(tbl_Cleaned[Clean_Amount],tbl_Cleaned[Brand],B$1,tbl_Cleaned[Account_Name],$A11) -> -6517000 | C11: =SUMIFS(tbl_Cleaned[Clean_Amount],tbl_Cleaned[Brand],C$1,tbl_Cleaned[Account_Name],$A11) -> 0 | D11: =SUMIFS(tbl_Cleaned[Clean_Amount],tbl_Cleaned[Brand],D$1,tbl_Cleaned[Account_Name],$A11) -> -7986000 | E11: =SUM(B11:D11) -> -14503000
A12: Aggregator Commission | B12: =SUMIFS(tbl_Cleaned[Clean_Amount],tbl_Cleaned[Brand],B$1,tbl_Cleaned[Account_Name],$A12) -> -3916000 | C12: =SUMIFS(tbl_Cleaned[Clean_Amount],tbl_Cleaned[Brand],C$1,tbl_Cleaned[Account_Name],$A12) -> 0 | D12: =SUMIFS(tbl_Cleaned[Clean_Amount],tbl_Cleaned[Brand],D$1,tbl_Cleaned[Account_Name],$A12) -> 0 | E12: =SUM(B12:D12) -> -3916000
A13: Fuel & Vehicle | B13: =SUMIFS(tbl_Cleaned[Clean_Amount],tbl_Cleaned[Brand],B$1,tbl_Cleaned[Account_Name],$A13) -> 0 | C13: =SUMIFS(tbl_Cleaned[Clean_Amount],tbl_Cleaned[Brand],C$1,tbl_Cleaned[Account_Name],$A13) -> 0 | D13: =SUMIFS(tbl_Cleaned[Clean_Amount],tbl_Cleaned[Brand],D$1,tbl_Cleaned[Account_Name],$A13) -> -15233000 | E13: =SUM(B13:D13) -> -15233000
A14: Packaging | B14: =SUMIFS(tbl_Cleaned[Clean_Amount],tbl_Cleaned[Brand],B$1,tbl_Cleaned[Account_Name],$A14) -> -1527000 | C14: =SUMIFS(tbl_Cleaned[Clean_Amount],tbl_Cleaned[Brand],C$1,tbl_Cleaned[Account_Name],$A14) -> -1184000 | D14: =SUMIFS(tbl_Cleaned[Clean_Amount],tbl_Cleaned[Brand],D$1,tbl_Cleaned[Account_Name],$A14) -> 0 | E14: =SUM(B14:D14) -> -2711000
A15: TOTAL COGS | B15: =SUM(B9:B14) -> -25444000 | C15: =SUM(C9:C14) -> -47763000 | D15: =SUM(D9:D14) -> -23219000 | E15: =SUM(B15:D15) -> -96426000
E16: =SUM(B16:D16) -> 0
A17: GROSS PROFIT | B17: =B6+B15 -> -12363608 | C17: =C6+C15 -> -27499944 | D17: =D6+D15 -> -6490068.9 | E17: =SUM(B17:D17) -> -46353621
E18: =SUM(B18:D18) -> 0
A19: OPERATING EXPENSES | B19: =SUMIFS(tbl_Cleaned[Clean_Amount],tbl_Cleaned[Brand],B$1,tbl_Cleaned[Account_Name],$A19) -> 0 | E19: =SUM(B19:D19) -> 0
A20: Salaries & Wages | B20: =SUMIFS(tbl_Cleaned[Clean_Amount],tbl_Cleaned[Brand],B$1,tbl_Cleaned[Account_Name],$A20) -> -9715824 | C20: =SUMIFS(tbl_Cleaned[Clean_Amount],tbl_Cleaned[Brand],C$1,tbl_Cleaned[Account_Name],$A20) -> -12448400 | D20: =SUMIFS(tbl_Cleaned[Clean_Amount],tbl_Cleaned[Brand],D$1,tbl_Cleaned[Account_Name],$A20) -> -8737727 | E20: =SUM(B20:D20) -> -30901951
A21: Rent | B21: =SUMIFS(tbl_Cleaned[Clean_Amount],tbl_Cleaned[Brand],B$1,tbl_Cleaned[Account_Name],$A21) -> -2160000 | C21: =SUMIFS(tbl_Cleaned[Clean_Amount],tbl_Cleaned[Brand],C$1,tbl_Cleaned[Account_Name],$A21) -> -4200000 | D21: =SUMIFS(tbl_Cleaned[Clean_Amount],tbl_Cleaned[Brand],D$1,tbl_Cleaned[Account_Name],$A21) -> -1140000 | E21: =SUM(B21:D21) -> -7500000
A22: Marketing | B22: =SUMIFS(tbl_Cleaned[Clean_Amount],tbl_Cleaned[Brand],B$1,tbl_Cleaned[Account_Name],$A22) -> -3959948.1 | C22: =SUMIFS(tbl_Cleaned[Clean_Amount],tbl_Cleaned[Brand],C$1,tbl_Cleaned[Account_Name],$A22) -> -1804621 | D22: =SUMIFS(tbl_Cleaned[Clean_Amount],tbl_Cleaned[Brand],D$1,tbl_Cleaned[Account_Name],$A22) -> 0 | E22: =SUM(B22:D22) -> -5764569.1
A23: Bank & Payment Fees | B23: =SUMIFS(tbl_Cleaned[Clean_Amount],tbl_Cleaned[Brand],B$1,tbl_Cleaned[Account_Name],$A23) -> -281912 | C23: =SUMIFS(tbl_Cleaned[Clean_Amount],tbl_Cleaned[Brand],C$1,tbl_Cleaned[Account_Name],$A23) -> -518064 | D23: =SUMIFS(tbl_Cleaned[Clean_Amount],tbl_Cleaned[Brand],D$1,tbl_Cleaned[Account_Name],$A23) -> -267950 | E23: =SUM(B23:D23) -> -1067926
A24: Software & Tools | B24: =SUMIFS(tbl_Cleaned[Clean_Amount],tbl_Cleaned[Brand],B$1,tbl_Cleaned[Account_Name],$A24) -> -3864660 | C24: =SUMIFS(tbl_Cleaned[Clean_Amount],tbl_Cleaned[Brand],C$1,tbl_Cleaned[Account_Name],$A24) -> 0 | D24: =SUMIFS(tbl_Cleaned[Clean_Amount],tbl_Cleaned[Brand],D$1,tbl_Cleaned[Account_Name],$A24) -> 0 | E24: =SUM(B24:D24) -> -3864660
A25: Professional Services | B25: =SUMIFS(tbl_Cleaned[Clean_Amount],tbl_Cleaned[Brand],B$1,tbl_Cleaned[Account_Name],$A25) -> 0 | C25: =SUMIFS(tbl_Cleaned[Clean_Amount],tbl_Cleaned[Brand],C$1,tbl_Cleaned[Account_Name],$A25) -> -1050000 | D25: =SUMIFS(tbl_Cleaned[Clean_Amount],tbl_Cleaned[Brand],D$1,tbl_Cleaned[Account_Name],$A25) -> 0 | E25: =SUM(B25:D25) -> -1050000
A26: Utilities | B26: =SUMIFS(tbl_Cleaned[Clean_Amount],tbl_Cleaned[Brand],B$1,tbl_Cleaned[Account_Name],$A26) -> -533105 | C26: =SUMIFS(tbl_Cleaned[Clean_Amount],tbl_Cleaned[Brand],C$1,tbl_Cleaned[Account_Name],$A26) -> -1205409 | D26: =SUMIFS(tbl_Cleaned[Clean_Amount],tbl_Cleaned[Brand],D$1,tbl_Cleaned[Account_Name],$A26) -> -541742 | E26: =SUM(B26:D26) -> -2280256
A27: TOTAL OPEX | B27: =SUM(B20:B26) -> -20515449 | C27: =SUM(C20:C26) -> -21226494 | D27: =SUM(D20:D26) -> -10687419 | E27: =SUM(B27:D27) -> -52429362
E28: =SUM(B28:D28) -> 0
A29: NET PROFIT | B29: =B17+B27 -> -32879057 | C29: =C17+C27 -> -48726438 | D29: =D17+D27 -> -17177488 | E29: =SUM(B29:D29) -> -98782983

Sheet Reconciliation
A1: Account | B1: Bank Statement Total (NGN) | C1: P&L Ledger Total (NGN) | D1: Difference | E1: Status
A2: GTB - NGN Operating (Inflow) | B2: =SUMIFS(tbl_Bank[Total_Inflow],tbl_Bank[Currency],"NGN") -> 427230000 | C2: =SUMIF(tbl_Cleaned[PL_Bucket],"Revenue",tbl_Cleaned[Clean_Amount]) -> 50072379 | D2: =B2-C2 -> 377157621 | E2: =IF(D3=0,"✅ MATCH",IF(ABS(D3)=1840000,"⚠️ Explained — duplicate vendor pmt excluded","❌ INVESTIGATE")) -> ❌ INVESTIGATE
A3: GTB - NGN Operating (Outflow) | B3: =SUMIFS(tbl_Bank[Total_Outflow],tbl_Bank[Currency],"NGN") -> -314370000 | C3: =SUMIF(tbl_Cleaned[PL_Bucket],"COGS",tbl_Cleaned[Clean_Amount])+SUMIF(tbl_Cleaned[PL_Bucket],"Opex",tbl_Cleaned[Clean_Amount]) -> -1.4885536e+08 | D3: =B3-C3 -> -1.6551464e+08 | E3: =IF(D3=0,"✅ MATCH",IF(ABS(D3)=1840000,"⚠️ Explained — duplicate vendor pmt excluded","❌ INVESTIGATE")) -> ❌ INVESTIGATE
A4: GTB - USD Domiciliary (Inflow) | B4: =(14820*1530)+(16320*1572)+(18940*1611) -> 78841980 | C4: =SUMIFS(tbl_Bank[Total_Inflow],tbl_Bank[Currency],"USD")*1571 -> 78675680 | D4: =B4-C4 -> 166300 | E4: =IF(D4=0,"✅ MATCH",IF(ABS(D4)=1840000,"⚠️ Explained — duplicate vendor pmt excluded","❌ INVESTIGATE")) -> ❌ INVESTIGATE
A5: GTB - USD Domiciliary (Outflow) | B5: =-((1460*1530)+(1640*1572)+(1710*1611)) -> -7566690 | C5: =-((1460*1530)+(1640*1572)+(1710*1611)) -> -7566690 | D5: =B5-C5 -> 0 | E5: =IF(D5=0,"✅ MATCH",IF(ABS(D5)=1840000,"⚠️ Explained — duplicate vendor pmt excluded","❌ INVESTIGATE")) -> ✅ MATCH
A6: GTB - GHS Account (Inflow) | B6: =SUMIFS(tbl_Bank[Total_Inflow],tbl_Bank[Currency],"GHS")*104 -> 0 | D6: =B6-C6 -> 0 | E6: =IF(D6=0,"✅ MATCH",IF(ABS(D6)=1840000,"⚠️ Explained — duplicate vendor pmt excluded","❌ INVESTIGATE")) -> ✅ MATCH
A7: GTB - GHS Account (Outflow) | B7: =SUMIFS(tbl_Bank[Total_Outflow],tbl_Bank[Currency],"GHS")*104 -> 0 | D7: =B7-C7 -> 0 | E7: =IF(D7=0,"✅ MATCH",IF(ABS(D7)=1840000,"⚠️ Explained — duplicate vendor pmt excluded","❌ INVESTIGATE")) -> ✅ MATCH
A8: NET TOTAL | B8: =SUM(B2:B7) -> 184135290 | C8: =SUM(C2:C7) -> -27673993 | D8: =B8-C8 -> 2.1180928e+08 | E8: =IF(D8=0,"✅ MATCH","⚠️ Gap explained, bank includes non-trading cash flows excluded from P&L") -> ⚠️ Gap explained, bank includes non-trading cash flows excluded from P&L
A10: Note: Bank vs Ledger g ap explained by: (1) Bank records gross cash flows while P&L shows net trading activity only. (2) ₦1,840,000 duplicate Distell vendor payment confirmed in August bank notes, excluded from P&L. (3) Non-trading flows (VAT, transfers) not captured in P&L.

Sheet CEO_Summary
B1: ZUMI HOLDINGS — Q3 2025 FINANCIAL SUMMARY
B2: Prepared by: Elizabeth Ese Williams | Date: May 09, 2025 | Currency: NGN
A4: KEY FINDINGS
A5: Did Zumi Holdings make money in Q3? NO. All three brands operated at a loss.
A7: PROFIT & LOSS SUMMARY
B8: Zumi Eats | C8: Zumi Mart | D8: Zumi Logistics | E8: TOTAL
A9: Net Revenue | B9: =PL_By_Brand_Month!B6 -> 13080392 | C9: =PL_By_Brand_Month!C6 -> 20263056 | D9: =PL_By_Brand_Month!D6 -> 16728931 | E9: =PL_By_Brand_Month!E6 -> 50072379
A10: Total COGS | B10: =PL_By_Brand_Month!B15 -> -25444000 | C10: =PL_By_Brand_Month!C15 -> -47763000 | D10: =PL_By_Brand_Month!D15 -> -23219000 | E10: =PL_By_Brand_Month!E15 -> -96426000
A11: Gross Profit | B11: =PL_By_Brand_Month!B17 -> -12363608 | C11: =PL_By_Brand_Month!C17 -> -27499944 | D11: =PL_By_Brand_Month!D17 -> -6490068.9 | E11: =PL_By_Brand_Month!E17 -> -46353621
A12: Total OpEx | B12: =PL_By_Brand_Month!B27 -> -20515449 | C12: =PL_By_Brand_Month!C27 -> -21226494 | D12: =PL_By_Brand_Month!D27 -> -10687419 | E12: =PL_By_Brand_Month!E27 -> -52429362
A13: NET PROFIT | B13: =PL_By_Brand_Month!B29 -> -32879057 | C13: =PL_By_Brand_Month!C29 -> -48726438 | D13: =PL_By_Brand_Month!D29 -> -17177488 | E13: =PL_By_Brand_Month!E29 -> -98782983
A15: DATA QUALITY ISSUES FOUND
A16: Issue | B16: Amount (NGN) | C16: Action Taken
A17: Duplicate vendor invoice — Distell Wholesale | B17: =Issues_Log!E2 -> -1840000 | C17: Excluded from P&L
A18: Duplicate payroll entry — Bento Africa | B18: =Issues_Log!E3 -> -680000 | C18: Excluded from P&L
A19: Salary misclassified — Rider supervisor | B19: =Issues_Log!E4 -> -540000 | C19: Reclassified to Zumi Logistics
A20: Uncategorized cash withdrawal | B20: =Issues_Log!E5 -> -180000 | C20: Parked CEO must explain
A21: Missing transaction date — Fuel invoice | B21: =Issues_Log!E6 -> -240000 | C21: Excluded — cannot assign to month
A22: Refunds booked as positive | B22: =Issues_Log!E7 -> -2962453 | C22: Fixed in Clean_Amount formula
A23: Total Financial Impact of Issues Found | B23: =SUM(B17:B22) -> -6442453
A25: RECOMMENDATION
A26: Zumi Holdings lost ₦98.8M in Q3 2025. All three brands are unprofitable. Zumi Mart is the largest loss-maker, inventory costs exceed revenue by 2.4x. Zumi Eats carries the highest OpEx burden at ₦20.5M. Zumi Logistics is closest to breakeven with the strongest revenue base. Data quality issues totalling ₦6,442,453 were identified and corrected and finance team must implement duplicate payment controls immediately before Q4 closes.
